Workbook

Sheet Summary
A1: BU 2027 | B1: Описание: сводный P&L AdTech 2027 по месяцам и за год vs FC 2026, млн ₽. Логика: ссылки на «P&L 2027» | S1: Bridge to strategy | U1: Описание: сверка BU 2027 со стратегией. | X1: CONS BU 2027 | Y1: Описание: вид для консолидации. Логика: E-comm / Offline = прирост выручки 2027 к FC 2026 (кол. DIFF); расходы - BU 2027 | AB1: CONS STR 2027 | AE1: Описание: сверка BU 2027 с консолидационной формой в стратегии
A2: Статья | B2: янв | C2: фев | D2: мар | E2: апр | F2: май | G2: июн | H2: июл | I2: авг | J2: сен | K2: окт | L2: ноя | M2: дек | N2: 2027 BU | O2: 2026 FC | P2: DIFF | Q2: YoY | S2: Strategy 2027 | T2: DIFF | U2: % | X2: Статья | Y2: 2027 BU | AB2: Статья | AC2: 2027 STR | AD2: DIFF | AE2: %
A3: APP | B3: ='P&L 2027'!B5 -> 153.92468 | C3: ='P&L 2027'!C5 -> 384.81171 | D3: ='P&L 2027'!D5 -> 538.73639 | E3: ='P&L 2027'!E5 -> 538.73639 | F3: ='P&L 2027'!F5 -> 538.73639 | G3: ='P&L 2027'!G5 -> 538.73639 | H3: ='P&L 2027'!H5 -> 538.73639 | I3: ='P&L 2027'!I5 -> 615.69874 | ... O3: ='P&L 2027'!O5 -> 6195.4 | P3: =N3-O3 -> 1500.8342 | Q3: =(N3/O3)-1 -> 0.24224977 | S3: 7250.8 | T3: =N3-S3 -> 445.4342 | U3: =T3/S3 -> 0.061432421 | X3: E-comm | Y3: =SUM(P3) -> 1500.8342 | AB3: E-comm | AC3: =1012275179.86692/10^6 -> 1012.2752 | AD3: =Y3-AC3 -> 488.55902 | AE3: =AD3/AC3 -> 0.48263459
A4: E-commerce | B4: ='P&L 2027'!B6 -> 153.92468 | C4: ='P&L 2027'!C6 -> 384.81171 | D4: ='P&L 2027'!D6 -> 538.73639 | E4: ='P&L 2027'!E6 -> 538.73639 | F4: ='P&L 2027'!F6 -> 538.73639 | G4: ='P&L 2027'!G6 -> 538.73639 | H4: ='P&L 2027'!H6 -> 538.73639 | I4: ='P&L 2027'!I6 -> 615.69874 | ... O4: ='P&L 2027'!O6 -> 6195.4 | P4: =N4-O4 -> 1500.8342
A5: Online DMP | B5: ='P&L 2027'!B11 -> 32 | C5: ='P&L 2027'!C11 -> 80 | D5: ='P&L 2027'!D11 -> 112 | E5: ='P&L 2027'!E11 -> 112 | F5: ='P&L 2027'!F11 -> 112 | G5: ='P&L 2027'!G11 -> 112 | H5: ='P&L 2027'!H11 -> 112 | I5: ='P&L 2027'!I11 -> 128 | ... O5: ='P&L 2027'!O11 -> 987 | P5: =N5-O5 -> 613 | Q5: =(N5/O5)-1 -> 0.62107396 | S5: 1063.4449 | T5: =N5-S5 -> 536.55515 | U5: =T5/S5 -> 0.5045444 | X5: Offline | Y5: =SUM(P5,P10,P12,P18,P20) -> 2741.9517 | AB5: Offline | AC5: =1792170775.52776/10^6+675 -> 2467.1708 | AD5: =Y5-AC5 -> 274.7809 | AE5: =AD5/AC5 -> 0.1113749
A6: МК | B6: ='P&L 2027'!B12 -> 24.92632 | C6: ='P&L 2027'!C12 -> 62.3158 | D6: ='P&L 2027'!D12 -> 87.24212 | E6: ='P&L 2027'!E12 -> 87.24212 | F6: ='P&L 2027'!F12 -> 87.24212 | G6: ='P&L 2027'!G12 -> 87.24212 | H6: ='P&L 2027'!H12 -> 87.24212 | I6: ='P&L 2027'!I12 -> 99.70528 | ... O6: ='P&L 2027'!O12 -> 768.82118 | P6: =N6-O6 -> 477.49482
A7: ММ | B7: ='P&L 2027'!B13 -> 6.2505901 | C7: ='P&L 2027'!C13 -> 15.626475 | D7: ='P&L 2027'!D13 -> 21.877065 | E7: ='P&L 2027'!E13 -> 21.877065 | F7: ='P&L 2027'!F13 -> 21.877065 | G7: ='P&L 2027'!G13 -> 21.877065 | H7: ='P&L 2027'!H13 -> 21.877065 | I7: ='P&L 2027'!I13 -> 25.002361 | ... O7: ='P&L 2027'!O13 -> 192.79164 | P7: =N7-O7 -> 119.73787
A8: МЭ | B8: ='P&L 2027'!B14 -> 0.61413761 | C8: ='P&L 2027'!C14 -> 1.535344 | D8: ='P&L 2027'!D14 -> 2.1494816 | E8: ='P&L 2027'!E14 -> 2.1494816 | F8: ='P&L 2027'!F14 -> 2.1494816 | G8: ='P&L 2027'!G14 -> 2.1494816 | H8: ='P&L 2027'!H14 -> 2.1494816 | I8: ='P&L 2027'!I14 -> 2.4565504 | ... O8: ='P&L 2027'!O14 -> 18.942307 | P8: =N8-O8 -> 11.764574
A9: МС | B9: ='P&L 2027'!B15 -> 0.20895231 | C9: ='P&L 2027'!C15 -> 0.52238079 | D9: ='P&L 2027'!D15 -> 0.7313331 | E9: ='P&L 2027'!E15 -> 0.7313331 | F9: ='P&L 2027'!F15 -> 0.7313331 | G9: ='P&L 2027'!G15 -> 0.7313331 | H9: ='P&L 2027'!H15 -> 0.7313331 | I9: ='P&L 2027'!I15 -> 0.83580926 | ... O9: ='P&L 2027'!O15 -> 6.444873 | P9: =N9-O9 -> 4.0027428
A10: DMP | B10: ='P&L 2027'!B9 -> 3.74 | C10: ='P&L 2027'!C9 -> 9.35 | D10: ='P&L 2027'!D9 -> 13.09 | E10: ='P&L 2027'!E9 -> 13.09 | F10: ='P&L 2027'!F9 -> 13.09 | G10: ='P&L 2027'!G9 -> 13.09 | H10: ='P&L 2027'!H9 -> 13.09 | I10: ='P&L 2027'!I9 -> 14.96 | ... O10: ='P&L 2027'!O9 -> 102.4 | P10: =N10-O10 -> 84.6 | Q10: =(N10/O10)-1 -> 0.82617188 | S10: 124.68 | T10: =N10-S10 -> 62.32 | U10: =T10/S10 -> 0.49983959
A11: Без формата | B11: ='P&L 2027'!B10 -> 3.74 | C11: ='P&L 2027'!C10 -> 9.35 | D11: ='P&L 2027'!D10 -> 13.09 | E11: ='P&L 2027'!E10 -> 13.09 | F11: ='P&L 2027'!F10 -> 13.09 | G11: ='P&L 2027'!G10 -> 13.09 | H11: ='P&L 2027'!H10 -> 13.09 | I11: ='P&L 2027'!I10 -> 14.96 | ... O11: ='P&L 2027'!O10 -> 102.4 | P11: =N11-O11 -> 84.6
A12: Instore digital | B12: ='P&L 2027'!B16 -> 80.390907 | C12: ='P&L 2027'!C16 -> 200.98173 | D12: ='P&L 2027'!D16 -> 281.36817 | E12: ='P&L 2027'!E16 -> 281.35478 | F12: ='P&L 2027'!F16 -> 281.36817 | G12: ='P&L 2027'!G16 -> 281.36817 | H12: ='P&L 2027'!H16 -> 281.36817 | I12: ='P&L 2027'!I16 -> 321.5413 | ... O12: ='P&L 2027'!O16 -> 2446.0892 | P12: =N12-O12 -> 1573.4025 | Q12: =(N12/O12)-1 -> 0.64323186 | S12: 4509.1703 | T12: =N12-S12 -> -489.67856 | U12: =T12/S12 -> -0.10859615
A13: ММ | B13: ='P&L 2027'!B17 -> 54.868947 | C13: ='P&L 2027'!C17 -> 137.17542 | D13: ='P&L 2027'!D17 -> 192.04132 | E13: ='P&L 2027'!E17 -> 192.03217 | F13: ='P&L 2027'!F17 -> 192.04132 | G13: ='P&L 2027'!G17 -> 192.04132 | H13: ='P&L 2027'!H17 -> 192.04132 | I13: ='P&L 2027'!I17 -> 219.46055 | ... O13: ='P&L 2027'!O17 -> 1669.5214 | P13: =N13-O13 -> 1073.8894
A14: МЭ | B14: ='P&L 2027'!B18 -> 10.543305 | C14: ='P&L 2027'!C18 -> 26.358849 | D14: ='P&L 2027'!D18 -> 36.901569 | E14: ='P&L 2027'!E18 -> 36.899812 | F14: ='P&L 2027'!F18 -> 36.901569 | G14: ='P&L 2027'!G18 -> 36.901569 | H14: ='P&L 2027'!H18 -> 36.901569 | I14: ='P&L 2027'!I18 -> 42.170293 | ... O14: ='P&L 2027'!O18 -> 320.80576 | P14: =N14-O14 -> 206.35248
A15: МС | B15: ='P&L 2027'!B19 -> 4.7716856 | C15: ='P&L 2027'!C19 -> 11.929479 | D15: ='P&L 2027'!D19 -> 16.7009 | E15: ='P&L 2027'!E19 -> 16.700104 | F15: ='P&L 2027'!F19 -> 16.7009 | G15: ='P&L 2027'!G19 -> 16.7009 | H15: ='P&L 2027'!H19 -> 16.7009 | I15: ='P&L 2027'!I19 -> 19.085417 | ... O15: ='P&L 2027'!O19 -> 145.19016 | P15: =N15-O15 -> 93.390937
A16: МК | B16: ='P&L 2027'!B20 -> 7.8696434 | C16: ='P&L 2027'!C20 -> 19.674546 | D16: ='P&L 2027'!D20 -> 27.543752 | E16: ='P&L 2027'!E20 -> 27.54244 | F16: ='P&L 2027'!F20 -> 27.543752 | G16: ='P&L 2027'!G20 -> 27.543752 | H16: ='P&L 2027'!H20 -> 27.543752 | I16: ='P&L 2027'!I20 -> 31.476387 | ... O16: ='P&L 2027'!O20 -> 239.45308 | P16: =N16-O16 -> 154.02385
A17: МС Лайт | B17: ='P&L 2027'!B21 -> 2.3373256 | C17: ='P&L 2027'!C21 -> 5.8434438 | D17: ='P&L 2027'!D21 -> 8.1806395 | E17: ='P&L 2027'!E21 -> 8.1802499 | F17: ='P&L 2027'!F21 -> 8.1806395 | G17: ='P&L 2027'!G21 -> 8.1806395 | H17: ='P&L 2027'!H21 -> 8.1806395 | I17: ='P&L 2027'!I21 -> 9.348653 | ... O17: ='P&L 2027'!O21 -> 71.118826 | P17: =N17-O17 -> 45.745894
A18: Content factory отдельное ЮЛ | B18: ='P&L 2027'!B7 -> 4.266 | C18: ='P&L 2027'!C7 -> 10.665 | D18: ='P&L 2027'!D7 -> 14.931 | E18: ='P&L 2027'!E7 -> 14.931 | F18: ='P&L 2027'!F7 -> 14.931 | G18: ='P&L 2027'!G7 -> 14.931 | H18: ='P&L 2027'!H7 -> 14.931 | I18: ='P&L 2027'!I7 -> 17.064 | ... O18: ='P&L 2027'!O7 -> 0 | P18: =N18-O18 -> 213.3 | Q18: -
A19: Без формата | B19: ='P&L 2027'!B8 -> 4.266 | C19: ='P&L 2027'!C8 -> 10.665 | D19: ='P&L 2027'!D8 -> 14.931 | E19: ='P&L 2027'!E8 -> 14.931 | F19: ='P&L 2027'!F8 -> 14.931 | G19: ='P&L 2027'!G8 -> 14.931 | H19: ='P&L 2027'!H8 -> 14.931 | I19: ='P&L 2027'!I8 -> 17.064 | ... O19: ='P&L 2027'!O8 -> 0 | P19: =N19-O19 -> 213.3
A20: RMN (Brand budgets call) отдельное ЮЛ | B20: ='P&L 2027'!B22 -> 17.004183 | C20: ='P&L 2027'!C22 -> 42.510457 | D20: ='P&L 2027'!D22 -> 59.51464 | E20: ='P&L 2027'!E22 -> 59.51464 | F20: ='P&L 2027'!F22 -> 59.51464 | G20: ='P&L 2027'!G22 -> 59.51464 | H20: ='P&L 2027'!H22 -> 59.51464 | I20: ='P&L 2027'!I22 -> 68.016732 | ... O20: ='P&L 2027'!O22 -> 592.56 | P20: =N20-O20 -> 257.64914 | Q20: =(N20/O20)-1 -> 0.43480685 | S20: 0 | T20: =N20-S20 -> 850.20914
A21: Без формата | B21: ='P&L 2027'!B23 -> 17.004183 | C21: ='P&L 2027'!C23 -> 42.510457 | D21: ='P&L 2027'!D23 -> 59.51464 | E21: ='P&L 2027'!E23 -> 59.51464 | F21: ='P&L 2027'!F23 -> 59.51464 | G21: ='P&L 2027'!G23 -> 59.51464 | H21: ='P&L 2027'!H23 -> 59.51464 | I21: ='P&L 2027'!I23 -> 68.016732 | ... O21: ='P&L 2027'!O23 -> 592.56 | P21: =N21-O21 -> 257.64914
A22: Gross Revenue | B22: =SUM(B3,B5,B10,B12,B18,B20) -> 291.32577 | C22: =SUM(C3,C5,C10,C12,C18,C20) -> 728.3189 | D22: =SUM(D3,D5,D10,D12,D18,D20) -> 1019.6402 | E22: =SUM(E3,E5,E10,E12,E18,E20) -> 1019.6268 | F22: =SUM(F3,F5,F10,F12,F18,F20) -> 1019.6402 | G22: =SUM(G3,G5,G10,G12,G18,G20) -> 1019.6402 | H22: =SUM(H3,H5,H10,H12,H18,H20) -> 1019.6402 | I22: =SUM(I3,I5,I10,I12,I18,I20) -> 1165.2808 | ... O22: =SUM(O3,O5,O10,O12,O18,O20) -> 10323.449 | P22: =N22-O22 -> 4242.7859 | Q22: =(N22/O22)-1 -> 0.4109853 | S22: =SUM(S3:S20) -> 12948.095 | T22: =N22-S22 -> 1618.1399 | U22: =T22/S22 -> 0.12497127 | X22: Revenue increase YOY | Y22: =SUM(Y3:Y20) -> 4242.7859 | AB22: Revenue increase YOY | AC22: =AC3+AC5 -> 3479.446 | AD22: =Y22-AC22 -> 763.33991 | AE22: =AD22/AC22 -> 0.21938548
A23: COGS (расходы, привязанные к выручке) | B23: ='P&L 2027'!B28 -> -89.8693 | C23: ='P&L 2027'!C28 -> -125.27429 | D23: ='P&L 2027'!D28 -> -148.83773 | E23: ='P&L 2027'!E28 -> -152.62163 | F23: ='P&L 2027'!F28 -> -153.65103 | G23: ='P&L 2027'!G28 -> -154.55941 | H23: ='P&L 2027'!H28 -> -154.51273 | I23: ='P&L 2027'!I28 -> -164.49599 | ... O23: ='P&L 2027'!O28 -> -880.54 | P23: =N23-O23 -> -1090.526 | Q23: =(N23/O23)-1 -> 1.2384741 | S23: -1292.1891 | T23: =N23-S23 -> -678.87692 | U23: =T23/S23 -> 0.52536965 | X23: COGS | Y23: =N23 -> -1971.066 | AB23: COGS | AC23: =S23 -> -1292.1891 | AD23: =Y23-AC23 -> -678.87692 | AE23: =AD23/AC23 -> 0.52536965
A24: Net Revenue | B24: =B22+B23 -> 201.45647 | C24: =C22+C23 -> 603.04461 | D24: =D22+D23 -> 870.80248 | E24: =E22+E23 -> 867.00518 | F24: =F22+F23 -> 865.98918 | G24: =G22+G23 -> 865.0808 | H24: =H22+H23 -> 865.12748 | I24: =I22+I23 -> 1000.7848 | ... O24: =O22+O23 -> 9442.9092 | P24: =N24-O24 -> 3152.2599 | Q24: =(N24/O24)-1 -> 0.33382296 | S24: =S22+S23 -> 11655.906 | T24: =N24-S24 -> 939.26301 | U24: =T24/S24 -> 0.080582582 | X24: Net Revenue increase | Y24: =Y22+Y23 -> 2271.7199 | AB24: Net Revenue increase | AC24: =AC22+AC23 -> 2187.2569 | AD24: =Y24-AC24 -> 84.462989 | AE24: =AD24/AC24 -> 0.038615944
A25: PEX | B25: ='P&L 2027'!B37 -> -113.96405 | C25: ='P&L 2027'!C37 -> -116.10616 | D25: ='P&L 2027'!D37 -> -116.71057 | E25: ='P&L 2027'!E37 -> -118.66284 | F25: ='P&L 2027'!F37 -> -120.87805 | G25: ='P&L 2027'!G37 -> -117.8386 | H25: ='P&L 2027'!H37 -> -120.78408 | I25: ='P&L 2027'!I37 -> -102.88362 | ... O25: ='P&L 2027'!O37 -> -1120.0714 | P25: =N25-O25 -> -316.2915 | Q25: =(N25/O25)-1 -> 0.28238511 | S25: -1478.5147 | T25: =N25-S25 -> 42.151724 | U25: =T25/S25 -> -0.028509507 | X25: PEX | Y25: =N25 -> -1436.3629 | AB25: PEX | AC25: =S25 -> -1478.5147 | AD25: =Y25-AC25 -> 42.151724 | AE25: =AD25/AC25 -> -0.028509507
A26: Other PEX | B26: ='P&L 2027'!B48 -> -1.1561945 | C26: ='P&L 2027'!C48 -> -5.1511945 | D26: ='P&L 2027'!D48 -> -1.8032845 | E26: ='P&L 2027'!E48 -> -12.253285 | F26: ='P&L 2027'!F48 -> -1.6682845 | G26: ='P&L 2027'!G48 -> -1.6632845 | H26: ='P&L 2027'!H48 -> -7.8032845 | I26: ='P&L 2027'!I48 -> -2.0029545 | ... O26: ='P&L 2027'!O48 -> -32.7 | P26: =N26-O26 -> -7.5864319 | Q26: =(N26/O26)-1 -> 0.23200098 | S26: -26.209876 | T26: =N26-S26 -> -14.076556 | U26: =T26/S26 -> 0.5370707 | X26: Other PEX | Y26: =N26 -> -40.286432 | AB26: Other PEX | AC26: =S26 -> -26.209876 | AD26: =Y26-AC26 -> -14.076556 | AE26: =AD26/AC26 -> 0.5370707
A27: Marketing | B27: ='P&L 2027'!B53 -> -5.9676923 | C27: ='P&L 2027'!C53 -> -10.317692 | D27: ='P&L 2027'!D53 -> -9.5426923 | E27: ='P&L 2027'!E53 -> -7.9676923 | F27: ='P&L 2027'!F53 -> -6.1676923 | G27: ='P&L 2027'!G53 -> -7.3426923 | H27: ='P&L 2027'!H53 -> -10.308677 | I27: ='P&L 2027'!I53 -> -7.6586771 | ... O27: ='P&L 2027'!O53 -> -55.25 | P27: =N27-O27 -> -45.408216 | Q27: =(N27/O27)-1 -> 0.82186816 | S27: -37.5 | T27: =N27-S27 -> -63.158216 | U27: =T27/S27 -> 1.6842191 | X27: Marketing | Y27: =N27 -> -100.65822 | AB27: Marketing | AC27: =S27 -> -37.5 | AD27: =Y27-AC27 -> -63.158216 | AE27: =AD27/AC27 -> 1.6842191
A28: Other OPEX | B28: ='P&L 2027'!B64 -> -2.4452511 | C28: ='P&L 2027'!C64 -> -5.3256591 | D28: ='P&L 2027'!D64 -> -7.245879 | E28: ='P&L 2027'!E64 -> -7.2457852 | F28: ='P&L 2027'!F64 -> -7.245879 | G28: ='P&L 2027'!G64 -> -7.245879 | H28: ='P&L 2027'!H64 -> -7.245879 | I28: ='P&L 2027'!I64 -> -8.2058482 | ... O28: ='P&L 2027'!O64 -> -91.6 | P28: =N28-O28 -> -10.712182 | Q28: =(N28/O28)-1 -> 0.11694522 | S28: -98.201769 | T28: =N28-S28 -> -4.1104132 | U28: =T28/S28 -> 0.041856815 | X28: Other OPEX | Y28: =N28 -> -102.31218 | AB28: Other OPEX | AC28: =S28 -> -98.201769 | AD28: =Y28-AC28 -> -4.1104132 | AE28: =AD28/AC28 -> 0.041856815
A29: IT | B29: ='P&L 2027'!B55 -> -6.4490727 | C29: ='P&L 2027'!C55 -> -6.4490727 | D29: ='P&L 2027'!D55 -> -6.8490727 | E29: ='P&L 2027'!E55 -> -6.6490727 | F29: ='P&L 2027'!F55 -> -7.1490727 | G29: ='P&L 2027'!G55 -> -7.0995797 | H29: ='P&L 2027'!H55 -> -7.0420068 | I29: ='P&L 2027'!I55 -> -7.309943 | ... O29: ='P&L 2027'!O55 -> -58.6 | P29: =N29-O29 -> -33.500557 | Q29: =(N29/O29)-1 -> 0.57168186 | S29: -62.06 | T29: =N29-S29 -> -30.040557 | U29: =T29/S29 -> 0.48405667 | X29: IT | Y29: =N29 -> -92.100557 | AB29: IT | AC29: =S29 -> -62.06 | AD29: =Y29-AC29 -> -30.040557 | AE29: =AD29/AC29 -> 0.48405667
A30: OPEX | B30: =SUM(B25:B29) -> -129.98226 | C30: =SUM(C25:C29) -> -143.34978 | D30: =SUM(D25:D29) -> -142.1515 | E30: =SUM(E25:E29) -> -152.77868 | F30: =SUM(F25:F29) -> -143.10898 | G30: =SUM(G25:G29) -> -141.19004 | H30: =SUM(H25:H29) -> -153.18393 | I30: =SUM(I25:I29) -> -128.06104 | ... O30: =SUM(O25:O29) -> -1358.2214 | P30: =N30-O30 -> -413.49888 | Q30: =(N30/O30)-1 -> 0.30444143 | S30: =SUM(S25:S29) -> -1702.4863 | T30: =N30-S30 -> -69.234018 | U30: =T30/S30 -> 0.040666417 | W30: - | X30: OPEX | Y30: =SUM(Y25:Y29) -> -1771.7203 | AB30: OPEX | AC30: =SUM(AC25:AC29) -> -1702.4863 | AD30: =Y30-AC30 -> -69.234018 | AE30: =AD30/AC30 -> 0.040666417
A31: EBITDA | B31: =B30+B24 -> 71.474217 | C31: =C30+C24 -> 459.69482 | D31: =D30+D24 -> 728.65098 | E31: =E30+E24 -> 714.2265 | F31: =F30+F24 -> 722.8802 | G31: =G30+G24 -> 723.89076 | H31: =H30+H24 -> 711.94356 | I31: =I30+I24 -> 872.72373 | ... O31: =O30+O24 -> 8084.6878 | P31: =N31-O31 -> 2738.761 | Q31: =(N31/O31)-1 -> 0.33875903 | S31: =S30+S24 -> 9953.4198 | T31: =N31-S31 -> 870.02899 | U31: =T31/S31 -> 0.087410057 | X31: EBITDA | Y31: =Y24+Y30 -> 499.99955 | AB31: EBITDA | AC31: =AC30+AC24 -> 484.77058 | AD31: =Y31-AC31 -> 15.228971 | AE31: =AD31/AC31 -> 0.0314148
A32: Разработка рекламной платформы | B32: ='P&L 2027_AdvInventory'!B54 -> -42.458922 | C32: ='P&L 2027_AdvInventory'!C54 -> -43.04558 | D32: ='P&L 2027_AdvInventory'!D54 -> -44.505901 | E32: ='P&L 2027_AdvInventory'!E54 -> -44.369799 | F32: ='P&L 2027_AdvInventory'!F54 -> -44.528812 | G32: ='P&L 2027_AdvInventory'!G54 -> -44.182905 | H32: ='P&L 2027_AdvInventory'!H54 -> -47.108845 | I32: ='P&L 2027_AdvInventory'!I54 -> -46.623045 | ... O32: ='P&L 2027_AdvInventory'!O54 -> -447.2 | P32: =N32-O32 -> -93.833873 | Q32: =(N32/O32)-1 -> 0.2098253
A33: Проекты Digital Instore (оснащение ТТ) | B33: ='P&L 2027_AdvInventory'!B55 -> 0 | C33: ='P&L 2027_AdvInventory'!C55 -> 0 | D33: ='P&L 2027_AdvInventory'!D55 -> 0 | E33: ='P&L 2027_AdvInventory'!E55 -> -10.23056 | F33: ='P&L 2027_AdvInventory'!F55 -> -18.36096 | G33: ='P&L 2027_AdvInventory'!G55 -> -52.572558 | H33: ='P&L 2027_AdvInventory'!H55 -> -45.678337 | I33: ='P&L 2027_AdvInventory'!I55 -> -56.619953 | ... O33: ='P&L 2027_AdvInventory'!O55 -> -732.4 | P33: =N33-O33 -> 122.79413 | Q33: =(N33/O33)-1 -> -0.16765993
A34: CAPEX | B34: =SUM(B32:B33) -> -42.458922 | C34: =SUM(C32:C33) -> -43.04558 | D34: =SUM(D32:D33) -> -44.505901 | E34: =SUM(E32:E33) -> -54.600359 | F34: =SUM(F32:F33) -> -62.889772 | G34: =SUM(G32:G33) -> -96.755463 | H34: =SUM(H32:H33) -> -92.787183 | I34: =SUM(I32:I33) -> -103.243 | ... O34: =SUM(O32:O33) -> -1179.6 | P34: =N34-O34 -> 28.960258 | Q34: =(N34/O34)-1 -> -0.024550914 | S34: -1242.3503 | T34: =N34-S34 -> 91.71053 | U34: =T34/S34 -> -0.073820187 | X34: =A34 -> CAPEX | Y34: =N34 -> -1150.6397 | AB34: CAPEX | AC34: =S34 -> -1242.3503 | AD34: =Y34-AC34 -> 91.71053 | AE34: =AD34/AC34 -> -0.073820187
A35: FCF | B35: =B34+B31 -> 29.015294 | C35: =C34+C31 -> 416.64924 | D35: =D34+D31 -> 684.14508 | E35: =E34+E31 -> 659.62614 | F35: =F34+F31 -> 659.99043 | G35: =G34+G31 -> 627.1353 | H35: =H34+H31 -> 619.15637 | I35: =I34+I31 -> 769.48073 | ... O35: =O34+O31 -> 6905.0878 | P35: =N35-O35 -> 2767.7212 | Q35: =(N35/O35)-1 -> 0.40082347 | S35: =S34+S31 -> 8711.0695 | T35: =N35-S35 -> 961.73952 | U35: =T35/S35 -> 0.1104043 | X35: FCF | Y35: =Y31+Y34 -> -650.6402 | AB35: FCF | AC35: =AC34+AC31 -> -757.5797 | AD35: =Y35-AC35 -> 106.9395 | AE35: =AD35/AC35 -> -0.14115941
A37: Revenue М+ | B37: ='P&L 2027'!B73 -> 337.89281 | C37: ='P&L 2027'!C73 -> 365.73325 | D37: ='P&L 2027'!D73 -> 377.3919 | E37: ='P&L 2027'!E73 -> 394.58185 | F37: ='P&L 2027'!F73 -> 414.44746 | G37: ='P&L 2027'!G73 -> 435.07252 | H37: ='P&L 2027'!H73 -> 455.65159 | I37: ='P&L 2027'!I73 -> 478.67974 | ... O37: ='P&L 2027'!O73 -> 3007 | P37: =N37-O37 -> 2437.4019 | Q37: =(N37/O37)-1 -> 0.81057595 | AC37: =AC31-500 -> -15.229425
A40: Справочно экономия CAPEX ГК благодаря собственной разработке AdTech
N41: CAPEX adj. | O41: Add. OPEX | P41: Total saving
A42: Cubic | N42: -28.46873 | O42: 14.234365 | P42: =SUM(N42:O42) -> -14.234365
A43: InAppStory | N43: -7.3794 | O43: 0 | P43: =SUM(N43:O43) -> -7.3794
A44: Total | N44: =SUM(N42:N43) -> -35.84813 | O44: =SUM(O42:O43) -> 14.234365 | P44: =SUM(P42:P43) -> -21.613765

Sheet P&L 2027
A1: P&L AdTech 2027 - BOTTOM-UP | Q1: Описание: bottom-up P&L AdTech 2027 по месяцам, млн ₽ без НДС. Логика: выручка - из листов направлений (APP = Медиа + Перформанс, Content factory, DMP, In-store; RMN), логика по распределению на форматы см. на листе «RevSplit»; расходы - из листа «Расходы»
A2: Млн руб. без НДС.
B3: =B24/$N$24 -> 0.020000074 | C3: =C24/$N$24 -> 0.050000491 | D3: =D24/$N$24 -> 0.070000258 | E3: =E24/$N$24 -> 0.069999338 | F3: =F24/$N$24 -> 0.070000258 | G3: =G24/$N$24 -> 0.070000258 | H3: =H24/$N$24 -> 0.070000258 | I3: =I24/$N$24 -> 0.079998761 | ... N3: =N24/$N$24 -> 1
A4: Статья | B4: янв | C4: фев | D4: мар | E4: апр | F4: май | G4: июн | H4: июл | I4: авг | J4: сен | K4: окт | L4: ноя | M4: дек | N4: 2027 | O4: 2026
A5: APP | B5: =B6 -> 153.92468 | C5: =C6 -> 384.81171 | D5: =D6 -> 538.73639 | E5: =E6 -> 538.73639 | F5: =F6 -> 538.73639 | G5: =G6 -> 538.73639 | H5: =H6 -> 538.73639 | I5: =I6 -> 615.69874 | ... O5: =O6 -> 6195.4 | P5: =IFERROR(N5/O5-1,"") -> 0.24224977
A6: =RevSplit!W5 -> E-commerce | B6: =RevSplit!X5 -> 153.92468 | C6: =RevSplit!Y5 -> 384.81171 | D6: =RevSplit!Z5 -> 538.73639 | E6: =RevSplit!AA5 -> 538.73639 | F6: =RevSplit!AB5 -> 538.73639 | G6: =RevSplit!AC5 -> 538.73639 | H6: =RevSplit!AD5 -> 538.73639 | ... M6: =RevSplit!AI5 -> 1308.3598 | N6: =SUM(B6:M6) -> 7696.2342 | O6: =RevSplit!AK5 -> 6195.4
A7: Content factory | B7: =B8 -> 4.266 | C7: =C8 -> 10.665 | D7: =D8 -> 14.931 | E7: =E8 -> 14.931 | F7: =F8 -> 14.931 | G7: =G8 -> 14.931 | H7: =H8 -> 14.931 | I7: =I8 -> 17.064 | ... O7: =O8 -> 0 | P7: =IFERROR(N7/O7-1,"")
A8: Без формата | B8: =RevSplit!F6 -> 4.266 | C8: =RevSplit!G6 -> 10.665 | D8: =RevSplit!H6 -> 14.931 | E8: =RevSplit!I6 -> 14.931 | F8: =RevSplit!J6 -> 14.931 | G8: =RevSplit!K6 -> 14.931 | H8: =RevSplit!L6 -> 14.931 | I8: =RevSplit!M6 -> 17.064 | ... M8: =RevSplit!Q6 -> 36.261 | N8: =SUM(B8:M8) -> 213.3 | O8: =RevSplit!S6 -> 0
A9: DMP+ Analitycs | B9: =B10 -> 3.74 | C9: =C10 -> 9.35 | D9: =D10 -> 13.09 | E9: =E10 -> 13.09 | F9: =F10 -> 13.09 | G9: =G10 -> 13.09 | H9: =H10 -> 13.09 | I9: =I10 -> 14.96 | ... O9: =O10 -> 102.4 | P9: =IFERROR(N9/O9-1,"") -> 0.82617188
A10: Без формата | B10: =RevSplit!F7 -> 3.74 | C10: =RevSplit!G7 -> 9.35 | D10: =RevSplit!H7 -> 13.09 | E10: =RevSplit!I7 -> 13.09 | F10: =RevSplit!J7 -> 13.09 | G10: =RevSplit!K7 -> 13.09 | H10: =RevSplit!L7 -> 13.09 | I10: =RevSplit!M7 -> 14.96 | ... M10: =RevSplit!Q7 -> 31.79 | N10: =SUM(B10:M10) -> 187 | O10: =RevSplit!S7 -> 102.4
A11: DMP+Online | B11: =SUM(B12:B15) -> 32 | C11: =SUM(C12:C15) -> 80 | D11: =SUM(D12:D15) -> 112 | E11: =SUM(E12:E15) -> 112 | F11: =SUM(F12:F15) -> 112 | G11: =SUM(G12:G15) -> 112 | H11: =SUM(H12:H15) -> 112 | I11: =SUM(I12:I15) -> 128 | ... O11: =SUM(O12:O15) -> 987 | P11: =IFERROR(N11/O11-1,"") -> 0.62107396
A12: МК | B12: =RevSplit!F21 -> 24.92632 | C12: =RevSplit!G21 -> 62.3158 | D12: =RevSplit!H21 -> 87.24212 | E12: =RevSplit!I21 -> 87.24212 | F12: =RevSplit!J21 -> 87.24212 | G12: =RevSplit!K21 -> 87.24212 | H12: =RevSplit!L21 -> 87.24212 | I12: =RevSplit!M21 -> 99.70528 | ... M12: =RevSplit!Q21 -> 211.87372 | N12: =SUM(B12:M12) -> 1246.316 | O12: =RevSplit!S21 -> 768.82118
A13: ММ | B13: =RevSplit!F22 -> 6.2505901 | C13: =RevSplit!G22 -> 15.626475 | D13: =RevSplit!H22 -> 21.877065 | E13: =RevSplit!I22 -> 21.877065 | F13: =RevSplit!J22 -> 21.877065 | G13: =RevSplit!K22 -> 21.877065 | H13: =RevSplit!L22 -> 21.877065 | I13: =RevSplit!M22 -> 25.002361 | ... M13: =RevSplit!Q22 -> 53.130016 | N13: =SUM(B13:M13) -> 312.52951 | O13: =RevSplit!S22 -> 192.79164
A14: МЭ | B14: =RevSplit!F23 -> 0.61413761 | C14: =RevSplit!G23 -> 1.535344 | D14: =RevSplit!H23 -> 2.1494816 | E14: =RevSplit!I23 -> 2.1494816 | F14: =RevSplit!J23 -> 2.1494816 | G14: =RevSplit!K23 -> 2.1494816 | H14: =RevSplit!L23 -> 2.1494816 | I14: =RevSplit!M23 -> 2.4565504 | ... M14: =RevSplit!Q23 -> 5.2201697 | N14: =SUM(B14:M14) -> 30.706881 | O14: =RevSplit!S23 -> 18.942307
A15: МС | B15: =RevSplit!F24 -> 0.20895231 | C15: =RevSplit!G24 -> 0.52238079 | D15: =RevSplit!H24 -> 0.7313331 | E15: =RevSplit!I24 -> 0.7313331 | F15: =RevSplit!J24 -> 0.7313331 | G15: =RevSplit!K24 -> 0.7313331 | H15: =RevSplit!L24 -> 0.7313331 | I15: =RevSplit!M24 -> 0.83580926 | ... M15: =RevSplit!Q24 -> 1.7760947 | N15: =SUM(B15:M15) -> 10.447616 | O15: =RevSplit!S24 -> 6.444873
A16: Instore digital | B16: =SUM(B17:B21) -> 80.390907 | C16: =SUM(C17:C21) -> 200.98173 | D16: =SUM(D17:D21) -> 281.36817 | E16: =SUM(E17:E21) -> 281.35478 | F16: =SUM(F17:F21) -> 281.36817 | G16: =SUM(G17:G21) -> 281.36817 | H16: =SUM(H17:H21) -> 281.36817 | I16: =SUM(I17:I21) -> 321.5413 | ... O16: =SUM(O17:O21) -> 2446.0892 | P16: =IFERROR(N16/O16-1,"") -> 0.64323186
A17: ММ | B17: =RevSplit!F30 -> 54.868947 | C17: =RevSplit!G30 -> 137.17542 | D17: =RevSplit!H30 -> 192.04132 | E17: =RevSplit!I30 -> 192.03217 | F17: =RevSplit!J30 -> 192.04132 | G17: =RevSplit!K30 -> 192.04132 | H17: =RevSplit!L30 -> 192.04132 | I17: =RevSplit!M30 -> 219.46055 | ... M17: =RevSplit!Q30 -> 466.38605 | N17: =SUM(B17:M17) -> 2743.4108 | O17: =RevSplit!S30 -> 1669.5214
A18: МЭ | B18: =RevSplit!F31 -> 10.543305 | C18: =RevSplit!G31 -> 26.358849 | D18: =RevSplit!H31 -> 36.901569 | E18: =RevSplit!I31 -> 36.899812 | F18: =RevSplit!J31 -> 36.901569 | G18: =RevSplit!K31 -> 36.901569 | H18: =RevSplit!L31 -> 36.901569 | I18: =RevSplit!M31 -> 42.170293 | ... M18: =RevSplit!Q31 -> 89.618096 | N18: =SUM(B18:M18) -> 527.15824 | O18: =RevSplit!S31 -> 320.80576
A19: МС | B19: =RevSplit!F32 -> 4.7716856 | C19: =RevSplit!G32 -> 11.929479 | D19: =RevSplit!H32 -> 16.7009 | E19: =RevSplit!I32 -> 16.700104 | F19: =RevSplit!J32 -> 16.7009 | G19: =RevSplit!K32 -> 16.7009 | H19: =RevSplit!L32 -> 16.7009 | I19: =RevSplit!M32 -> 19.085417 | ... M19: =RevSplit!Q32 -> 40.559327 | N19: =SUM(B19:M19) -> 238.5811 | O19: =RevSplit!S32 -> 145.19016
A20: МК | B20: =RevSplit!F33 -> 7.8696434 | C20: =RevSplit!G33 -> 19.674546 | D20: =RevSplit!H33 -> 27.543752 | E20: =RevSplit!I33 -> 27.54244 | F20: =RevSplit!J33 -> 27.543752 | G20: =RevSplit!K33 -> 27.543752 | H20: =RevSplit!L33 -> 27.543752 | I20: =RevSplit!M33 -> 31.476387 | ... M20: =RevSplit!Q33 -> 66.891969 | N20: =SUM(B20:M20) -> 393.47692 | O20: =RevSplit!S33 -> 239.45308
A21: МС Лайт | B21: =RevSplit!F34 -> 2.3373256 | C21: =RevSplit!G34 -> 5.8434438 | D21: =RevSplit!H34 -> 8.1806395 | E21: =RevSplit!I34 -> 8.1802499 | F21: =RevSplit!J34 -> 8.1806395 | G21: =RevSplit!K34 -> 8.1806395 | H21: =RevSplit!L34 -> 8.1806395 | I21: =RevSplit!M34 -> 9.348653 | ... M21: =RevSplit!Q34 -> 19.867267 | N21: =SUM(B21:M21) -> 116.86472 | O21: =RevSplit!S34 -> 71.118826
A22: RMN (Brand budgets call) | B22: =B23 -> 17.004183 | C22: =C23 -> 42.510457 | D22: =D23 -> 59.51464 | E22: =E23 -> 59.51464 | F22: =F23 -> 59.51464 | G22: =G23 -> 59.51464 | H22: =H23 -> 59.51464 | I22: =I23 -> 68.016732 | ... O22: =O23 -> 592.56 | P22: =IFERROR(N22/O22-1,"") -> 0.43480685
A23: Без формата | B23: =RevSplit!F10 -> 17.004183 | C23: =RevSplit!G10 -> 42.510457 | D23: =RevSplit!H10 -> 59.51464 | E23: =RevSplit!I10 -> 59.51464 | F23: =RevSplit!J10 -> 59.51464 | G23: =RevSplit!K10 -> 59.51464 | H23: =RevSplit!L10 -> 59.51464 | I23: =RevSplit!M10 -> 68.016732 | ... M23: =RevSplit!Q10 -> 144.53555 | N23: =SUM(B23:M23) -> 850.20914 | O23: =RevSplit!S10 -> 592.56
A24: Gross Revenue | B24: =SUM(B5,B7,B9,B11,B16,B22) -> 291.32577 | C24: =SUM(C5,C7,C9,C11,C16,C22) -> 728.3189 | D24: =SUM(D5,D7,D9,D11,D16,D22) -> 1019.6402 | E24: =SUM(E5,E7,E9,E11,E16,E22) -> 1019.6268 | F24: =SUM(F5,F7,F9,F11,F16,F22) -> 1019.6402 | G24: =SUM(G5,G7,G9,G11,G16,G22) -> 1019.6402 | H24: =SUM(H5,H7,H9,H11,H16,H22) -> 1019.6402 | I24: =SUM(I5,I7,I9,I11,I16,I22) -> 1165.2808 | ... O24: =SUM(O5,O7,O9,O11,O16,O22) -> 10323.449
A25: Расходы на маркетинг в сети интернет | B25: =Расходы!C26 -> -19.3793 | C25: =Расходы!D26 -> -51.604294 | D25: =Расходы!E26 -> -68.277733 | E25: =Расходы!F26 -> -71.584631 | F25: =Расходы!G26 -> -72.296031 | G25: =Расходы!H26 -> -72.409411 | H25: =Расходы!I26 -> -72.362725 | I25: =Расходы!J26 -> -81.232995 | ... M25: =Расходы!N26 -> -163.80337 | N25: =SUM(B25:M25) -> -1000 | O25: =Расходы!P26 -> -510.54
A26: Вознаграждения креаторам | B26: =Расходы!C27 -> -4.24 | C26: =Расходы!D27 -> -7.42 | D26: =Расходы!E27 -> -14.31 | E26: =Расходы!F27 -> -14.787 | F26: =Расходы!G27 -> -15.105 | G26: =Расходы!H27 -> -15.9 | H26: =Расходы!I27 -> -15.9 | I26: =Расходы!J27 -> -17.013 | ... M26: =Расходы!N27 -> -19.08 | N26: =SUM(B26:M26) -> -176.066 | O26: -15.6
A27: Вознаграждения рекламным агентствам | B27: =Расходы!C28 -> -66.25 | C27: =Расходы!D28 -> -66.25 | D27: =Расходы!E28 -> -66.25 | E27: =Расходы!F28 -> -66.25 | F27: =Расходы!G28 -> -66.25 | G27: =Расходы!H28 -> -66.25 | H27: =Расходы!I28 -> -66.25 | I27: =Расходы!J28 -> -66.25 | ... M27: =Расходы!N28 -> -66.25 | N27: =SUM(B27:M27) -> -795 | O27: =Расходы!P28 -> -354.4
A28: COGS (расходы, привязанные к выручке) | B28: =SUM(B25:B27) -> -89.8693 | C28: =SUM(C25:C27) -> -125.27429 | D28: =SUM(D25:D27) -> -148.83773 | E28: =SUM(E25:E27) -> -152.62163 | F28: =SUM(F25:F27) -> -153.65103 | G28: =SUM(G25:G27) -> -154.55941 | H28: =SUM(H25:H27) -> -154.51273 | I28: =SUM(I25:I27) -> -164.49599 | ... M28: =SUM(M25:M27) -> -249.13337 | N28: =SUM(B28:M28) -> -1971.066 | O28: =SUM(O25:O27) -> -880.54
A29: Net Revenue | B29: =B24+B28 -> 201.45647 | C29: =C24+C28 -> 603.04461 | D29: =D24+D28 -> 870.80248 | E29: =E24+E28 -> 867.00518 | F29: =F24+F28 -> 865.98918 | G29: =G24+G28 -> 865.0808 | H29: =H24+H28 -> 865.12748 | I29: =I24+I28 -> 1000.7848 | ... M29: =M24+M28 -> 2227.1357 | N29: =SUM(B29:M29) -> 12595.169 | O29: =O24+O28 -> 9442.9092
A30: Налоги и взносы, связанные с расходами на оплату труда (ФОТ) | B30: =Расходы!C3 -> -20.502132 | C30: =Расходы!D3 -> -20.887499 | D30: =Расходы!E3 -> -20.996231 | E30: =Расходы!F3 -> -21.347445 | F30: =Расходы!G3 -> -21.745961 | G30: =Расходы!H3 -> -21.199164 | H30: =Расходы!I3 -> -21.729056 | I30: =Расходы!J3 -> -18.508763 | ... M30: =Расходы!N3 -> -23.873296 | N30: =SUM(B30:M30) -> -258.40169 | O30: =Расходы!P3 -> -201.50085
A31: Индексация | B31: =Расходы!C4 -> 0 | C31: =Расходы!D4 -> 0 | D31: =Расходы!E4 -> 0 | E31: =Расходы!F4 -> 0 | F31: =Расходы!G4 -> 0 | G31: =Расходы!H4 -> 0 | H31: =Расходы!I4 -> 0 | I31: =Расходы!J4 -> 0 | ... M31: =Расходы!N4 -> 0 | N31: =SUM(B31:M31) -> 0 | O31: =Расходы!P4 -> 0
A32: Оплата труда - постоянная часть | B32: =Расходы!C5 -> -71.250322 | C32: =Расходы!D5 -> -72.589574 | D32: =Расходы!E5 -> -72.967448 | E32: =Расходы!F5 -> -74.188009 | F32: =Расходы!G5 -> -75.572956 | G32: =Расходы!H5 -> -73.672694 | H32: =Расходы!I5 -> -75.514206 | I32: =Расходы!J5 -> -64.322839 | ... M32: =Расходы!N5 -> -82.966006 | N32: =SUM(B32:M32) -> -898.01411 | O32: =Расходы!P5 -> -700.26866
A33: Оплата труда - премии | B33: =Расходы!C6 -> -2.6895515 | C33: =Расходы!D6 -> -2.7401055 | D33: =Расходы!E6 -> -2.7543694 | E33: =Расходы!F6 -> -2.8004431 | F33: =Расходы!G6 -> -2.852722 | G33: =Расходы!H6 -> -2.780991 | H33: =Расходы!I6 -> -2.8505043 | I33: =Расходы!J6 -> -2.4280534 | ... M33: =Расходы!N6 -> -3.1317942 | N33: =SUM(B33:M33) -> -33.898165 | O33: =Расходы!P6 -> -26.433686
A34: Оплата труда - отпускные | B34: =Расходы!C7 -> -4.6155439 | C34: =Расходы!D7 -> -4.7022997 | D34: =Расходы!E7 -> -4.7267781 | E34: =Расходы!F7 -> -4.8058451 | F34: =Расходы!G7 -> -4.895561 | G34: =Расходы!H7 -> -4.7724634 | H34: =Расходы!I7 -> -4.8917552 | I34: =Расходы!J7 -> -4.1667866 | ... M34: =Расходы!N7 -> -5.3744774 | N34: =SUM(B34:M34) -> -58.172699 | O34: =Расходы!P7 -> -45.362893
A35: Начисление резерва STI 100%, годовой бонус | B35: =Расходы!C8 -> -11.555954 | C35: =Расходы!D8 -> -11.773165 | D35: =Расходы!E8 -> -11.834452 | E35: =Расходы!F8 -> -12.032412 | F35: =Расходы!G8 -> -12.257034 | G35: =Расходы!H8 -> -11.948834 | H35: =Расходы!I8 -> -12.247506 | I35: =Расходы!J8 -> -10.432399 | ... M35: =Расходы!N8 -> -13.456099 | N35: =SUM(B35:M35) -> -145.6472 | O35: =Расходы!P8 -> -113.57524
A36: Начисление резерва STI 100%, квартальные бонусы | B36: =Расходы!C9 -> -3.350543 | C36: =Расходы!D9 -> -3.4135212 | D36: =Расходы!E9 -> -3.4312907 | E36: =Расходы!F9 -> -3.4886876 | F36: =Расходы!G9 -> -3.5538146 | G36: =Расходы!H9 -> -3.4644549 | H36: =Расходы!I9 -> -3.5510519 | I36: =Расходы!J9 -> -3.0247784 | ... M36: =Расходы!N9 -> -3.9014725 | N36: =SUM(B36:M36) -> -42.22907 | O36: =Расходы!P9 -> -32.9301
A37: PEX | B37: =SUM(B30:B36) -> -113.96405 | C37: =SUM(C30:C36) -> -116.10616 | D37: =SUM(D30:D36) -> -116.71057 | E37: =SUM(E30:E36) -> -118.66284 | F37: =SUM(F30:F36) -> -120.87805 | G37: =SUM(G30:G36) -> -117.8386 | H37: =SUM(H30:H36) -> -120.78408 | I37: =SUM(I30:I36) -> -102.88362 | ... M37: =SUM(M30:M36) -> -132.70314 | N37: =SUM(B37:M37) -> -1436.3629 | O37: =SUM(O30:O36) -> -1120.0714
A38: Материальная помощь | B38: =Расходы!C11 -> -0.005 | C38: =Расходы!D11 -> 0 | D38: =Расходы!E11 -> -0.005 | E38: =Расходы!F11 -> -0.005 | F38: =Расходы!G11 -> -0.005 | G38: =Расходы!H11 -> 0 | H38: =Расходы!I11 -> -0.005 | I38: =Расходы!J11 -> 0 | ... M38: =Расходы!N11 -> -0.005 | N38: =SUM(B38:M38) -> -0.04 | O38: =Расходы!P11 -> -0.4
A39: Затраты на корп. мероприятие кроме проезда и проживания | B39: =Расходы!C12 -> -0.375 | C39: =Расходы!D12 -> -0.375 | D39: =Расходы!E12 -> -0.51 | E39: =Расходы!F12 -> -0.375 | F39: =Расходы!G12 -> -0.375 | G39: =Расходы!H12 -> -0.375 | H39: =Расходы!I12 -> -0.51 | I39: =Расходы!J12 -> -0.375 | ... M39: =Расходы!N12 -> -0.375 | N39: =SUM(B39:M39) -> -4.77 | O39: =Расходы!P12 -> -3
A40: ДМС и НС | B40: =Расходы!C13 -> -0.86919813 | C40: =Расходы!D13 -> -0.86919813 | D40: =Расходы!E13 -> -0.86919813 | E40: =Расходы!F13 -> -0.86919813 | F40: =Расходы!G13 -> -0.86919813 | G40: =Расходы!H13 -> -0.86919813 | H40: =Расходы!I13 -> -0.86919813 | I40: =Расходы!J13 -> -0.86919813 | ... M40: =Расходы!N13 -> -0.97250298 | N40: =SUM(B40:M40) -> -10.546904 | O40: =Расходы!P13 -> -6.5
A41: Подбор массовых позиций | B41: =Расходы!C14 -> 0 | C41: =Расходы!D14 -> 0 | D41: =Расходы!E14 -> 0 | E41: =Расходы!F14 -> 0 | F41: =Расходы!G14 -> 0 | G41: =Расходы!H14 -> 0 | H41: =Расходы!I14 -> 0 | I41: =Расходы!J14 -> 0 | ... M41: =Расходы!N14 -> 0 | N41: =SUM(B41:M41) -> 0 | O41: =Расходы!P14 -> -4.9
A42: Подбор офисных позиций | B42: =Расходы!C15 -> -0.037333 | C42: =Расходы!D15 -> -0.037333 | D42: =Расходы!E15 -> -0.037333 | E42: =Расходы!F15 -> -0.37233367 | F42: =Расходы!G15 -> -0.037333 | G42: =Расходы!H15 -> -0.037333 | H42: =Расходы!I15 -> -0.037333 | I42: =Расходы!J15 -> -0.377003 | ... M42: =Расходы!N15 -> -0.037333 | N42: =SUM(B42:M42) -> -1.1226667 | O42: =Расходы!P15 -> 0
A43: Расходы на внешнее обучение | B43: =Расходы!C16 -> 0 | C43: =Расходы!D16 -> 0 | D43: =Расходы!E16 -> -0.51209 | E43: =Расходы!F16 -> -0.51209 | F43: =Расходы!G16 -> -0.51209 | G43: =Расходы!H16 -> -0.51209 | H43: =Расходы!I16 -> -0.51209 | I43: =Расходы!J16 -> -0.51209 | ... M43: =Расходы!N16 -> -0.51209 | N43: =SUM(B43:M43) -> -5.1209 | O43: =Расходы!P16 -> -5.7
A44: Развитие HR бренда | B44: =Расходы!C17 -> 0 | C44: =Расходы!D17 -> -4 | D44: =Расходы!E17 -> 0 | E44: =Расходы!F17 -> -10.25 | F44: =Расходы!G17 -> 0 | G44: =Расходы!H17 -> 0 | H44: =Расходы!I17 -> -6 | I44: =Расходы!J17 -> 0 | ... M44: =Расходы!N17 -> 0 | N44: =SUM(B44:M44) -> -20.25 | O44: =Расходы!P17 -> -14
A45: Карты лояльности (мотивация сотрудников) | B45: =Расходы!C18 -> -0.02799675 | C45: =Расходы!D18 -> -0.02799675 | D45: =Расходы!E18 -> -0.02799675 | E45: =Расходы!F18 -> -0.02799675 | F45: =Расходы!G18 -> -0.02799675 | G45: =Расходы!H18 -> -0.02799675 | H45: =Расходы!I18 -> -0.02799675 | I45: =Расходы!J18 -> -0.02799675 | ... M45: =Расходы!N18 -> -0.02799675 | N45: =SUM(B45:M45) -> -0.335961 | O45: =Расходы!P18 -> 0
A46: Прочие компенсации и льготы | B46: =Расходы!C19 -> -0.041666667 | C46: =Расходы!D19 -> -0.041666667 | D46: =Расходы!E19 -> -0.041666667 | E46: =Расходы!F19 -> -0.041666667 | F46: =Расходы!G19 -> -0.041666667 | G46: =Расходы!H19 -> -0.041666667 | H46: =Расходы!I19 -> -0.041666667 | I46: =Расходы!J19 -> -0.041666667 | ... M46: =Расходы!N19 -> -0.041666667 | N46: =SUM(B46:M46) -> -0.5 | O46: =Расходы!P19 -> -1.2
A47: Резерв на оплату отпусков | B47: =Расходы!C20 -> 0.2 | C47: =Расходы!D20 -> 0.2 | D47: =Расходы!E20 -> 0.2 | E47: =Расходы!F20 -> 0.2 | F47: =Расходы!G20 -> 0.2 | G47: =Расходы!H20 -> 0.2 | H47: =Расходы!I20 -> 0.2 | I47: =Расходы!J20 -> 0.2 | ... M47: =Расходы!N20 -> 0.2 | N47: =SUM(B47:M47) -> 2.4 | O47: =Расходы!P20 -> 3
A48: Other PEX | B48: =SUM(B38:B47) -> -1.1561945 | C48: =SUM(C38:C47) -> -5.1511945 | D48: =SUM(D38:D47) -> -1.8032845 | E48: =SUM(E38:E47) -> -12.253285 | F48: =SUM(F38:F47) -> -1.6682845 | G48: =SUM(G38:G47) -> -1.6632845 | H48: =SUM(H38:H47) -> -7.8032845 | I48: =SUM(I38:I47) -> -2.0029545 | ... M48: =SUM(M38:M47) -> -1.7715894 | N48: =SUM(B48:M48) -> -40.286432 | O48: =SUM(O38:O47) -> -32.7
A49: PR/GR | B49: =Расходы!C22 -> -0.675 | C49: =Расходы!D22 -> -3.525 | D49: =Расходы!E22 -> -4.25 | E49: =Расходы!F22 -> -2.675 | F49: =Расходы!G22 -> -0.875 | G49: =Расходы!H22 -> -1.9 | H49: =Расходы!I22 -> -4.675 | I49: =Расходы!J22 -> -2.025 | ... M49: =Расходы!N22 -> -1.4 | N49: =SUM(B49:M49) -> -33.3 | O49: =Расходы!P22 -> -23.25
A50: Организация бизнес-мероприятий для партнеров | B50: =Расходы!C23 -> 0 | C50: =Расходы!D23 -> -1.5 | D50: =Расходы!E23 -> 0 | E50: =Расходы!F23 -> 0 | F50: =Расходы!G23 -> 0 | G50: =Расходы!H23 -> -0.15 | H50: =Расходы!I23 -> 0 | I50: =Расходы!J23 -> 0 | ... M50: =Расходы!N23 -> 0 | N50: =SUM(B50:M50) -> -1.8 | O50: =Расходы!P23 -> -3.5
A51: Маркетинговые исследования | B51: =Расходы!C24 -> -1.1260256 | C51: =Расходы!D24 -> -1.1260256 | D51: =Расходы!E24 -> -1.1260256 | E51: =Расходы!F24 -> -1.1260256 | F51: =Расходы!G24 -> -1.1260256 | G51: =Расходы!H24 -> -1.1260256 | H51: =Расходы!I24 -> -1.4670104 | I51: =Расходы!J24 -> -1.4670104 | ... M51: =Расходы!N24 -> -1.4670104 | N51: =SUM(B51:M51) -> -15.558216 | O51: =Расходы!P24 -> -8.3
A52: Маркетинг ВГО (не поставщики) | B52: =Расходы!C25 -> -4.1666667 | C52: =Расходы!D25 -> -4.1666667 | D52: =Расходы!E25 -> -4.1666667 | E52: =Расходы!F25 -> -4.1666667 | F52: =Расходы!G25 -> -4.1666667 | G52: =Расходы!H25 -> -4.1666667 | H52: =Расходы!I25 -> -4.1666667 | I52: =Расходы!J25 -> -4.1666667 | ... M52: =Расходы!N25 -> -4.1666667 | N52: =SUM(B52:M52) -> -50 | O52: =Расходы!P25 -> -20.2
A53: Marketing | B53: =SUM(B49:B52) -> -5.9676923 | C53: =SUM(C49:C52) -> -10.317692 | D53: =SUM(D49:D52) -> -9.5426923 | E53: =SUM(E49:E52) -> -7.9676923 | F53: =SUM(F49:F52) -> -6.1676923 | G53: =SUM(G49:G52) -> -7.3426923 | H53: =SUM(H49:H52) -> -10.308677 | I53: =SUM(I49:I52) -> -7.6586771 | ... M53: =SUM(M49:M52) -> -7.0336771 | N53: =SUM(B53:M53) -> -100.65822 | O53: =SUM(O49:O52) -> -55.25
A54: Техподдержка и сопровождение программного обеспечения | B54: =Расходы!C30 -> -6.4490727 | C54: =Расходы!D30 -> -6.4490727 | D54: =Расходы!E30 -> -6.8490727 | E54: =Расходы!F30 -> -6.6490727 | F54: =Расходы!G30 -> -7.1490727 | G54: =Расходы!H30 -> -7.0995797 | H54: =Расходы!I30 -> -7.0420068 | I54: =Расходы!J30 -> -7.309943 | ... M54: =Расходы!N30 -> -9.4274407 | N54: =SUM(B54:M54) -> -92.100557 | O54: =Расходы!P30 -> -58.6
A55: IT | B55: =B54 -> -6.4490727 | C55: =C54 -> -6.4490727 | D55: =D54 -> -6.8490727 | E55: =E54 -> -6.6490727 | F55: =F54 -> -7.1490727 | G55: =G54 -> -7.0995797 | H55: =H54 -> -7.0420068 | I55: =I54 -> -7.309943 | ... M55: =M54 -> -9.4274407 | N55: =SUM(B55:M55) -> -92.100557 | O55: =O54 -> -58.6
A56: Аренда | B56: =Расходы!C32 -> 0 | C56: =Расходы!D32 -> 0 | D56: =Расходы!E32 -> 0 | E56: =Расходы!F32 -> 0 | F56: =Расходы!G32 -> 0 | G56: =Расходы!H32 -> 0 | H56: =Расходы!I32 -> 0 | I56: =Расходы!J32 -> 0 | ... M56: =Расходы!N32 -> 0 | N56: =SUM(B56:M56) -> 0 | O56: =Расходы!P32 -> 0
A57: Сервисный договор | B57: =Расходы!C33 -> -0.31333333 | C57: =Расходы!D33 -> -0.31333333 | D57: =Расходы!E33 -> -0.31333333 | E57: =Расходы!F33 -> -0.31333333 | F57: =Расходы!G33 -> -0.31333333 | G57: =Расходы!H33 -> -0.31333333 | H57: =Расходы!I33 -> -0.31333333 | I57: =Расходы!J33 -> -0.31333333 | ... M57: =Расходы!N33 -> -0.31333333 | N57: =SUM(B57:M57) -> -3.76 | O57: =Расходы!P33 -> -5
A58: Рекламный сбор | B58: =Расходы!C34 -> -1.9202511 | C58: =Расходы!D34 -> -4.8006591 | D58: =Расходы!E34 -> -6.720879 | E58: =Расходы!F34 -> -6.7207852 | F58: =Расходы!G34 -> -6.720879 | G58: =Расходы!H34 -> -6.720879 | H58: =Расходы!I34 -> -6.720879 | I58: =Расходы!J34 -> -7.6808482 | ... M58: =Расходы!N34 -> -16.322135 | N58: =SUM(B58:M58) -> -96.012182 | O58: =Расходы!P34 -> -80.7
A59: Командировочные - Проезд | B59: =Расходы!C35 -> -0.085833333 | C59: =Расходы!D35 -> -0.085833333 | D59: =Расходы!E35 -> -0.085833333 | E59: =Расходы!F35 -> -0.085833333 | F59: =Расходы!G35 -> -0.085833333 | G59: =Расходы!H35 -> -0.085833333 | H59: =Расходы!I35 -> -0.085833333 | I59: =Расходы!J35 -> -0.085833333 | ... M59: =Расходы!N35 -> -0.085833333 | N59: =SUM(B59:M59) -> -1.03 | O59: =Расходы!P35 -> -2.6
A60: Командировочные - Проживание | B60: =Расходы!C36 -> -0.06 | C60: =Расходы!D36 -> -0.06 | D60: =Расходы!E36 -> -0.06 | E60: =Расходы!F36 -> -0.06 | F60: =Расходы!G36 -> -0.06 | G60: =Расходы!H36 -> -0.06 | H60: =Расходы!I36 -> -0.06 | I60: =Расходы!J36 -> -0.06 | ... M60: =Расходы!N36 -> -0.06 | N60: =SUM(B60:M60) -> -0.72 | O60: =Расходы!P36 -> -1.9
A61: Командировочные - Суточные | B61: =Расходы!C37 -> -0.02 | C61: =Расходы!D37 -> -0.02 | D61: =Расходы!E37 -> -0.02 | E61: =Расходы!F37 -> -0.02 | F61: =Расходы!G37 -> -0.02 | G61: =Расходы!H37 -> -0.02 | H61: =Расходы!I37 -> -0.02 | I61: =Расходы!J37 -> -0.02 | ... M61: =Расходы!N37 -> -0.02 | N61: =SUM(B61:M61) -> -0.24 | O61: =Расходы!P37 -> -0.2
A62: Представительские расходы | B62: =Расходы!C38 -> -0.045833333 | C62: =Расходы!D38 -> -0.045833333 | D62: =Расходы!E38 -> -0.045833333 | E62: =Расходы!F38 -> -0.045833333 | F62: =Расходы!G38 -> -0.045833333 | G62: =Расходы!H38 -> -0.045833333 | H62: =Расходы!I38 -> -0.045833333 | I62: =Расходы!J38 -> -0.045833333 | ... M62: =Расходы!N38 -> -0.045833333 | N62: =SUM(B62:M62) -> -0.55 | O62: =Расходы!P38 -> -0.7
A63: Почтовые, курьерские услуги | B63: =Расходы!C39 -> 0 | C63: =Расходы!D39 -> 0 | D63: =Расходы!E39 -> 0 | E63: =Расходы!F39 -> 0 | F63: =Расходы!G39 -> 0 | G63: =Расходы!H39 -> 0 | H63: =Расходы!I39 -> 0 | I63: =Расходы!J39 -> 0 | ... M63: =Расходы!N39 -> 0 | N63: =SUM(B63:M63) -> 0 | O63: =Расходы!P39 -> -0.5
A64: Other OPEX | B64: =SUM(B56:B63) -> -2.4452511 | C64: =SUM(C56:C63) -> -5.3256591 | D64: =SUM(D56:D63) -> -7.245879 | E64: =SUM(E56:E63) -> -7.2457852 | F64: =SUM(F56:F63) -> -7.245879 | G64: =SUM(G56:G63) -> -7.245879 | H64: =SUM(H56:H63) -> -7.245879 | I64: =SUM(I56:I63) -> -8.2058482 | ... M64: =SUM(M56:M63) -> -16.847135 | N64: =SUM(B64:M64) -> -102.31218 | O64: =SUM(O56:O63) -> -91.6
A65: OPEX | B65: =B37+B48+B53+B55+B64 -> -129.98226 | C65: =C37+C48+C53+C55+C64 -> -143.34978 | D65: =D37+D48+D53+D55+D64 -> -142.1515 | E65: =E37+E48+E53+E55+E64 -> -152.77868 | F65: =F37+F48+F53+F55+F64 -> -143.10898 | G65: =G37+G48+G53+G55+G64 -> -141.19004 | H65: =H37+H48+H53+H55+H64 -> -153.18393 | I65: =I37+I48+I53+I55+I64 -> -128.06104 | ... M65: =M37+M48+M53+M55+M64 -> -167.78299 | N65: =SUM(B65:M65) -> -1771.7203 | O65: =O37+O48+O53+O55+O64 -> -1358.2214
A66: EBITDA | B66: =B29+B65 -> 71.474217 | C66: =C29+C65 -> 459.69482 | D66: =D29+D65 -> 728.65098 | E66: =E29+E65 -> 714.2265 | F66: =F29+F65 -> 722.8802 | G66: =G29+G65 -> 723.89076 | H66: =H29+H65 -> 711.94356 | I66: =I29+I65 -> 872.72373 | ... M66: =M29+M65 -> 2059.3527 | N66: =SUM(B66:M66) -> 10823.449 | O66: =O29+O65 -> 8084.6878
A67: Разработка рекламной платформы | B67: =Расходы!C42 -> -42.458922 | C67: =Расходы!D42 -> -43.04558 | D67: =Расходы!E42 -> -44.505901 | E67: =Расходы!F42 -> -44.369799 | F67: =Расходы!G42 -> -44.528812 | G67: =Расходы!H42 -> -44.182905 | H67: =Расходы!I42 -> -47.108845 | I67: =Расходы!J42 -> -46.623045 | ... M67: =Расходы!N42 -> -45.904437 | N67: =SUM(B67:M67) -> -541.03387 | O67: =Расходы!P42 -> -447.2
A68: Проекты Digital Instore (оснащение ТТ) | B68: =Расходы!C43 -> 0 | C68: =Расходы!D43 -> 0 | D68: =Расходы!E43 -> 0 | E68: =Расходы!F43 -> -10.23056 | F68: =Расходы!G43 -> -18.36096 | G68: =Расходы!H43 -> -52.572558 | H68: =Расходы!I43 -> -45.678337 | I68: =Расходы!J43 -> -56.619953 | ... M68: =Расходы!N43 -> -100 | N68: =SUM(B68:M68) -> -609.60587 | O68: =Расходы!P43 -> -732.4
A69: CAPEX | B69: =SUM(B67:B68) -> -42.458922 | C69: =SUM(C67:C68) -> -43.04558 | D69: =SUM(D67:D68) -> -44.505901 | E69: =SUM(E67:E68) -> -54.600359 | F69: =SUM(F67:F68) -> -62.889772 | G69: =SUM(G67:G68) -> -96.755463 | H69: =SUM(H67:H68) -> -92.787183 | I69: =SUM(I67:I68) -> -103.243 | ... O69: =SUM(O67:O68) -> -1179.6
A70: FCF | B70: =B66+B69 -> 29.015294 | C70: =C66+C69 -> 416.64924 | D70: =D66+D69 -> 684.14508 | E70: =E66+E69 -> 659.62614 | F70: =F66+F69 -> 659.99043 | G70: =G66+G69 -> 627.1353 | H70: =H66+H69 -> 619.15637 | I70: =I66+I69 -> 769.48073 | ... M70: =M66+M69 -> 1913.4483 | N70: =SUM(B70:M70) -> 9672.809 | O70: =O66+O69 -> 6905.0878
A72: СПРАВОЧНО
A73: Выручка М+ | B73: ='М+ справочно'!C34 -> 337.89281 | C73: ='М+ справочно'!D34 -> 365.73325 | D73: ='М+ справочно'!E34 -> 377.3919 | E73: ='М+ справочно'!F34 -> 394.58185 | F73: ='М+ справочно'!G34 -> 414.44746 | G73: ='М+ справочно'!H34 -> 435.07252 | H73: ='М+ справочно'!I34 -> 455.65159 | I73: ='М+ справочно'!J34 -> 478.67974 | ... M73: ='М+ справочно'!N34 -> 586.0261 | N73: =SUM(B73:M73) -> 5444.4019 | O73: ='М+ справочно'!P34 -> 3007 | P73: =IFERROR(N73/O73-1,"") -> 0.81057595
A77: Справочно экономия CAPEX ГК благодаря собственной разработке AdTech
B78: CAPEX adj. | C78: Add. OPEX | D78: Total saving
A79: Cubic | B79: -28.46873 | C79: 14.234365 | D79: =SUM(B79:C79) -> -14.234365
A80: InAppStory | B80: -7.3794 | C80: 0 | D80: =SUM(B80:C80) -> -7.3794
A81: Total | B81: =SUM(B79:B80) -> -35.84813 | C81: =SUM(C79:C80) -> 14.234365 | D81: =SUM(D79:D80) -> -21.613765

Sheet P&L 2027_AdvInventory
A1: P&L AdTech 2027 - BOTTOM-UP Advertising Inventory | Q1: Описание: bottom-up P&L AdTech 2027 по месяцам, млн ₽ без НДС. Логика: выручка - из листов направлений (APP = Медиа + Перформанс, Content factory, DMP, In-store; RMN); расходы - из листа «Расходы»
A2: Млн руб. без НДС.
A4: Статья | B4: янв | C4: фев | D4: мар | E4: апр | F4: май | G4: июн | H4: июл | I4: авг | J4: сен | K4: окт | L4: ноя | M4: дек | N4: 2027 | O4: 2026
A5: APP | B5: ='APP Медиа'!C54+'APP Перформанс'!C24 -> 153.92468 | C5: ='APP Медиа'!D54+'APP Перформанс'!D24 -> 384.81171 | D5: ='APP Медиа'!E54+'APP Перформанс'!E24 -> 538.73639 | E5: ='APP Медиа'!F54+'APP Перформанс'!F24 -> 538.73639 | F5: ='APP Медиа'!G54+'APP Перформанс'!G24 -> 538.73639 | G5: ='APP Медиа'!H54+'APP Перформанс'!H24 -> 538.73639 | H5: ='APP Медиа'!I54+'APP Перформанс'!I24 -> 538.73639 | I5: ='APP Медиа'!J54+'APP Перформанс'!J24 -> 615.69874 | ... M5: ='APP Медиа'!N54+'APP Перформанс'!N24 -> 1308.3598 | N5: =SUM(B5:M5) -> 7696.2342 | O5: ='APP Медиа'!P54+'APP Перформанс'!P24 -> 6195.4 | P5: =IFERROR(N5/O5-1,"") -> 0.24224977
A6: Content factory | B6: ='Content factory'!C31 -> 4.266 | C6: ='Content factory'!D31 -> 10.665 | D6: ='Content factory'!E31 -> 14.931 | E6: ='Content factory'!F31 -> 14.931 | F6: ='Content factory'!G31 -> 14.931 | G6: ='Content factory'!H31 -> 14.931 | H6: ='Content factory'!I31 -> 14.931 | I6: ='Content factory'!J31 -> 17.064 | ... M6: ='Content factory'!N31 -> 36.261 | N6: =SUM(B6:M6) -> 213.3 | O6: ='Content factory'!P31 -> 0 | P6: =IFERROR(N6/O6-1,"")
A7: DMP+ Analitycs | B7: =DMP!C20 -> 3.74 | C7: =DMP!D20 -> 9.35 | D7: =DMP!E20 -> 13.09 | E7: =DMP!F20 -> 13.09 | F7: =DMP!G20 -> 13.09 | G7: =DMP!H20 -> 13.09 | H7: =DMP!I20 -> 13.09 | I7: =DMP!J20 -> 14.96 | ... M7: =DMP!N20 -> 31.79 | N7: =SUM(B7:M7) -> 187 | O7: =DMP!O24 -> 102.4 | P7: =IFERROR(N7/O7-1,"") -> 0.82617188
A8: DMP+Online | B8: =DMP!C9 -> 32 | C8: =DMP!D9 -> 80 | D8: =DMP!E9 -> 112 | E8: =DMP!F9 -> 112 | F8: =DMP!G9 -> 112 | G8: =DMP!H9 -> 112 | H8: =DMP!I9 -> 112 | I8: =DMP!J9 -> 128 | ... M8: =DMP!N9 -> 272 | N8: =SUM(B8:M8) -> 1600 | O8: =DMP!O23 -> 987 | P8: =IFERROR(N8/O8-1,"") -> 0.62107396
A9: Instore digital | B9: ='In-store'!C28 -> 80.390907 | C9: ='In-store'!D28 -> 200.98173 | D9: ='In-store'!E28 -> 281.36817 | E9: ='In-store'!F28 -> 281.35478 | F9: ='In-store'!G28 -> 281.36817 | G9: ='In-store'!H28 -> 281.36817 | H9: ='In-store'!I28 -> 281.36817 | I9: ='In-store'!J28 -> 321.5413 | ... M9: ='In-store'!N28 -> 683.32271 | N9: =SUM(B9:M9) -> 4019.4918 | O9: ='In-store'!P28 -> 2446.0892 | P9: =IFERROR(N9/O9-1,"") -> 0.64323186
A10: RMN (Brand budgets call) | B10: =RevSplit!F10 -> 17.004183 | C10: =RevSplit!G10 -> 42.510457 | D10: =RevSplit!H10 -> 59.51464 | E10: =RevSplit!I10 -> 59.51464 | F10: =RevSplit!J10 -> 59.51464 | G10: =RevSplit!K10 -> 59.51464 | H10: =RevSplit!L10 -> 59.51464 | I10: =RevSplit!M10 -> 68.016732 | ... M10: =RevSplit!Q10 -> 144.53555 | N10: =SUM(B10:M10) -> 850.20914 | O10: =RevSplit!S10 -> 592.56 | P10: =IFERROR(N10/O10-1,"") -> 0.43480685
A11: Gross Revenue | B11: =SUM(B5:B10) -> 291.32577 | C11: =SUM(C5:C10) -> 728.3189 | D11: =SUM(D5:D10) -> 1019.6402 | E11: =SUM(E5:E10) -> 1019.6268 | F11: =SUM(F5:F10) -> 1019.6402 | G11: =SUM(G5:G10) -> 1019.6402 | H11: =SUM(H5:H10) -> 1019.6402 | I11: =SUM(I5:I10) -> 1165.2808 | ... M11: =SUM(M5:M10) -> 2476.2691 | N11: =SUM(B11:M11) -> 14566.235 | O11: =SUM(O5:O10) -> 10323.449
A12: Расходы на маркетинг в сети интернет | B12: =Расходы!C26 -> -19.3793 | C12: =Расходы!D26 -> -51.604294 | D12: =Расходы!E26 -> -68.277733 | E12: =Расходы!F26 -> -71.584631 | F12: =Расходы!G26 -> -72.296031 | G12: =Расходы!H26 -> -72.409411 | H12: =Расходы!I26 -> -72.362725 | I12: =Расходы!J26 -> -81.232995 | ... M12: =Расходы!N26 -> -163.80337 | N12: =SUM(B12:M12) -> -1000 | O12: =Расходы!P26 -> -510.54
A13: Вознаграждения креаторам | B13: =Расходы!C27 -> -4.24 | C13: =Расходы!D27 -> -7.42 | D13: =Расходы!E27 -> -14.31 | E13: =Расходы!F27 -> -14.787 | F13: =Расходы!G27 -> -15.105 | G13: =Расходы!H27 -> -15.9 | H13: =Расходы!I27 -> -15.9 | I13: =Расходы!J27 -> -17.013 | ... M13: =Расходы!N27 -> -19.08 | N13: =SUM(B13:M13) -> -176.066 | O13: -15.6
A14: Вознаграждения рекламным агентствам | B14: =Расходы!C28 -> -66.25 | C14: =Расходы!D28 -> -66.25 | D14: =Расходы!E28 -> -66.25 | E14: =Расходы!F28 -> -66.25 | F14: =Расходы!G28 -> -66.25 | G14: =Расходы!H28 -> -66.25 | H14: =Расходы!I28 -> -66.25 | I14: =Расходы!J28 -> -66.25 | ... M14: =Расходы!N28 -> -66.25 | N14: =SUM(B14:M14) -> -795 | O14: =Расходы!P28 -> -354.4
A15: COGS (расходы, привязанные к выручке) | B15: =SUM(B12:B14) -> -89.8693 | C15: =SUM(C12:C14) -> -125.27429 | D15: =SUM(D12:D14) -> -148.83773 | E15: =SUM(E12:E14) -> -152.62163 | F15: =SUM(F12:F14) -> -153.65103 | G15: =SUM(G12:G14) -> -154.55941 | H15: =SUM(H12:H14) -> -154.51273 | I15: =SUM(I12:I14) -> -164.49599 | ... M15: =SUM(M12:M14) -> -249.13337 | N15: =SUM(B15:M15) -> -1971.066 | O15: =SUM(O12:O14) -> -880.54
A16: Net Revenue | B16: =B11+B15 -> 201.45647 | C16: =C11+C15 -> 603.04461 | D16: =D11+D15 -> 870.80248 | E16: =E11+E15 -> 867.00518 | F16: =F11+F15 -> 865.98918 | G16: =G11+G15 -> 865.0808 | H16: =H11+H15 -> 865.12748 | I16: =I11+I15 -> 1000.7848 | ... M16: =M11+M15 -> 2227.1357 | N16: =SUM(B16:M16) -> 12595.169 | O16: =O11+O15 -> 9442.9092
A17: Налоги и взносы, связанные с расходами на оплату труда (ФОТ) | B17: =Расходы!C3 -> -20.502132 | C17: =Расходы!D3 -> -20.887499 | D17: =Расходы!E3 -> -20.996231 | E17: =Расходы!F3 -> -21.347445 | F17: =Расходы!G3 -> -21.745961 | G17: =Расходы!H3 -> -21.199164 | H17: =Расходы!I3 -> -21.729056 | I17: =Расходы!J3 -> -18.508763 | ... M17: =Расходы!N3 -> -23.873296 | N17: =SUM(B17:M17) -> -258.40169 | O17: =Расходы!P3 -> -201.50085
A18: Индексация | B18: =Расходы!C4 -> 0 | C18: =Расходы!D4 -> 0 | D18: =Расходы!E4 -> 0 | E18: =Расходы!F4 -> 0 | F18: =Расходы!G4 -> 0 | G18: =Расходы!H4 -> 0 | H18: =Расходы!I4 -> 0 | I18: =Расходы!J4 -> 0 | ... M18: =Расходы!N4 -> 0 | N18: =SUM(B18:M18) -> 0 | O18: =Расходы!P4 -> 0
A19: Оплата труда - постоянная часть | B19: =Расходы!C5 -> -71.250322 | C19: =Расходы!D5 -> -72.589574 | D19: =Расходы!E5 -> -72.967448 | E19: =Расходы!F5 -> -74.188009 | F19: =Расходы!G5 -> -75.572956 | G19: =Расходы!H5 -> -73.672694 | H19: =Расходы!I5 -> -75.514206 | I19: =Расходы!J5 -> -64.322839 | ... M19: =Расходы!N5 -> -82.966006 | N19: =SUM(B19:M19) -> -898.01411 | O19: =Расходы!P5 -> -700.26866
A20: Оплата труда - премии | B20: =Расходы!C6 -> -2.6895515 | C20: =Расходы!D6 -> -2.7401055 | D20: =Расходы!E6 -> -2.7543694 | E20: =Расходы!F6 -> -2.8004431 | F20: =Расходы!G6 -> -2.852722 | G20: =Расходы!H6 -> -2.780991 | H20: =Расходы!I6 -> -2.8505043 | I20: =Расходы!J6 -> -2.4280534 | ... M20: =Расходы!N6 -> -3.1317942 | N20: =SUM(B20:M20) -> -33.898165 | O20: =Расходы!P6 -> -26.433686
A21: Оплата труда - отпускные | B21: =Расходы!C7 -> -4.6155439 | C21: =Расходы!D7 -> -4.7022997 | D21: =Расходы!E7 -> -4.7267781 | E21: =Расходы!F7 -> -4.8058451 | F21: =Расходы!G7 -> -4.895561 | G21: =Расходы!H7 -> -4.7724634 | H21: =Расходы!I7 -> -4.8917552 | I21: =Расходы!J7 -> -4.1667866 | ... M21: =Расходы!N7 -> -5.3744774 | N21: =SUM(B21:M21) -> -58.172699 | O21: =Расходы!P7 -> -45.362893
A22: Начисление резерва STI 100%, годовой бонус | B22: =Расходы!C8 -> -11.555954 | C22: =Расходы!D8 -> -11.773165 | D22: =Расходы!E8 -> -11.834452 | E22: =Расходы!F8 -> -12.032412 | F22: =Расходы!G8 -> -12.257034 | G22: =Расходы!H8 -> -11.948834 | H22: =Расходы!I8 -> -12.247506 | I22: =Расходы!J8 -> -10.432399 | ... M22: =Расходы!N8 -> -13.456099 | N22: =SUM(B22:M22) -> -145.6472 | O22: =Расходы!P8 -> -113.57524
A23: Начисление резерва STI 100%, квартальные бонусы | B23: =Расходы!C9 -> -3.350543 | C23: =Расходы!D9 -> -3.4135212 | D23: =Расходы!E9 -> -3.4312907 | E23: =Расходы!F9 -> -3.4886876 | F23: =Расходы!G9 -> -3.5538146 | G23: =Расходы!H9 -> -3.4644549 | H23: =Расходы!I9 -> -3.5510519 | I23: =Расходы!J9 -> -3.0247784 | ... M23: =Расходы!N9 -> -3.9014725 | N23: =SUM(B23:M23) -> -42.22907 | O23: =Расходы!P9 -> -32.9301
A24: PEX | B24: =SUM(B17:B23) -> -113.96405 | C24: =SUM(C17:C23) -> -116.10616 | D24: =SUM(D17:D23) -> -116.71057 | E24: =SUM(E17:E23) -> -118.66284 | F24: =SUM(F17:F23) -> -120.87805 | G24: =SUM(G17:G23) -> -117.8386 | H24: =SUM(H17:H23) -> -120.78408 | I24: =SUM(I17:I23) -> -102.88362 | ... M24: =SUM(M17:M23) -> -132.70314 | N24: =SUM(B24:M24) -> -1436.3629 | O24: =SUM(O17:O23) -> -1120.0714
A25: Материальная помощь | B25: =Расходы!C11 -> -0.005 | C25: =Расходы!D11 -> 0 | D25: =Расходы!E11 -> -0.005 | E25: =Расходы!F11 -> -0.005 | F25: =Расходы!G11 -> -0.005 | G25: =Расходы!H11 -> 0 | H25: =Расходы!I11 -> -0.005 | I25: =Расходы!J11 -> 0 | ... M25: =Расходы!N11 -> -0.005 | N25: =SUM(B25:M25) -> -0.04 | O25: =Расходы!P11 -> -0.4
A26: Затраты на корп. мероприятие кроме проезда и проживания | B26: =Расходы!C12 -> -0.375 | C26: =Расходы!D12 -> -0.375 | D26: =Расходы!E12 -> -0.51 | E26: =Расходы!F12 -> -0.375 | F26: =Расходы!G12 -> -0.375 | G26: =Расходы!H12 -> -0.375 | H26: =Расходы!I12 -> -0.51 | I26: =Расходы!J12 -> -0.375 | ... M26: =Расходы!N12 -> -0.375 | N26: =SUM(B26:M26) -> -4.77 | O26: =Расходы!P12 -> -3
A27: ДМС и НС | B27: =Расходы!C13 -> -0.86919813 | C27: =Расходы!D13 -> -0.86919813 | D27: =Расходы!E13 -> -0.86919813 | E27: =Расходы!F13 -> -0.86919813 | F27: =Расходы!G13 -> -0.86919813 | G27: =Расходы!H13 -> -0.86919813 | H27: =Расходы!I13 -> -0.86919813 | I27: =Расходы!J13 -> -0.86919813 | ... M27: =Расходы!N13 -> -0.97250298 | N27: =SUM(B27:M27) -> -10.546904 | O27: =Расходы!P13 -> -6.5
A28: Подбор массовых позиций | B28: =Расходы!C14 -> 0 | C28: =Расходы!D14 -> 0 | D28: =Расходы!E14 -> 0 | E28: =Расходы!F14 -> 0 | F28: =Расходы!G14 -> 0 | G28: =Расходы!H14 -> 0 | H28: =Расходы!I14 -> 0 | I28: =Расходы!J14 -> 0 | ... M28: =Расходы!N14 -> 0 | N28: =SUM(B28:M28) -> 0 | O28: =Расходы!P14 -> -4.9
A29: Подбор офисных позиций | B29: =Расходы!C15 -> -0.037333 | C29: =Расходы!D15 -> -0.037333 | D29: =Расходы!E15 -> -0.037333 | E29: =Расходы!F15 -> -0.37233367 | F29: =Расходы!G15 -> -0.037333 | G29: =Расходы!H15 -> -0.037333 | H29: =Расходы!I15 -> -0.037333 | I29: =Расходы!J15 -> -0.377003 | ... M29: =Расходы!N15 -> -0.037333 | N29: =SUM(B29:M29) -> -1.1226667 | O29: =Расходы!P15 -> 0
A30: Расходы на внешнее обучение | B30: =Расходы!C16 -> 0 | C30: =Расходы!D16 -> 0 | D30: =Расходы!E16 -> -0.51209 | E30: =Расходы!F16 -> -0.51209 | F30: =Расходы!G16 -> -0.51209 | G30: =Расходы!H16 -> -0.51209 | H30: =Расходы!I16 -> -0.51209 | I30: =Расходы!J16 -> -0.51209 | ... M30: =Расходы!N16 -> -0.51209 | N30: =SUM(B30:M30) -> -5.1209 | O30: =Расходы!P16 -> -5.7
A31: Развитие HR бренда | B31: =Расходы!C17 -> 0 | C31: =Расходы!D17 -> -4 | D31: =Расходы!E17 -> 0 | E31: =Расходы!F17 -> -10.25 | F31: =Расходы!G17 -> 0 | G31: =Расходы!H17 -> 0 | H31: =Расходы!I17 -> -6 | I31: =Расходы!J17 -> 0 | ... M31: =Расходы!N17 -> 0 | N31: =SUM(B31:M31) -> -20.25 | O31: =Расходы!P17 -> -14
A32: Карты лояльности (мотивация сотрудников) | B32: =Расходы!C18 -> -0.02799675 | C32: =Расходы!D18 -> -0.02799675 | D32: =Расходы!E18 -> -0.02799675 | E32: =Расходы!F18 -> -0.02799675 | F32: =Расходы!G18 -> -0.02799675 | G32: =Расходы!H18 -> -0.02799675 | H32: =Расходы!I18 -> -0.02799675 | I32: =Расходы!J18 -> -0.02799675 | ... M32: =Расходы!N18 -> -0.02799675 | N32: =SUM(B32:M32) -> -0.335961 | O32: =Расходы!P18 -> 0
A33: Прочие компенсации и льготы | B33: =Расходы!C19 -> -0.041666667 | C33: =Расходы!D19 -> -0.041666667 | D33: =Расходы!E19 -> -0.041666667 | E33: =Расходы!F19 -> -0.041666667 | F33: =Расходы!G19 -> -0.041666667 | G33: =Расходы!H19 -> -0.041666667 | H33: =Расходы!I19 -> -0.041666667 | I33: =Расходы!J19 -> -0.041666667 | ... M33: =Расходы!N19 -> -0.041666667 | N33: =SUM(B33:M33) -> -0.5 | O33: =Расходы!P19 -> -1.2
A34: Резерв на оплату отпусков | B34: =Расходы!C20 -> 0.2 | C34: =Расходы!D20 -> 0.2 | D34: =Расходы!E20 -> 0.2 | E34: =Расходы!F20 -> 0.2 | F34: =Расходы!G20 -> 0.2 | G34: =Расходы!H20 -> 0.2 | H34: =Расходы!I20 -> 0.2 | I34: =Расходы!J20 -> 0.2 | ... M34: =Расходы!N20 -> 0.2 | N34: =SUM(B34:M34) -> 2.4 | O34: =Расходы!P20 -> 3
A35: Other PEX | B35: =SUM(B25:B34) -> -1.1561945 | C35: =SUM(C25:C34) -> -5.1511945 | D35: =SUM(D25:D34) -> -1.8032845 | E35: =SUM(E25:E34) -> -12.253285 | F35: =SUM(F25:F34) -> -1.6682845 | G35: =SUM(G25:G34) -> -1.6632845 | H35: =SUM(H25:H34) -> -7.8032845 | I35: =SUM(I25:I34) -> -2.0029545 | ... M35: =SUM(M25:M34) -> -1.7715894 | N35: =SUM(B35:M35) -> -40.286432 | O35: =SUM(O25:O34) -> -32.7
A36: PR/GR | B36: =Расходы!C22 -> -0.675 | C36: =Расходы!D22 -> -3.525 | D36: =Расходы!E22 -> -4.25 | E36: =Расходы!F22 -> -2.675 | F36: =Расходы!G22 -> -0.875 | G36: =Расходы!H22 -> -1.9 | H36: =Расходы!I22 -> -4.675 | I36: =Расходы!J22 -> -2.025 | ... M36: =Расходы!N22 -> -1.4 | N36: =SUM(B36:M36) -> -33.3 | O36: =Расходы!P22 -> -23.25
A37: Организация бизнес-мероприятий для партнеров | B37: =Расходы!C23 -> 0 | C37: =Расходы!D23 -> -1.5 | D37: =Расходы!E23 -> 0 | E37: =Расходы!F23 -> 0 | F37: =Расходы!G23 -> 0 | G37: =Расходы!H23 -> -0.15 | H37: =Расходы!I23 -> 0 | I37: =Расходы!J23 -> 0 | ... M37: =Расходы!N23 -> 0 | N37: =SUM(B37:M37) -> -1.8 | O37: =Расходы!P23 -> -3.5
A38: Маркетинговые исследования | B38: =Расходы!C24 -> -1.1260256 | C38: =Расходы!D24 -> -1.1260256 | D38: =Расходы!E24 -> -1.1260256 | E38: =Расходы!F24 -> -1.1260256 | F38: =Расходы!G24 -> -1.1260256 | G38: =Расходы!H24 -> -1.1260256 | H38: =Расходы!I24 -> -1.4670104 | I38: =Расходы!J24 -> -1.4670104 | ... M38: =Расходы!N24 -> -1.4670104 | N38: =SUM(B38:M38) -> -15.558216 | O38: =Расходы!P24 -> -8.3
A39: Маркетинг ВГО (не поставщики) | B39: =Расходы!C25 -> -4.1666667 | C39: =Расходы!D25 -> -4.1666667 | D39: =Расходы!E25 -> -4.1666667 | E39: =Расходы!F25 -> -4.1666667 | F39: =Расходы!G25 -> -4.1666667 | G39: =Расходы!H25 -> -4.1666667 | H39: =Расходы!I25 -> -4.1666667 | I39: =Расходы!J25 -> -4.1666667 | ... M39: =Расходы!N25 -> -4.1666667 | N39: =SUM(B39:M39) -> -50 | O39: =Расходы!P25 -> -20.2
A40: Marketing | B40: =SUM(B36:B39) -> -5.9676923 | C40: =SUM(C36:C39) -> -10.317692 | D40: =SUM(D36:D39) -> -9.5426923 | E40: =SUM(E36:E39) -> -7.9676923 | F40: =SUM(F36:F39) -> -6.1676923 | G40: =SUM(G36:G39) -> -7.3426923 | H40: =SUM(H36:H39) -> -10.308677 | I40: =SUM(I36:I39) -> -7.6586771 | ... M40: =SUM(M36:M39) -> -7.0336771 | N40: =SUM(B40:M40) -> -100.65822 | O40: =SUM(O36:O39) -> -55.25
A41: Техподдержка и сопровождение программного обеспечения | B41: =Расходы!C30 -> -6.4490727 | C41: =Расходы!D30 -> -6.4490727 | D41: =Расходы!E30 -> -6.8490727 | E41: =Расходы!F30 -> -6.6490727 | F41: =Расходы!G30 -> -7.1490727 | G41: =Расходы!H30 -> -7.0995797 | H41: =Расходы!I30 -> -7.0420068 | I41: =Расходы!J30 -> -7.309943 | ... M41: =Расходы!N30 -> -9.4274407 | N41: =SUM(B41:M41) -> -92.100557 | O41: =Расходы!P30 -> -58.6
A42: IT | B42: =B41 -> -6.4490727 | C42: =C41 -> -6.4490727 | D42: =D41 -> -6.8490727 | E42: =E41 -> -6.6490727 | F42: =F41 -> -7.1490727 | G42: =G41 -> -7.0995797 | H42: =H41 -> -7.0420068 | I42: =I41 -> -7.309943 | ... M42: =M41 -> -9.4274407 | N42: =SUM(B42:M42) -> -92.100557 | O42: =O41 -> -58.6
A43: Аренда | B43: =Расходы!C32 -> 0 | C43: =Расходы!D32 -> 0 | D43: =Расходы!E32 -> 0 | E43: =Расходы!F32 -> 0 | F43: =Расходы!G32 -> 0 | G43: =Расходы!H32 -> 0 | H43: =Расходы!I32 -> 0 | I43: =Расходы!J32 -> 0 | ... M43: =Расходы!N32 -> 0 | N43: =SUM(B43:M43) -> 0 | O43: =Расходы!P32 -> 0
A44: Сервисный договор | B44: =Расходы!C33 -> -0.31333333 | C44: =Расходы!D33 -> -0.31333333 | D44: =Расходы!E33 -> -0.31333333 | E44: =Расходы!F33 -> -0.31333333 | F44: =Расходы!G33 -> -0.31333333 | G44: =Расходы!H33 -> -0.31333333 | H44: =Расходы!I33 -> -0.31333333 | I44: =Расходы!J33 -> -0.31333333 | ... M44: =Расходы!N33 -> -0.31333333 | N44: =SUM(B44:M44) -> -3.76 | O44: =Расходы!P33 -> -5
A45: Рекламный сбор | B45: =Расходы!C34 -> -1.9202511 | C45: =Расходы!D34 -> -4.8006591 | D45: =Расходы!E34 -> -6.720879 | E45: =Расходы!F34 -> -6.7207852 | F45: =Расходы!G34 -> -6.720879 | G45: =Расходы!H34 -> -6.720879 | H45: =Расходы!I34 -> -6.720879 | I45: =Расходы!J34 -> -7.6808482 | ... M45: =Расходы!N34 -> -16.322135 | N45: =SUM(B45:M45) -> -96.012182 | O45: =Расходы!P34 -> -80.7
A46: Командировочные - Проезд | B46: =Расходы!C35 -> -0.085833333 | C46: =Расходы!D35 -> -0.085833333 | D46: =Расходы!E35 -> -0.085833333 | E46: =Расходы!F35 -> -0.085833333 | F46: =Расходы!G35 -> -0.085833333 | G46: =Расходы!H35 -> -0.085833333 | H46: =Расходы!I35 -> -0.085833333 | I46: =Расходы!J35 -> -0.085833333 | ... M46: =Расходы!N35 -> -0.085833333 | N46: =SUM(B46:M46) -> -1.03 | O46: =Расходы!P35 -> -2.6
A47: Командировочные - Проживание | B47: =Расходы!C36 -> -0.06 | C47: =Расходы!D36 -> -0.06 | D47: =Расходы!E36 -> -0.06 | E47: =Расходы!F36 -> -0.06 | F47: =Расходы!G36 -> -0.06 | G47: =Расходы!H36 -> -0.06 | H47: =Расходы!I36 -> -0.06 | I47: =Расходы!J36 -> -0.06 | ... M47: =Расходы!N36 -> -0.06 | N47: =SUM(B47:M47) -> -0.72 | O47: =Расходы!P36 -> -1.9
A48: Командировочные - Суточные | B48: =Расходы!C37 -> -0.02 | C48: =Расходы!D37 -> -0.02 | D48: =Расходы!E37 -> -0.02 | E48: =Расходы!F37 -> -0.02 | F48: =Расходы!G37 -> -0.02 | G48: =Расходы!H37 -> -0.02 | H48: =Расходы!I37 -> -0.02 | I48: =Расходы!J37 -> -0.02 | ... M48: =Расходы!N37 -> -0.02 | N48: =SUM(B48:M48) -> -0.24 | O48: =Расходы!P37 -> -0.2
A49: Представительские расходы | B49: =Расходы!C38 -> -0.045833333 | C49: =Расходы!D38 -> -0.045833333 | D49: =Расходы!E38 -> -0.045833333 | E49: =Расходы!F38 -> -0.045833333 | F49: =Расходы!G38 -> -0.045833333 | G49: =Расходы!H38 -> -0.045833333 | H49: =Расходы!I38 -> -0.045833333 | I49: =Расходы!J38 -> -0.045833333 | ... M49: =Расходы!N38 -> -0.045833333 | N49: =SUM(B49:M49) -> -0.55 | O49: =Расходы!P38 -> -0.7
A50: Почтовые, курьерские услуги | B50: =Расходы!C39 -> 0 | C50: =Расходы!D39 -> 0 | D50: =Расходы!E39 -> 0 | E50: =Расходы!F39 -> 0 | F50: =Расходы!G39 -> 0 | G50: =Расходы!H39 -> 0 | H50: =Расходы!I39 -> 0 | I50: =Расходы!J39 -> 0 | ... M50: =Расходы!N39 -> 0 | N50: =SUM(B50:M50) -> 0 | O50: =Расходы!P39 -> -0.5
A51: Other OPEX | B51: =SUM(B43:B50) -> -2.4452511 | C51: =SUM(C43:C50) -> -5.3256591 | D51: =SUM(D43:D50) -> -7.245879 | E51: =SUM(E43:E50) -> -7.2457852 | F51: =SUM(F43:F50) -> -7.245879 | G51: =SUM(G43:G50) -> -7.245879 | H51: =SUM(H43:H50) -> -7.245879 | I51: =SUM(I43:I50) -> -8.2058482 | ... M51: =SUM(M43:M50) -> -16.847135 | N51: =SUM(B51:M51) -> -102.31218 | O51: =SUM(O43:O50) -> -91.6
A52: OPEX | B52: =B24+B35+B40+B42+B51 -> -129.98226 | C52: =C24+C35+C40+C42+C51 -> -143.34978 | D52: =D24+D35+D40+D42+D51 -> -142.1515 | E52: =E24+E35+E40+E42+E51 -> -152.77868 | F52: =F24+F35+F40+F42+F51 -> -143.10898 | G52: =G24+G35+G40+G42+G51 -> -141.19004 | H52: =H24+H35+H40+H42+H51 -> -153.18393 | I52: =I24+I35+I40+I42+I51 -> -128.06104 | ... M52: =M24+M35+M40+M42+M51 -> -167.78299 | N52: =SUM(B52:M52) -> -1771.7203 | O52: =O24+O35+O40+O42+O51 -> -1358.2214
A53: EBITDA | B53: =B16+B52 -> 71.474217 | C53: =C16+C52 -> 459.69482 | D53: =D16+D52 -> 728.65098 | E53: =E16+E52 -> 714.2265 | F53: =F16+F52 -> 722.8802 | G53: =G16+G52 -> 723.89076 | H53: =H16+H52 -> 711.94356 | I53: =I16+I52 -> 872.72373 | ... M53: =M16+M52 -> 2059.3527 | N53: =SUM(B53:M53) -> 10823.449 | O53: =O16+O52 -> 8084.6878
A54: Разработка рекламной платформы | B54: =Расходы!C42 -> -42.458922 | C54: =Расходы!D42 -> -43.04558 | D54: =Расходы!E42 -> -44.505901 | E54: =Расходы!F42 -> -44.369799 | F54: =Расходы!G42 -> -44.528812 | G54: =Расходы!H42 -> -44.182905 | H54: =Расходы!I42 -> -47.108845 | I54: =Расходы!J42 -> -46.623045 | ... M54: =Расходы!N42 -> -45.904437 | N54: =SUM(B54:M54) -> -541.03387 | O54: =Расходы!P42 -> -447.2
A55: Проекты Digital Instore (оснащение ТТ) | B55: =Расходы!C43 -> 0 | C55: =Расходы!D43 -> 0 | D55: =Расходы!E43 -> 0 | E55: =Расходы!F43 -> -10.23056 | F55: =Расходы!G43 -> -18.36096 | G55: =Расходы!H43 -> -52.572558 | H55: =Расходы!I43 -> -45.678337 | I55: =Расходы!J43 -> -56.619953 | ... M55: =Расходы!N43 -> -100 | N55: =SUM(B55:M55) -> -609.60587 | O55: =Расходы!P43 -> -732.4
A56: CAPEX | B56: =SUM(B54:B55) -> -42.458922 | C56: =SUM(C54:C55) -> -43.04558 | D56: =SUM(D54:D55) -> -44.505901 | E56: =SUM(E54:E55) -> -54.600359 | F56: =SUM(F54:F55) -> -62.889772 | G56: =SUM(G54:G55) -> -96.755463 | H56: =SUM(H54:H55) -> -92.787183 | I56: =SUM(I54:I55) -> -103.243 | ... O56: =SUM(O54:O55) -> -1179.6
A57: FCF | B57: =B53+B56 -> 29.015294 | C57: =C53+C56 -> 416.64924 | D57: =D53+D56 -> 684.14508 | E57: =E53+E56 -> 659.62614 | F57: =F53+F56 -> 659.99043 | G57: =G53+G56 -> 627.1353 | H57: =H53+H56 -> 619.15637 | I57: =I53+I56 -> 769.48073 | ... M57: =M53+M56 -> 1913.4483 | N57: =SUM(B57:M57) -> 9672.809 | O57: =O53+O56 -> 6905.0878
A59: СПРАВОЧНО
A60: Выручка М+ | B60: ='М+ справочно'!C34 -> 337.89281 | C60: ='М+ справочно'!D34 -> 365.73325 | D60: ='М+ справочно'!E34 -> 377.3919 | E60: ='М+ справочно'!F34 -> 394.58185 | F60: ='М+ справочно'!G34 -> 414.44746 | G60: ='М+ справочно'!H34 -> 435.07252 | H60: ='М+ справочно'!I34 -> 455.65159 | I60: ='М+ справочно'!J34 -> 478.67974 | ... M60: ='М+ справочно'!N34 -> 586.0261 | N60: =SUM(B60:M60) -> 5444.4019 | O60: ='М+ справочно'!P34 -> 3007 | P60: =IFERROR(N60/O60-1,"") -> 0.81057595

Sheet P&L 2027_Formats
A1: P&L AdTech 2027 - BOTTOM-UP Formats | Q1: Описание: bottom-up P&L AdTech 2027 по месяцам, млн ₽ без НДС. Логика: выручка трансформированная из направлений в форматы - лист «RevSplit»; расходы - из листа «Расходы»
A2: Млн руб. без НДС.
A4: Статья | B4: янв | C4: фев | D4: мар | E4: апр | F4: май | G4: июн | H4: июл | I4: авг | J4: сен | K4: окт | L4: ноя | M4: дек | N4: 2027 | O4: 2026
A5: E-commerce | B5: =RevSplit!X5 -> 153.92468 | C5: =RevSplit!Y5 -> 384.81171 | D5: =RevSplit!Z5 -> 538.73639 | E5: =RevSplit!AA5 -> 538.73639 | F5: =RevSplit!AB5 -> 538.73639 | G5: =RevSplit!AC5 -> 538.73639 | H5: =RevSplit!AD5 -> 538.73639 | I5: =RevSplit!AE5 -> 615.69874 | ... M5: =RevSplit!AI5 -> 1308.3598 | N5: =SUM(B5:M5) -> 7696.2342 | O5: =RevSplit!AK5 -> 6195.4 | P5: =IFERROR(N5/O5-1,"") -> 0.24224977
A6: ММ | B6: =RevSplit!X6 -> 61.119537 | C6: =RevSplit!Y6 -> 152.80189 | D6: =RevSplit!Z6 -> 213.91838 | E6: =RevSplit!AA6 -> 213.90924 | F6: =RevSplit!AB6 -> 213.91838 | G6: =RevSplit!AC6 -> 213.91838 | H6: =RevSplit!AD6 -> 213.91838 | I6: =RevSplit!AE6 -> 244.46291 | ... M6: =RevSplit!AI6 -> 519.51607 | N6: =SUM(B6:M6) -> 3055.9403 | O6: =RevSplit!AK6 -> 1862.3131 | P6: =IFERROR(N6/O6-1,"") -> 0.64093801
A7: МК | B7: =RevSplit!X7 -> 32.795963 | C7: =RevSplit!Y7 -> 81.990345 | D7: =RevSplit!Z7 -> 114.78587 | E7: =RevSplit!AA7 -> 114.78456 | F7: =RevSplit!AB7 -> 114.78587 | G7: =RevSplit!AC7 -> 114.78587 | H7: =RevSplit!AD7 -> 114.78587 | I7: =RevSplit!AE7 -> 131.18167 | ... M7: =RevSplit!AI7 -> 278.76569 | N7: =SUM(B7:M7) -> 1639.7929 | O7: =RevSplit!AK7 -> 1008.2743 | P7: =IFERROR(N7/O7-1,"") -> 0.6263362
A8: МЭ | B8: =RevSplit!X8 -> 11.157443 | C8: =RevSplit!Y8 -> 27.894193 | D8: =RevSplit!Z8 -> 39.051051 | E8: =RevSplit!AA8 -> 39.049293 | F8: =RevSplit!AB8 -> 39.051051 | G8: =RevSplit!AC8 -> 39.051051 | H8: =RevSplit!AD8 -> 39.051051 | I8: =RevSplit!AE8 -> 44.626843 | ... M8: =RevSplit!AI8 -> 94.838266 | N8: =SUM(B8:M8) -> 557.86512 | O8: =RevSplit!AK8 -> 339.74806 | P8: =IFERROR(N8/O8-1,"") -> 0.64199647
A9: МС | B9: =RevSplit!X9 -> 4.9806379 | C9: =RevSplit!Y9 -> 12.45186 | D9: =RevSplit!Z9 -> 17.432233 | E9: =RevSplit!AA9 -> 17.431437 | F9: =RevSplit!AB9 -> 17.432233 | G9: =RevSplit!AC9 -> 17.432233 | H9: =RevSplit!AD9 -> 17.432233 | I9: =RevSplit!AE9 -> 19.921226 | ... M9: =RevSplit!AI9 -> 42.335422 | N9: =SUM(B9:M9) -> 249.02871 | O9: =RevSplit!AK9 -> 151.63503 | P9: =IFERROR(N9/O9-1,"") -> 0.64229009
A10: МС Лайт | B10: =RevSplit!X10 -> 2.3373256 | C10: =RevSplit!Y10 -> 5.8434438 | D10: =RevSplit!Z10 -> 8.1806395 | E10: =RevSplit!AA10 -> 8.1802499 | F10: =RevSplit!AB10 -> 8.1806395 | G10: =RevSplit!AC10 -> 8.1806395 | H10: =RevSplit!AD10 -> 8.1806395 | I10: =RevSplit!AE10 -> 9.348653 | ... M10: =RevSplit!AI10 -> 19.867267 | N10: =SUM(B10:M10) -> 116.86472 | O10: =RevSplit!AK10 -> 71.118826 | P10: =IFERROR(N10/O10-1,"") -> 0.64323186
A11: Без формата | B11: =RevSplit!X11 -> 25.010183 | C11: =RevSplit!Y11 -> 62.525457 | D11: =RevSplit!Z11 -> 87.53564 | E11: =RevSplit!AA11 -> 87.53564 | F11: =RevSplit!AB11 -> 87.53564 | G11: =RevSplit!AC11 -> 87.53564 | H11: =RevSplit!AD11 -> 87.53564 | I11: =RevSplit!AE11 -> 100.04073 | ... M11: =RevSplit!AI11 -> 212.58655 | N11: =SUM(B11:M11) -> 1250.5091 | O11: =RevSplit!AK11 -> 694.96 | P11: =IFERROR(N11/O11-1,"") -> 0.7993973
A12: Gross Revenue | B12: =SUM(B5:B11) -> 291.32577 | C12: =SUM(C5:C11) -> 728.3189 | D12: =SUM(D5:D11) -> 1019.6402 | E12: =SUM(E5:E11) -> 1019.6268 | F12: =SUM(F5:F11) -> 1019.6402 | G12: =SUM(G5:G11) -> 1019.6402 | H12: =SUM(H5:H11) -> 1019.6402 | I12: =SUM(I5:I11) -> 1165.2808 | ... M12: =SUM(M5:M11) -> 2476.2691 | N12: =SUM(B12:M12) -> 14566.235 | O12: =SUM(O5:O11) -> 10323.449
A13: Расходы на маркетинг в сети интернет | B13: =Расходы!C26 -> -19.3793 | C13: =Расходы!D26 -> -51.604294 | D13: =Расходы!E26 -> -68.277733 | E13: =Расходы!F26 -> -71.584631 | F13: =Расходы!G26 -> -72.296031 | G13: =Расходы!H26 -> -72.409411 | H13: =Расходы!I26 -> -72.362725 | I13: =Расходы!J26 -> -81.232995 | ... M13: =Расходы!N26 -> -163.80337 | N13: =SUM(B13:M13) -> -1000 | O13: =Расходы!P26 -> -510.54
A14: Вознаграждения креаторам | B14: =Расходы!C27 -> -4.24 | C14: =Расходы!D27 -> -7.42 | D14: =Расходы!E27 -> -14.31 | E14: =Расходы!F27 -> -14.787 | F14: =Расходы!G27 -> -15.105 | G14: =Расходы!H27 -> -15.9 | H14: =Расходы!I27 -> -15.9 | I14: =Расходы!J27 -> -17.013 | ... M14: =Расходы!N27 -> -19.08 | N14: =SUM(B14:M14) -> -176.066 | O14: -15.6
A15: Вознаграждения рекламным агентствам | B15: =Расходы!C28 -> -66.25 | C15: =Расходы!D28 -> -66.25 | D15: =Расходы!E28 -> -66.25 | E15: =Расходы!F28 -> -66.25 | F15: =Расходы!G28 -> -66.25 | G15: =Расходы!H28 -> -66.25 | H15: =Расходы!I28 -> -66.25 | I15: =Расходы!J28 -> -66.25 | ... M15: =Расходы!N28 -> -66.25 | N15: =SUM(B15:M15) -> -795 | O15: =Расходы!P28 -> -354.4
A16: COGS (расходы, привязанные к выручке) | B16: =SUM(B13:B15) -> -89.8693 | C16: =SUM(C13:C15) -> -125.27429 | D16: =SUM(D13:D15) -> -148.83773 | E16: =SUM(E13:E15) -> -152.62163 | F16: =SUM(F13:F15) -> -153.65103 | G16: =SUM(G13:G15) -> -154.55941 | H16: =SUM(H13:H15) -> -154.51273 | I16: =SUM(I13:I15) -> -164.49599 | ... M16: =SUM(M13:M15) -> -249.13337 | N16: =SUM(B16:M16) -> -1971.066 | O16: =SUM(O13:O15) -> -880.54
A17: Net Revenue | B17: =B12+B16 -> 201.45647 | C17: =C12+C16 -> 603.04461 | D17: =D12+D16 -> 870.80248 | E17: =E12+E16 -> 867.00518 | F17: =F12+F16 -> 865.98918 | G17: =G12+G16 -> 865.0808 | H17: =H12+H16 -> 865.12748 | I17: =I12+I16 -> 1000.7848 | ... M17: =M12+M16 -> 2227.1357 | N17: =SUM(B17:M17) -> 12595.169 | O17: =O12+O16 -> 9442.9092
A18: Налоги и взносы, связанные с расходами на оплату труда (ФОТ) | B18: =Расходы!C3 -> -20.502132 | C18: =Расходы!D3 -> -20.887499 | D18: =Расходы!E3 -> -20.996231 | E18: =Расходы!F3 -> -21.347445 | F18: =Расходы!G3 -> -21.745961 | G18: =Расходы!H3 -> -21.199164 | H18: =Расходы!I3 -> -21.729056 | I18: =Расходы!J3 -> -18.508763 | ... M18: =Расходы!N3 -> -23.873296 | N18: =SUM(B18:M18) -> -258.40169 | O18: =Расходы!P3 -> -201.50085
A19: Индексация | B19: =Расходы!C4 -> 0 | C19: =Расходы!D4 -> 0 | D19: =Расходы!E4 -> 0 | E19: =Расходы!F4 -> 0 | F19: =Расходы!G4 -> 0 | G19: =Расходы!H4 -> 0 | H19: =Расходы!I4 -> 0 | I19: =Расходы!J4 -> 0 | ... M19: =Расходы!N4 -> 0 | N19: =SUM(B19:M19) -> 0 | O19: =Расходы!P4 -> 0
A20: Оплата труда - постоянная часть | B20: =Расходы!C5 -> -71.250322 | C20: =Расходы!D5 -> -72.589574 | D20: =Расходы!E5 -> -72.967448 | E20: =Расходы!F5 -> -74.188009 | F20: =Расходы!G5 -> -75.572956 | G20: =Расходы!H5 -> -73.672694 | H20: =Расходы!I5 -> -75.514206 | I20: =Расходы!J5 -> -64.322839 | ... M20: =Расходы!N5 -> -82.966006 | N20: =SUM(B20:M20) -> -898.01411 | O20: =Расходы!P5 -> -700.26866
A21: Оплата труда - премии | B21: =Расходы!C6 -> -2.6895515 | C21: =Расходы!D6 -> -2.7401055 | D21: =Расходы!E6 -> -2.7543694 | E21: =Расходы!F6 -> -2.8004431 | F21: =Расходы!G6 -> -2.852722 | G21: =Расходы!H6 -> -2.780991 | H21: =Расходы!I6 -> -2.8505043 | I21: =Расходы!J6 -> -2.4280534 | ... M21: =Расходы!N6 -> -3.1317942 | N21: =SUM(B21:M21) -> -33.898165 | O21: =Расходы!P6 -> -26.433686
A22: Оплата труда - отпускные | B22: =Расходы!C7 -> -4.6155439 | C22: =Расходы!D7 -> -4.7022997 | D22: =Расходы!E7 -> -4.7267781 | E22: =Расходы!F7 -> -4.8058451 | F22: =Расходы!G7 -> -4.895561 | G22: =Расходы!H7 -> -4.7724634 | H22: =Расходы!I7 -> -4.8917552 | I22: =Расходы!J7 -> -4.1667866 | ... M22: =Расходы!N7 -> -5.3744774 | N22: =SUM(B22:M22) -> -58.172699 | O22: =Расходы!P7 -> -45.362893
A23: Начисление резерва STI 100%, годовой бонус | B23: =Расходы!C8 -> -11.555954 | C23: =Расходы!D8 -> -11.773165 | D23: =Расходы!E8 -> -11.834452 | E23: =Расходы!F8 -> -12.032412 | F23: =Расходы!G8 -> -12.257034 | G23: =Расходы!H8 -> -11.948834 | H23: =Расходы!I8 -> -12.247506 | I23: =Расходы!J8 -> -10.432399 | ... M23: =Расходы!N8 -> -13.456099 | N23: =SUM(B23:M23) -> -145.6472 | O23: =Расходы!P8 -> -113.57524
A24: Начисление резерва STI 100%, квартальные бонусы | B24: =Расходы!C9 -> -3.350543 | C24: =Расходы!D9 -> -3.4135212 | D24: =Расходы!E9 -> -3.4312907 | E24: =Расходы!F9 -> -3.4886876 | F24: =Расходы!G9 -> -3.5538146 | G24: =Расходы!H9 -> -3.4644549 | H24: =Расходы!I9 -> -3.5510519 | I24: =Расходы!J9 -> -3.0247784 | ... M24: =Расходы!N9 -> -3.9014725 | N24: =SUM(B24:M24) -> -42.22907 | O24: =Расходы!P9 -> -32.9301
A25: PEX | B25: =SUM(B18:B24) -> -113.96405 | C25: =SUM(C18:C24) -> -116.10616 | D25: =SUM(D18:D24) -> -116.71057 | E25: =SUM(E18:E24) -> -118.66284 | F25: =SUM(F18:F24) -> -120.87805 | G25: =SUM(G18:G24) -> -117.8386 | H25: =SUM(H18:H24) -> -120.78408 | I25: =SUM(I18:I24) -> -102.88362 | ... M25: =SUM(M18:M24) -> -132.70314 | N25: =SUM(B25:M25) -> -1436.3629 | O25: =SUM(O18:O24) -> -1120.0714
A26: Материальная помощь | B26: =Расходы!C11 -> -0.005 | C26: =Расходы!D11 -> 0 | D26: =Расходы!E11 -> -0.005 | E26: =Расходы!F11 -> -0.005 | F26: =Расходы!G11 -> -0.005 | G26: =Расходы!H11 -> 0 | H26: =Расходы!I11 -> -0.005 | I26: =Расходы!J11 -> 0 | ... M26: =Расходы!N11 -> -0.005 | N26: =SUM(B26:M26) -> -0.04 | O26: =Расходы!P11 -> -0.4
A27: Затраты на корп. мероприятие кроме проезда и проживания | B27: =Расходы!C12 -> -0.375 | C27: =Расходы!D12 -> -0.375 | D27: =Расходы!E12 -> -0.51 | E27: =Расходы!F12 -> -0.375 | F27: =Расходы!G12 -> -0.375 | G27: =Расходы!H12 -> -0.375 | H27: =Расходы!I12 -> -0.51 | I27: =Расходы!J12 -> -0.375 | ... M27: =Расходы!N12 -> -0.375 | N27: =SUM(B27:M27) -> -4.77 | O27: =Расходы!P12 -> -3
A28: ДМС и НС | B28: =Расходы!C13 -> -0.86919813 | C28: =Расходы!D13 -> -0.86919813 | D28: =Расходы!E13 -> -0.86919813 | E28: =Расходы!F13 -> -0.86919813 | F28: =Расходы!G13 -> -0.86919813 | G28: =Расходы!H13 -> -0.86919813 | H28: =Расходы!I13 -> -0.86919813 | I28: =Расходы!J13 -> -0.86919813 | ... M28: =Расходы!N13 -> -0.97250298 | N28: =SUM(B28:M28) -> -10.546904 | O28: =Расходы!P13 -> -6.5
A29: Подбор массовых позиций | B29: =Расходы!C14 -> 0 | C29: =Расходы!D14 -> 0 | D29: =Расходы!E14 -> 0 | E29: =Расходы!F14 -> 0 | F29: =Расходы!G14 -> 0 | G29: =Расходы!H14 -> 0 | H29: =Расходы!I14 -> 0 | I29: =Расходы!J14 -> 0 | ... M29: =Расходы!N14 -> 0 | N29: =SUM(B29:M29) -> 0 | O29: =Расходы!P14 -> -4.9
A30: Подбор офисных позиций | B30: =Расходы!C15 -> -0.037333 | C30: =Расходы!D15 -> -0.037333 | D30: =Расходы!E15 -> -0.037333 | E30: =Расходы!F15 -> -0.37233367 | F30: =Расходы!G15 -> -0.037333 | G30: =Расходы!H15 -> -0.037333 | H30: =Расходы!I15 -> -0.037333 | I30: =Расходы!J15 -> -0.377003 | ... M30: =Расходы!N15 -> -0.037333 | N30: =SUM(B30:M30) -> -1.1226667 | O30: =Расходы!P15 -> 0
A31: Расходы на внешнее обучение | B31: =Расходы!C16 -> 0 | C31: =Расходы!D16 -> 0 | D31: =Расходы!E16 -> -0.51209 | E31: =Расходы!F16 -> -0.51209 | F31: =Расходы!G16 -> -0.51209 | G31: =Расходы!H16 -> -0.51209 | H31: =Расходы!I16 -> -0.51209 | I31: =Расходы!J16 -> -0.51209 | ... M31: =Расходы!N16 -> -0.51209 | N31: =SUM(B31:M31) -> -5.1209 | O31: =Расходы!P16 -> -5.7
A32: Развитие HR бренда | B32: =Расходы!C17 -> 0 | C32: =Расходы!D17 -> -4 | D32: =Расходы!E17 -> 0 | E32: =Расходы!F17 -> -10.25 | F32: =Расходы!G17 -> 0 | G32: =Расходы!H17 -> 0 | H32: =Расходы!I17 -> -6 | I32: =Расходы!J17 -> 0 | ... M32: =Расходы!N17 -> 0 | N32: =SUM(B32:M32) -> -20.25 | O32: =Расходы!P17 -> -14
A33: Карты лояльности (мотивация сотрудников) | B33: =Расходы!C18 -> -0.02799675 | C33: =Расходы!D18 -> -0.02799675 | D33: =Расходы!E18 -> -0.02799675 | E33: =Расходы!F18 -> -0.02799675 | F33: =Расходы!G18 -> -0.02799675 | G33: =Расходы!H18 -> -0.02799675 | H33: =Расходы!I18 -> -0.02799675 | I33: =Расходы!J18 -> -0.02799675 | ... M33: =Расходы!N18 -> -0.02799675 | N33: =SUM(B33:M33) -> -0.335961 | O33: =Расходы!P18 -> 0
A34: Прочие компенсации и льготы | B34: =Расходы!C19 -> -0.041666667 | C34: =Расходы!D19 -> -0.041666667 | D34: =Расходы!E19 -> -0.041666667 | E34: =Расходы!F19 -> -0.041666667 | F34: =Расходы!G19 -> -0.041666667 | G34: =Расходы!H19 -> -0.041666667 | H34: =Расходы!I19 -> -0.041666667 | I34: =Расходы!J19 -> -0.041666667 | ... M34: =Расходы!N19 -> -0.041666667 | N34: =SUM(B34:M34) -> -0.5 | O34: =Расходы!P19 -> -1.2
A35: Резерв на оплату отпусков | B35: =Расходы!C20 -> 0.2 | C35: =Расходы!D20 -> 0.2 | D35: =Расходы!E20 -> 0.2 | E35: =Расходы!F20 -> 0.2 | F35: =Расходы!G20 -> 0.2 | G35: =Расходы!H20 -> 0.2 | H35: =Расходы!I20 -> 0.2 | I35: =Расходы!J20 -> 0.2 | ... M35: =Расходы!N20 -> 0.2 | N35: =SUM(B35:M35) -> 2.4 | O35: =Расходы!P20 -> 3
A36: Other PEX | B36: =SUM(B26:B35) -> -1.1561945 | C36: =SUM(C26:C35) -> -5.1511945 | D36: =SUM(D26:D35) -> -1.8032845 | E36: =SUM(E26:E35) -> -12.253285 | F36: =SUM(F26:F35) -> -1.6682845 | G36: =SUM(G26:G35) -> -1.6632845 | H36: =SUM(H26:H35) -> -7.8032845 | I36: =SUM(I26:I35) -> -2.0029545 | ... M36: =SUM(M26:M35) -> -1.7715894 | N36: =SUM(B36:M36) -> -40.286432 | O36: =SUM(O26:O35) -> -32.7
A37: PR/GR | B37: =Расходы!C22 -> -0.675 | C37: =Расходы!D22 -> -3.525 | D37: =Расходы!E22 -> -4.25 | E37: =Расходы!F22 -> -2.675 | F37: =Расходы!G22 -> -0.875 | G37: =Расходы!H22 -> -1.9 | H37: =Расходы!I22 -> -4.675 | I37: =Расходы!J22 -> -2.025 | ... M37: =Расходы!N22 -> -1.4 | N37: =SUM(B37:M37) -> -33.3 | O37: =Расходы!P22 -> -23.25
A38: Организация бизнес-мероприятий для партнеров | B38: =Расходы!C23 -> 0 | C38: =Расходы!D23 -> -1.5 | D38: =Расходы!E23 -> 0 | E38: =Расходы!F23 -> 0 | F38: =Расходы!G23 -> 0 | G38: =Расходы!H23 -> -0.15 | H38: =Расходы!I23 -> 0 | I38: =Расходы!J23 -> 0 | ... M38: =Расходы!N23 -> 0 | N38: =SUM(B38:M38) -> -1.8 | O38: =Расходы!P23 -> -3.5
A39: Маркетинговые исследования | B39: =Расходы!C24 -> -1.1260256 | C39: =Расходы!D24 -> -1.1260256 | D39: =Расходы!E24 -> -1.1260256 | E39: =Расходы!F24 -> -1.1260256 | F39: =Расходы!G24 -> -1.1260256 | G39: =Расходы!H24 -> -1.1260256 | H39: =Расходы!I24 -> -1.4670104 | I39: =Расходы!J24 -> -1.4670104 | ... M39: =Расходы!N24 -> -1.4670104 | N39: =SUM(B39:M39) -> -15.558216 | O39: =Расходы!P24 -> -8.3
A40: Маркетинг ВГО (не поставщики) | B40: =Расходы!C25 -> -4.1666667 | C40: =Расходы!D25 -> -4.1666667 | D40: =Расходы!E25 -> -4.1666667 | E40: =Расходы!F25 -> -4.1666667 | F40: =Расходы!G25 -> -4.1666667 | G40: =Расходы!H25 -> -4.1666667 | H40: =Расходы!I25 -> -4.1666667 | I40: =Расходы!J25 -> -4.1666667 | ... M40: =Расходы!N25 -> -4.1666667 | N40: =SUM(B40:M40) -> -50 | O40: =Расходы!P25 -> -20.2
A41: Marketing | B41: =SUM(B37:B40) -> -5.9676923 | C41: =SUM(C37:C40) -> -10.317692 | D41: =SUM(D37:D40) -> -9.5426923 | E41: =SUM(E37:E40) -> -7.9676923 | F41: =SUM(F37:F40) -> -6.1676923 | G41: =SUM(G37:G40) -> -7.3426923 | H41: =SUM(H37:H40) -> -10.308677 | I41: =SUM(I37:I40) -> -7.6586771 | ... M41: =SUM(M37:M40) -> -7.0336771 | N41: =SUM(B41:M41) -> -100.65822 | O41: =SUM(O37:O40) -> -55.25
A42: Техподдержка и сопровождение программного обеспечения | B42: =Расходы!C30 -> -6.4490727 | C42: =Расходы!D30 -> -6.4490727 | D42: =Расходы!E30 -> -6.8490727 | E42: =Расходы!F30 -> -6.6490727 | F42: =Расходы!G30 -> -7.1490727 | G42: =Расходы!H30 -> -7.0995797 | H42: =Расходы!I30 -> -7.0420068 | I42: =Расходы!J30 -> -7.309943 | ... M42: =Расходы!N30 -> -9.4274407 | N42: =SUM(B42:M42) -> -92.100557 | O42: =Расходы!P30 -> -58.6
A43: IT | B43: =B42 -> -6.4490727 | C43: =C42 -> -6.4490727 | D43: =D42 -> -6.8490727 | E43: =E42 -> -6.6490727 | F43: =F42 -> -7.1490727 | G43: =G42 -> -7.0995797 | H43: =H42 -> -7.0420068 | I43: =I42 -> -7.309943 | ... M43: =M42 -> -9.4274407 | N43: =SUM(B43:M43) -> -92.100557 | O43: =O42 -> -58.6
A44: Аренда | B44: =Расходы!C32 -> 0 | C44: =Расходы!D32 -> 0 | D44: =Расходы!E32 -> 0 | E44: =Расходы!F32 -> 0 | F44: =Расходы!G32 -> 0 | G44: =Расходы!H32 -> 0 | H44: =Расходы!I32 -> 0 | I44: =Расходы!J32 -> 0 | ... M44: =Расходы!N32 -> 0 | N44: =SUM(B44:M44) -> 0 | O44: =Расходы!P32 -> 0
A45: Сервисный договор | B45: =Расходы!C33 -> -0.31333333 | C45: =Расходы!D33 -> -0.31333333 | D45: =Расходы!E33 -> -0.31333333 | E45: =Расходы!F33 -> -0.31333333 | F45: =Расходы!G33 -> -0.31333333 | G45: =Расходы!H33 -> -0.31333333 | H45: =Расходы!I33 -> -0.31333333 | I45: =Расходы!J33 -> -0.31333333 | ... M45: =Расходы!N33 -> -0.31333333 | N45: =SUM(B45:M45) -> -3.76 | O45: =Расходы!P33 -> -5
A46: Рекламный сбор | B46: =Расходы!C34 -> -1.9202511 | C46: =Расходы!D34 -> -4.8006591 | D46: =Расходы!E34 -> -6.720879 | E46: =Расходы!F34 -> -6.7207852 | F46: =Расходы!G34 -> -6.720879 | G46: =Расходы!H34 -> -6.720879 | H46: =Расходы!I34 -> -6.720879 | I46: =Расходы!J34 -> -7.6808482 | ... M46: =Расходы!N34 -> -16.322135 | N46: =SUM(B46:M46) -> -96.012182 | O46: =Расходы!P34 -> -80.7
A47: Командировочные - Проезд | B47: =Расходы!C35 -> -0.085833333 | C47: =Расходы!D35 -> -0.085833333 | D47: =Расходы!E35 -> -0.085833333 | E47: =Расходы!F35 -> -0.085833333 | F47: =Расходы!G35 -> -0.085833333 | G47: =Расходы!H35 -> -0.085833333 | H47: =Расходы!I35 -> -0.085833333 | I47: =Расходы!J35 -> -0.085833333 | ... M47: =Расходы!N35 -> -0.085833333 | N47: =SUM(B47:M47) -> -1.03 | O47: =Расходы!P35 -> -2.6
A48: Командировочные - Проживание | B48: =Расходы!C36 -> -0.06 | C48: =Расходы!D36 -> -0.06 | D48: =Расходы!E36 -> -0.06 | E48: =Расходы!F36 -> -0.06 | F48: =Расходы!G36 -> -0.06 | G48: =Расходы!H36 -> -0.06 | H48: =Расходы!I36 -> -0.06 | I48: =Расходы!J36 -> -0.06 | ... M48: =Расходы!N36 -> -0.06 | N48: =SUM(B48:M48) -> -0.72 | O48: =Расходы!P36 -> -1.9
A49: Командировочные - Суточные | B49: =Расходы!C37 -> -0.02 | C49: =Расходы!D37 -> -0.02 | D49: =Расходы!E37 -> -0.02 | E49: =Расходы!F37 -> -0.02 | F49: =Расходы!G37 -> -0.02 | G49: =Расходы!H37 -> -0.02 | H49: =Расходы!I37 -> -0.02 | I49: =Расходы!J37 -> -0.02 | ... M49: =Расходы!N37 -> -0.02 | N49: =SUM(B49:M49) -> -0.24 | O49: =Расходы!P37 -> -0.2
A50: Представительские расходы | B50: =Расходы!C38 -> -0.045833333 | C50: =Расходы!D38 -> -0.045833333 | D50: =Расходы!E38 -> -0.045833333 | E50: =Расходы!F38 -> -0.045833333 | F50: =Расходы!G38 -> -0.045833333 | G50: =Расходы!H38 -> -0.045833333 | H50: =Расходы!I38 -> -0.045833333 | I50: =Расходы!J38 -> -0.045833333 | ... M50: =Расходы!N38 -> -0.045833333 | N50: =SUM(B50:M50) -> -0.55 | O50: =Расходы!P38 -> -0.7
A51: Почтовые, курьерские услуги | B51: =Расходы!C39 -> 0 | C51: =Расходы!D39 -> 0 | D51: =Расходы!E39 -> 0 | E51: =Расходы!F39 -> 0 | F51: =Расходы!G39 -> 0 | G51: =Расходы!H39 -> 0 | H51: =Расходы!I39 -> 0 | I51: =Расходы!J39 -> 0 | ... M51: =Расходы!N39 -> 0 | N51: =SUM(B51:M51) -> 0 | O51: =Расходы!P39 -> -0.5
A52: Other OPEX | B52: =SUM(B44:B51) -> -2.4452511 | C52: =SUM(C44:C51) -> -5.3256591 | D52: =SUM(D44:D51) -> -7.245879 | E52: =SUM(E44:E51) -> -7.2457852 | F52: =SUM(F44:F51) -> -7.245879 | G52: =SUM(G44:G51) -> -7.245879 | H52: =SUM(H44:H51) -> -7.245879 | I52: =SUM(I44:I51) -> -8.2058482 | ... M52: =SUM(M44:M51) -> -16.847135 | N52: =SUM(B52:M52) -> -102.31218 | O52: =SUM(O44:O51) -> -91.6
A53: OPEX | B53: =B25+B36+B41+B43+B52 -> -129.98226 | C53: =C25+C36+C41+C43+C52 -> -143.34978 | D53: =D25+D36+D41+D43+D52 -> -142.1515 | E53: =E25+E36+E41+E43+E52 -> -152.77868 | F53: =F25+F36+F41+F43+F52 -> -143.10898 | G53: =G25+G36+G41+G43+G52 -> -141.19004 | H53: =H25+H36+H41+H43+H52 -> -153.18393 | I53: =I25+I36+I41+I43+I52 -> -128.06104 | ... M53: =M25+M36+M41+M43+M52 -> -167.78299 | N53: =SUM(B53:M53) -> -1771.7203 | O53: =O25+O36+O41+O43+O52 -> -1358.2214
A54: EBITDA | B54: =B17+B53 -> 71.474217 | C54: =C17+C53 -> 459.69482 | D54: =D17+D53 -> 728.65098 | E54: =E17+E53 -> 714.2265 | F54: =F17+F53 -> 722.8802 | G54: =G17+G53 -> 723.89076 | H54: =H17+H53 -> 711.94356 | I54: =I17+I53 -> 872.72373 | ... M54: =M17+M53 -> 2059.3527 | N54: =SUM(B54:M54) -> 10823.449 | O54: =O17+O53 -> 8084.6878
A55: Разработка рекламной платформы | B55: =Расходы!C42 -> -42.458922 | C55: =Расходы!D42 -> -43.04558 | D55: =Расходы!E42 -> -44.505901 | E55: =Расходы!F42 -> -44.369799 | F55: =Расходы!G42 -> -44.528812 | G55: =Расходы!H42 -> -44.182905 | H55: =Расходы!I42 -> -47.108845 | I55: =Расходы!J42 -> -46.623045 | ... M55: =Расходы!N42 -> -45.904437 | N55: =SUM(B55:M55) -> -541.03387 | O55: =Расходы!P42 -> -447.2
A56: Проекты Digital Instore (оснащение ТТ) | B56: =Расходы!C43 -> 0 | C56: =Расходы!D43 -> 0 | D56: =Расходы!E43 -> 0 | E56: =Расходы!F43 -> -10.23056 | F56: =Расходы!G43 -> -18.36096 | G56: =Расходы!H43 -> -52.572558 | H56: =Расходы!I43 -> -45.678337 | I56: =Расходы!J43 -> -56.619953 | ... M56: =Расходы!N43 -> -100 | N56: =SUM(B56:M56) -> -609.60587 | O56: =Расходы!P43 -> -732.4
A57: CAPEX | B57: =SUM(B55:B56) -> -42.458922 | C57: =SUM(C55:C56) -> -43.04558 | D57: =SUM(D55:D56) -> -44.505901 | E57: =SUM(E55:E56) -> -54.600359 | F57: =SUM(F55:F56) -> -62.889772 | G57: =SUM(G55:G56) -> -96.755463 | H57: =SUM(H55:H56) -> -92.787183 | I57: =SUM(I55:I56) -> -103.243 | ... O57: =SUM(O55:O56) -> -1179.6
A58: FCF | B58: =B54+B57 -> 29.015294 | C58: =C54+C57 -> 416.64924 | D58: =D54+D57 -> 684.14508 | E58: =E54+E57 -> 659.62614 | F58: =F54+F57 -> 659.99043 | G58: =G54+G57 -> 627.1353 | H58: =H54+H57 -> 619.15637 | I58: =I54+I57 -> 769.48073 | ... M58: =M54+M57 -> 1913.4483 | N58: =SUM(B58:M58) -> 9672.809 | O58: =O54+O57 -> 6905.0878
A60: СПРАВОЧНО
A61: Выручка М+ | B61: ='М+ справочно'!C34 -> 337.89281 | C61: ='М+ справочно'!D34 -> 365.73325 | D61: ='М+ справочно'!E34 -> 377.3919 | E61: ='М+ справочно'!F34 -> 394.58185 | F61: ='М+ справочно'!G34 -> 414.44746 | G61: ='М+ справочно'!H34 -> 435.07252 | H61: ='М+ справочно'!I34 -> 455.65159 | I61: ='М+ справочно'!J34 -> 478.67974 | ... M61: ='М+ справочно'!N34 -> 586.0261 | N61: =SUM(B61:M61) -> 5444.4019 | O61: ='М+ справочно'!P34 -> 3007 | P61: =IFERROR(N61/O61-1,"") -> 0.81057595

Sheet Вводные
A1: ВВОДНЫЕ - АУДИТОРИЯ ПРИЛОЖЕНИЯ | B1: От М+ | R1: Описание: аудитория приложения (DAC) по месяцам: 2026 - факт, 2027 - прогноз М+. Логика: FY = Σ месяцев; доля месяца = DAC месяца / FY 2027 - используется для раскладки годовой выручки APP Медиа по месяцам.
A2: Year | B2: Line 1 | C2: 1 | D2: 2 | E2: 3 | F2: 4 | G2: 5 | H2: 6 | I2: 7 | J2: 8 | K2: 9 | L2: 10 | M2: 11 | N2: 12 | O2: FY
A3: 2026 | B3: DAC, млн чел. | C3: 21.478606 | D3: 21.386288 | E3: 22.602234 | F3: 22.935127 | G3: 24.267083 | H3: 24.884086 | I3: 25.381996 | J3: 25.928896 | K3: 26.261095 | L3: 26.775543 | M3: 27.007095 | N3: 28.106857 | O3: =SUM(C3:N3) -> 297.01491 | Q3: Факт
A4: 2027 | B4: DAC, млн чел. | C4: 27.468361 | D4: 27.419363 | E4: 28.26723 | F4: 28.523836 | G4: 28.980585 | H4: 29.181437 | I4: 29.584271 | J4: 29.800068 | K4: 29.950204 | L4: 30.361134 | M4: 30.534306 | N4: 31.1407 | O4: =SUM(C4:N4) -> 351.2115 | Q4: Прогноз
B6: Доля месяца в объёме | C6: =C4/$O$4 -> 0.078210312 | D6: =D4/$O$4 -> 0.078070803 | E6: =E4/$O$4 -> 0.080484922 | F6: =F4/$O$4 -> 0.081215553 | G6: =G4/$O$4 -> 0.08251605 | H6: =H4/$O$4 -> 0.083087933 | I6: =I4/$O$4 -> 0.084234918 | J6: =J4/$O$4 -> 0.084849353 | ... O6: =O4/$O$4 -> 1
A8: DAC - пользователи, совершившие хотя бы одно действие в приложении. Профиль по месяцам задаёт сезонность выручки.

Sheet DATA
A1: DATA - ПЕРВИЧНЫЕ ДАННЫЕ ПО ПОКАЗАМ И КАМПАНИЯМ
A2: Факт янв–авг 2026 из отчётов даталенз.
A4: 1. ПОКАЗЫ APP ПО ПЛЕЙСМЕНТАМ - ТОЛЬКО AdTech, ФАКТ ЯНВ–АВГ 2026, шт. | M4: Описание: исходные показы AdTech по плейсментам, янв–авг 2026 (даталенз). Логика: итог 8м = Σ месяцев; квота факт = показы AdTech / тотал показов (табл. 2). Используется в «APP Медиа».
A5: Плейсмент | C5: янв | D5: фев | E5: мар | F5: апр | G5: май | H5: июн | I5: июл | J5: авг | K5: Итого 8м | L5: Квота факт
A6: Главная | Hero-Banner | C6: 108751651 | D6: 120234971 | E6: 207868368 | F6: 128867024 | G6: 162792943 | H6: 209915491 | I6: 204852089 | J6: 202538053 | K6: =SUM(C6:J6) -> 1345820590 | L6: =IFERROR(K6/K33,0) -> 0.31211892
A7: Доставка | Категории | C7: 64339578 | D7: 51573093 | E7: 98229351 | F7: 93689400 | G7: 104305180 | H7: 88426327 | I7: 54438687 | J7: 45714667 | K7: =SUM(C7:J7) -> 600716283 | L7: =IFERROR(K7/K34,0) -> 0.56371213
A8: Главная | QR | C8: 103401163 | D8: 84692074 | E8: 51773130 | F8: 36534804 | G8: 37458883 | H8: 39211676 | I8: 41838843 | J8: 43468782 | K8: =SUM(C8:J8) -> 438379355 | L8: =IFERROR(K8/K35,0) -> 0.56157144
A9: Главная | C9: 57723291 | D9: 45723567 | E9: 42867338 | F9: 55101658 | G9: 56349529 | H9: 49654255 | I9: 57138982 | J9: 48851421 | K9: =SUM(C9:J9) -> 413410041 | L9: =IFERROR(K9/K36,0) -> 0.55369609
A10: Доставка | Каталог 1 уровня | C10: 85297467 | D10: 62769757 | E10: 33282253 | F10: 31456586 | G10: 33250726 | H10: 27346069 | I10: 30837230 | J10: 39006865 | K10: =SUM(C10:J10) -> 343246953 | L10: =IFERROR(K10/K37,0) -> 0.49103948
A11: Постчекаут | Онлайн | C11: 39729799 | D11: 36814242 | E11: 22921405 | F11: 23624048 | G11: 23650226 | H11: 23968440 | I11: 19421256 | J11: 34895910 | K11: =SUM(C11:J11) -> 225025326 | L11: =IFERROR(K11/K38,0) -> 0.68732322
A12: Сплешскрин | C12: 1507439 | D12: 11254903 | E12: 10190399 | F12: 25739949 | G12: 26997253 | H12: 26585981 | I12: 50199127 | J12: 19155738 | K12: =SUM(C12:J12) -> 171630789 | L12: =IFERROR(K12/K39,0) -> 0.16565301
A13: Главная | Профиль | C13: 14189577 | D13: 12493652 | E13: 10282061 | F13: 9260885 | G13: 11501486 | H13: 11467352 | I13: 7558322 | J13: 11265492 | K13: =SUM(C13:J13) -> 88018827 | L13: =IFERROR(K13/K40,0) -> 0.76206633
A14: Доставка | Косметик | C14: 11323073 | D14: 12145830 | E14: 11431551 | F14: 5770352 | G14: 6922152 | H14: 6401635 | I14: 4267962 | J14: 8074738 | K14: =SUM(C14:J14) -> 66337293 | L14: =IFERROR(K14/K41,0) -> 0.42127938
A15: В магазине | Акции и каталог розницы | C15: 5459276 | D15: 6092449 | E15: 12593411 | F15: 7380444 | G15: 7685516 | H15: 3988078 | I15: 2254953 | J15: 2817949 | K15: =SUM(C15:J15) -> 48272076 | L15: =IFERROR(K15/K42,0) -> 0.29660541
A16: Доставка экспресс главная | C16: 1765279 | D16: 3439965 | E16: 3563608 | F16: 3829073 | G16: 2621846 | H16: 2831652 | I16: 2858266 | J16: 2195808 | K16: =SUM(C16:J16) -> 23105497 | L16: =IFERROR(K16/K43,0) -> 0.63150421
A17: Главная | Баннер в рекомендациях | C17: 8641675 | D17: 4862984 | E17: 3455250 | F17: 1234565 | G17: 2027552 | H17: 771797 | I17: 594381 | J17: 703133 | K17: =SUM(C17:J17) -> 22291337 | L17: =IFERROR(K17/K44,0) -> 0.35113764
... A28: Эксперимент на Главной (2x2 баннер) | C28: 0 | D28: 0 | E28: 0 | F28: 0 | G28: 0 | H28: 0 | I28: 0 | J28: 0 | K28: =SUM(C28:J28) -> 0 | L28: =IFERROR(K28/K55,0) -> 0
A29: ИТОГО | C29: =SUM(C6:C28) -> 505680199 | D29: =SUM(D6:D28) -> 454279468 | E29: =SUM(E6:E28) -> 511215596 | F29: =SUM(F6:F28) -> 427799020 | G29: =SUM(G6:G28) -> 483474865 | H29: =SUM(H6:H28) -> 492013247 | I29: =SUM(I6:I28) -> 477395515 | J29: =SUM(J6:J28) -> 461543931 | K29: =SUM(K6:K28) -> 3813401841 | L29: =IFERROR(K29/K56,0) -> 0.37002102
A31: 2. ПОКАЗЫ APP ПО ПЛЕЙСМЕНТАМ - ТОТАЛ (все рекламодатели), ФАКТ ЯНВ–АВГ 2026, шт. | M31: Описание: тотал показов всех рекламодателей по плейсментам, янв–авг 2026. Логика: итог 8м = Σ месяцев; база для квоты AdTech и прогноза показов 2027.
A32: Плейсмент | C32: янв | D32: фев | E32: мар | F32: апр | G32: май | H32: июн | I32: июл | J32: авг | K32: Итого 8м
A33: Главная | Hero-Banner | C33: 601719364 | D33: 555654950 | E33: 595700137 | F33: 644446552 | G33: 509861663 | H33: 462252579 | I33: 446280527 | J33: 495968202 | K33: =SUM(C33:J33) -> 4311883974
A34: Доставка | Категории | C34: 74706543 | D34: 64339540 | E34: 170148376 | F34: 200887650 | G34: 177471336 | H34: 176074297 | I34: 114435611 | J34: 87580344 | K34: =SUM(C34:J34) -> 1065643697
A35: Главная | QR | C35: 130262413 | D35: 108921737 | E35: 90713173 | F35: 70286458 | G35: 71196370 | H35: 71280461 | I35: 71141519 | J35: 166827585 | K35: =SUM(C35:J35) -> 780629716
A36: Главная | C36: 84080510 | D36: 88172392 | E36: 80533230 | F36: 94842942 | G36: 94179074 | H36: 95052057 | I36: 106621308 | J36: 103155577 | K36: =SUM(C36:J36) -> 746637090
A37: Доставка | Каталог 1 уровня | C37: 134986016 | D37: 106511411 | E37: 82648980 | F37: 89550875 | G37: 75261204 | H37: 59821055 | I37: 56186105 | J37: 94055442 | K37: =SUM(C37:J37) -> 699021088
A38: Постчекаут | Онлайн | C38: 39729799 | D38: 40148584 | E38: 29196321 | F38: 31478694 | G38: 37398813 | H38: 38221237 | I38: 33611834 | J38: 77608467 | K38: =SUM(C38:J38) -> 327393749
A39: Сплешскрин | C39: 18961577 | D39: 85461168 | E39: 114187249 | F39: 179616122 | G39: 152251557 | H39: 153132074 | I39: 185570597 | J39: 146905811 | K39: =SUM(C39:J39) -> 1036086155
A40: Главная | Профиль | C40: 19573863 | D40: 17761714 | E40: 13804626 | F40: 10902630 | G40: 12900038 | H40: 13679384 | I40: 12806836 | J40: 14071126 | K40: =SUM(C40:J40) -> 115500217
A41: Доставка | Косметик | C41: 27970638 | D41: 27779619 | E41: 20755485 | F41: 14052032 | G41: 14587063 | H41: 13787197 | I41: 12273374 | J41: 26260862 | K41: =SUM(C41:J41) -> 157466270
A42: В магазине | Акции и каталог розницы | C42: 21678655 | D42: 21009966 | E42: 23596349 | F42: 25803769 | G42: 19969747 | H42: 15818330 | I42: 11124296 | J42: 23747358 | K42: =SUM(C42:J42) -> 162748470
A43: Доставка экспресс главная | C43: 2950246 | D43: 5374537 | E43: 5647822 | F43: 4274596 | G43: 4370905 | H43: 4456288 | I43: 4693646 | J43: 4819993 | K43: =SUM(C43:J43) -> 36588033
A44: Главная | Баннер в рекомендациях | C44: 10640661 | D44: 6208138 | E44: 4941827 | F44: 2907389 | G44: 3774871 | H44: 1978707 | I44: 3889858 | J44: 29141738 | K44: =SUM(C44:J44) -> 63483189
... A55: Эксперимент на Главной (2x2 баннер) | C55: 29824330 | D55: 38540242 | E55: 9872031 | F55: 6897916 | G55: 6181995 | H55: 493516 | I55: 237 | J55: 270 | K55: =SUM(C55:J55) -> 91810537
A56: ИТОГО | C56: =SUM(C33:C55) -> 1532899358 | D56: =SUM(D33:D55) -> 1268646495 | E56: =SUM(E33:E55) -> 1300775618 | F56: =SUM(F33:F55) -> 1441701286 | G56: =SUM(G33:G55) -> 1216196265 | H56: =SUM(H33:H55) -> 1125973187 | I56: =SUM(I33:I55) -> 1119764031 | J56: =SUM(J33:J55) -> 1299949666 | K56: =SUM(K33:K55) -> 10305905906
A58: 3. УНИКАЛЬНЫЕ РЕКЛАМНЫЕ КАМПАНИИ APP - ФАКТ ЯНВ–АВГ 2026, ед. | M58: Описание: уникальные рекламные кампании по форматам (медиа, сторис, закрепы). Логика: доля AdTech = кампании AdTech / всего; «В месяц» = среднее за 8 мес. Драйвер объёма для сторис и перформанса.
A59: Показатель | C59: янв | D59: фев | E59: мар | F59: апр | G59: май | H59: июн | I59: июл | J59: авг | K59: Итого 8м | L59: В месяц
A60: Медиа - всего рекламодателей | C60: 2662 | D60: 3136 | E60: 4079 | F60: 4817 | G60: 4587 | H60: 5179 | I60: 5358 | J60: 6364 | K60: =SUM(C60:J60) -> 36182 | L60: =AVERAGE(C60:J60) -> 4522.75
A61: Медиа - AdTech | C61: 895 | D61: 964 | E61: 1113 | F61: 1340 | G61: 1443 | H61: 1685 | I61: 1714 | J61: 1851 | K61: =SUM(C61:J61) -> 11005 | L61: =AVERAGE(C61:J61) -> 1375.625
A62: Доля AdTech | C62: =IFERROR(C61/C60,0) -> 0.33621337 | D62: =IFERROR(D61/D60,0) -> 0.30739796 | E62: =IFERROR(E61/E60,0) -> 0.272861 | F62: =IFERROR(F61/F60,0) -> 0.27818144 | G62: =IFERROR(G61/G60,0) -> 0.3145847 | H62: =IFERROR(H61/H60,0) -> 0.32535238 | I62: =IFERROR(I61/I60,0) -> 0.31989548 | J62: =IFERROR(J61/J60,0) -> 0.29085481 | K62: =IFERROR(K61/K60,0) -> 0.30415676
A64: Сторис - всего рекламодателей | C64: 1336 | D64: 1344 | E64: 1420 | F64: 1650 | G64: 1528 | H64: 1589 | I64: 1693 | J64: 1706 | K64: =SUM(C64:J64) -> 12266 | L64: =AVERAGE(C64:J64) -> 1533.25
A65: Сторис - AdTech | C65: 227 | D65: 208 | E65: 219 | F65: 282 | G65: 255 | H65: 289 | I65: 320 | J65: 315 | K65: =SUM(C65:J65) -> 2115 | L65: =AVERAGE(C65:J65) -> 264.375
A66: Доля AdTech | C66: =IFERROR(C65/C64,0) -> 0.16991018 | D66: =IFERROR(D65/D64,0) -> 0.1547619 | E66: =IFERROR(E65/E64,0) -> 0.15422535 | F66: =IFERROR(F65/F64,0) -> 0.17090909 | G66: =IFERROR(G65/G64,0) -> 0.16688482 | H66: =IFERROR(H65/H64,0) -> 0.18187539 | I66: =IFERROR(I65/I64,0) -> 0.18901359 | J66: =IFERROR(J65/J64,0) -> 0.18464244 | K66: =IFERROR(K65/K64,0) -> 0.17242785
A68: Закрепы (перформанс) - всего рекламодателей | C68: 3678 | D68: 3238 | E68: 3405 | F68: 3063 | G68: 3200 | H68: 3794 | I68: 4558 | J68: 4271 | K68: =SUM(C68:J68) -> 29207 | L68: =AVERAGE(C68:J68) -> 3650.875
A69: Закрепы (перформанс) - AdTech | C69: 2198 | D69: 1619 | E69: 1672 | F69: 1577 | G69: 1532 | H69: 2010 | I69: 2174 | J69: 2155 | K69: =SUM(C69:J69) -> 14937 | L69: =AVERAGE(C69:J69) -> 1867.125
A70: Доля AdTech | C70: =IFERROR(C69/C68,0) -> 0.5976074 | D70: =IFERROR(D69/D68,0) -> 0.5 | E70: =IFERROR(E69/E68,0) -> 0.49104258 | F70: =IFERROR(F69/F68,0) -> 0.51485472 | G70: =IFERROR(G69/G68,0) -> 0.47875 | H70: =IFERROR(H69/H68,0) -> 0.52978387 | I70: =IFERROR(I69/I68,0) -> 0.47696358 | J70: =IFERROR(J69/J68,0) -> 0.50456568 | K70: =IFERROR(K69/K68,0) -> 0.5114185
A72: 4. IN-STORE - ПАРК ОБОРУДОВАНИЯ, ФАКТ 2026 | M72: Описание: парк in-store оборудования 2026 и месяцы работы. Логика: средний парк = Σ(устройства × месяцы) / 12; сверка базового парка с файлом стратегии. Используется в «In-store».
A73: Тип оборудования | B73: Устройств 2026 | C73: Месяцев работы 2026
A74: КСО | B74: 16500 | C74: 12
A75: КСО - новые | B75: 40500 | C75: 3
A76: Шелф-баннеры | B76: 25 | C76: 12
A77: Шелф-баннеры - новые | B77: 2725 | C77: 3
A78: Фасадные экраны | B78: 400 | C78: 12
A79: Фасадные экраны - новые | B79: 831 | C79: 4
A80: TFT | B80: 2310 | C80: 12
A81: Дисплеи покупателя | B81: 6121 | C81: 12
A82: Радио | B82: 3821 | C82: 12
A83: Прайсчекеры | B83: 4408 | C83: 12
A84: Медиа-фасады | B84: 0 | C84: 12
A85: Медиа-фасады - новые | B85: 1 | C85: 4
A86: LED | B86: 79 | C86: 12
A87: Парк на конец 2026, всего | B87: =SUM(B74:B86) -> 77721
A88: в т.ч. базовый парк на начало 2026 | B88: =B74+B76+B78+B80+B81+B82+B83+B84+B86 -> 33664
A89: в т.ч. введено в течение 2026 | B89: =B75+B77+B79+B85 -> 44057
A90: Средний парк 2026, взвешенный по месяцам работы | B90: =SUMPRODUCT(B74:B86,C74:C86)/12 -> 44747.583
A91: Справочно: факт по файлу стратегии, лист «инвентарь» | B91: 34638
A92: Отклонение базового парка от стратегии | B92: =B88-B91 -> -974

Sheet ПРАЙС
A1: ПРАЙС - ЦЕНЫ РАЗМЕЩЕНИЙ | B1: Описание: прайс-лист размещений APP до и после 09.2026. Цены используются в «APP Медиа» и «APP Перформанс».
A3: 1. APP - ПРАЙС-ЛИСТ РАЗМЕЩЕНИЙ
A4: Прайс-позиция | B4: Тип формата | C4: Модель оплаты | D4: Цена до 09.2026, ₽ | E4: Цена с 09.2026, ₽ | F4: Рост | G4: Инкремент, ₽/мес
A5: Брендированная именная категория | B5: Перфоманс | C5: CPD | D5: 80000 | E5: 90000 | F5: =IFERROR(E5/D5-1,"") -> 0.125 | G5: 3125000
A6: Splash screen | B6: Медийный инвентарь | C6: CPM | D6: 600 | E6: 600 | F6: =IFERROR(E6/D6-1,"") -> 0 | G6: 0
A7: Hero-баннер | B7: Медийный инвентарь | C7: CPM | D7: 600 | E7: 600 | F7: =IFERROR(E7/D7-1,"") -> 0 | G7: 0
A8: Баннер на странице оформления заказа | B8: Медийный инвентарь | C8: CPM | D8: 450 | E8: 450 | F8: =IFERROR(E8/D8-1,"") -> 0 | G8: 8100000
A9: Баннер в листинге рекомендаций | B9: Медийный инвентарь | C9: CPM | D9: 350 | E9: 400 | F9: =IFERROR(E9/D9-1,"") -> 0.14285714 | G9: 175000
A10: Баннер над профилем пользователя | B10: Медийный инвентарь | C10: CPM | D10: 350 | E10: 400 | F10: =IFERROR(E10/D10-1,"") -> 0.14285714 | G10: 1200000
A11: В магазине | Акции и каталог розницы | B11: Медийный инвентарь | C11: CPM | D11: 350 | E11: 400 | F11: =IFERROR(E11/D11-1,"") -> 0.14285714 | G11: 1550000
A12: Баннеры в категориях и подкатегориях | B12: Медийный инвентарь | C12: CPM | D12: 350 | E12: 400 | F12: =IFERROR(E12/D12-1,"") -> 0.14285714 | G12: 12000000
A13: Баннер на первом экране Магнит Маркета | B13: Медийный инвентарь | C13: CPM | D13: 350 | E13: 400 | F13: =IFERROR(E13/D13-1,"") -> 0.14285714 | G13: 0
A14: Баннер в листинге Магнит Маркета | B14: Медийный инвентарь | C14: CPM | D14: 350 | E14: 400 | F14: =IFERROR(E14/D14-1,"") -> 0.14285714 | G14: 0
A15: Подборка в разделе «Покупайте с выгодой» | B15: Перфоманс | C15: CPD | D15: 90000 | E15: 110000 | F15: =IFERROR(E15/D15-1,"") -> 0.22222222 | G15: 3977777.8
A16: Доставка | Экспресс Самовывоз | Экспресс | B16: Медийный инвентарь | C16: CPM | D16: 350 | E16: 400 | F16: =IFERROR(E16/D16-1,"") -> 0.14285714 | G16: 4550000
... A63: А/b-тестирование новых форматов рекламы | B63: Дополнительные услуги | C63: CPM | D63: 100 | E63: 100 | F63: =IFERROR(E63/D63-1,"") -> 0 | G63: 0
A64: ИТОГО инкремент прайса, ₽/мес | G64: =SUM(G5:G63) -> 1.2934206e+08
A66: 2. СВОДКА ИНКРЕМЕНТОВ ПО ТИПАМ ИНВЕНТАРЯ | H66: Описание: инкремент нового прайса по типам инвентаря. Логика: SUMIFS инкремента из табл. 1 по типу формата и модели оплаты; «Прочее» = итог − три группы. Используется в «APP Перформанс» (блок 4).
A68: Медийный инвентарь, CPM | G68: =SUMIFS($G$5:$G$63,$B$5:$B$63,"Медийный инвентарь",$C$5:$C$63,"CPM") -> 89325000
A69: Медийный инвентарь, CPD (сторис) | G69: =SUMIFS($G$5:$G$63,$B$5:$B$63,"Медийный инвентарь",$C$5:$C$63,"CPD") -> 7200000
A70: Перформанс, CPD | G70: =SUMIFS($G$5:$G$63,$B$5:$B$63,"Перфоманс",$C$5:$C$63,"CPD") -> 32817063
A71: Прочее (clickout, пакеты, доп. услуги) | G71: =G64-SUMIFS($G$5:$G$63,$B$5:$B$63,"Медийный инвентарь",$C$5:$C$63,"CPM")-SUMIFS($G$5:$G$63,$B$5:$B$63,"Медийный инвентарь",$C$5:$C$63,"CPD")-SUMIFS($G$5:$G$63,$B$5:$B$63,"Перфоманс",$C$5:$C$63,"CPD") -> 0
A72: ИТОГО | G72: =SUM(G68:G71) -> 1.2934206e+08
A74: 3. IN-STORE - СРЕДНИЙ ДОХОД НА УСТРОЙСТВО В МЕСЯЦ, ₽ | H74: Описание: средний доход на устройство в месяц по типам оборудования, 2026 и 2027 (ввод). Логика: изменение = 2027 / 2026 − 1. Используется в «In-store».
A75: Тип оборудования | B75: 2026 | C75: 2027 | D75: Изменение
A76: КСО | B76: 4809 | C76: 2885.4 | D76: =IFERROR(C76/B76-1,"") -> -0.4
A77: КСО - новые | B77: 4809 | C77: 2885.4 | D77: =IFERROR(C77/B77-1,"") -> -0.4
A78: Шелф-баннеры | B78: 28800 | C78: 30240 | D78: =IFERROR(C78/B78-1,"") -> 0.05
A79: Шелф-баннеры - новые | B79: 28800 | C79: 30240 | D79: =IFERROR(C79/B79-1,"") -> 0.05
A80: Фасадные экраны | B80: 30214 | C80: 24171.2 | D80: =IFERROR(C80/B80-1,"") -> -0.2
A81: Фасадные экраны - новые | B81: 30214 | C81: 24171.2 | D81: =IFERROR(C81/B81-1,"") -> -0.2
A82: TFT | B82: 14350 | C82: 11480 | D82: =IFERROR(C82/B82-1,"") -> -0.2
A83: Дисплеи покупателя | B83: 1784 | C83: 1784 | D83: =IFERROR(C83/B83-1,"") -> 0
A84: Радио | B84: 506 | C84: 2024 | D84: =IFERROR(C84/B84-1,"") -> 3
A85: Прайсчекеры | B85: 1112 | C85: 1112 | D85: =IFERROR(C85/B85-1,"") -> 0
A86: Медиа-фасады | B86: 200000 | C86: 240000 | D86: =IFERROR(C86/B86-1,"") -> 0.2
A87: Медиа-фасады - новые | B87: 200000 | C87: 240000 | D87: =IFERROR(C87/B87-1,"") -> 0.2
A88: LED | B88: 7136 | C88: 7136 | D88: =IFERROR(C88/B88-1,"") -> 0
A90: 4. CONTENT FACTORY - ЦЕНА ПРОСМОТРА | H90: Описание: цена просмотра и ставка креатора для Content factory. Логика: цена 2027 = цена 2026 × (1 + коэффициент в строке 92); ставка = 60 000 / 0,94 (гросс-ап под НПД).
A91: Рыночная цена просмотра 2026, руб. | B91: 0.75
A92: НПД
A93: Рыночная цена просмотра 2027, руб. | B93: =B91*(1+B92) -> 0.75
A94: Ставка креатора в месяц, руб. | B94: =60000/0.94 -> 63829.787

Sheet APP Медиа
A1: APP МЕДИА - БЮДЖЕТ 2027
A2: Выручка считается по каждому плейсменту его собственным CPM. Сторис - медийный инвентарь с оплатой по CPD. Суммы в млн руб. без НДС.
A4: Сезонные коэффициенты цены | B4: 1 | C4: 1 - цена месяца умножается на сезонный коэффициент. 0 - цена равна прайсу во всех месяцах.
A5: Месяц | B5: янв | C5: фев | D5: мар | E5: апр | F5: май | G5: июн | H5: июл | I5: авг | J5: сен | K5: окт | L5: ноя | M5: дек | N5: Сумма за год
A6: Коэффициент | B6: 1 | C6: 1.1 | D6: 1.2 | E6: 1.1 | F6: 1.2 | G6: 1 | H6: 1 | I6: 1.1 | J6: 1.1 | K6: 1.2 | L6: 1.4 | M6: 1.7 | N6: =SUM(B6:M6) -> 14.1
A8: ДРАЙВЕРЫ АУДИТОРИИ | C8: Описание: драйверы аудитории для прогноза показов. Логика: пересчёт 8м → год = DAC 2026 за год / DAC янв–авг; рост 2027 = DAC 2027 / DAC 2026 − 1 (из «Вводные»).
A9: Показатель | B9: Значение
A10: DAC-месяцев 2026, всего | B10: =Вводные!O3 -> 297.01491
A11: DAC-месяцев 2026, январь-август | B11: =SUM(Вводные!C3:J3) -> 188.86432
A12: DAC-месяцев 2027, всего | B12: =Вводные!O4 -> 351.2115
A13: Коэффициент пересчёта 8 месяцев в год 2026 | B13: =B10/B11 -> 1.5726364
A14: Рост аудитории 2027 к 2026 | B14: =B12/B10-1 -> 0.18247094
A15: Индекс роста показов на 1 DAC | B15: 1
A17: 1. ПЛЕЙСМЕНТЫ CPM - ФАКТ 2026 И ПЛАН 2027 | L17: Описание: выручка CPM-плейсментов 2026 и 2027. Логика: квота = показы AdTech / тотал (DATA); показы 2027 = тотал 8м × пересчёт в год × (1 + рост аудитории) × индекс показов × квота 2027; выручка = показы × CPM (ПРАЙС) / 10⁹; в 2026 сен–дек - по новому CPM.
A18: Плейсмент | B18: Показы тотал 8м 2026 | C18: Показы AdTech 8м 2026 | D18: Квота факт | E18: Квота 2027 | F18: CPM старый | G18: CPM новый | H18: Показы AdTech 2026, год | I18: Показы AdTech 2027 | J18: Выручка 2026 | K18: Выручка 2027
A19: Главная | Hero-Banner | B19: =DATA!K33 -> 4311883974 | C19: =DATA!K6 -> 1345820590 | D19: =IFERROR(C19/B19,0) -> 0.31211892 | E19: =D19 -> 0.31211892 | F19: =ПРАЙС!D7 -> 600 | G19: =ПРАЙС!E7 -> 600 | H19: =C19*'APP Медиа'!$B$13 -> 2.1164865e+09 | I19: 2.2944007e+09 | J19: =(C19*F19+(H19-C19)*G19)/1000000000 -> 1269.8919 | K19: =I19*G19/1000000000 -> 1376.6404
A20: Доставка | Категории | B20: =DATA!K34 -> 1065643697 | C20: =DATA!K7 -> 600716283 | D20: =IFERROR(C20/B20,0) -> 0.56371213 | E20: =D20 -> 0.56371213 | F20: =ПРАЙС!D12 -> 350 | G20: =ПРАЙС!E12 -> 400 | H20: =C20*'APP Медиа'!$B$13 -> 9.4470832e+08 | I20: 1.0241216e+09 | J20: =(C20*F20+(H20-C20)*G20)/1000000000 -> 347.84751 | K20: =I20*G20/1000000000 -> 409.64863
A21: Главная | QR | B21: =DATA!K35 -> 780629716 | C21: =DATA!K8 -> 438379355 | D21: =IFERROR(C21/B21,0) -> 0.56157144 | E21: =D21 -> 0.56157144 | F21: =ПРАЙС!D21 -> 450 | G21: =ПРАЙС!E21 -> 600 | H21: =C21*'APP Медиа'!$B$13 -> 6.8941135e+08 | I21: 7.4736405e+08 | J21: =(C21*F21+(H21-C21)*G21)/1000000000 -> 347.88991 | K21: =I21*G21/1000000000 -> 448.41843
A22: Главная (модальное окно) | B22: =DATA!K36 -> 746637090 | C22: =DATA!K9 -> 413410041 | D22: =IFERROR(C22/B22,0) -> 0.55369609 | E22: =D22 -> 0.55369609 | F22: =ПРАЙС!D39 -> 600 | G22: =ПРАЙС!E39 -> 1000 | H22: =C22*'APP Медиа'!$B$13 -> 6.501437e+08 | I22: 7.0479551e+08 | J22: =(C22*F22+(H22-C22)*G22)/1000000000 -> 484.77968 | K22: =I22*G22/1000000000 -> 704.79551
A23: Доставка | Каталог 1 уровня | B23: =DATA!K37 -> 699021088 | C23: =DATA!K10 -> 343246953 | D23: =IFERROR(C23/B23,0) -> 0.49103948 | E23: =D23 -> 0.49103948 | F23: =ПРАЙС!D12 -> 350 | G23: =ПРАЙС!E12 -> 400 | H23: =C23*'APP Медиа'!$B$13 -> 5.3980267e+08 | I23: 5.8517909e+08 | J23: =(C23*F23+(H23-C23)*G23)/1000000000 -> 198.75872 | K23: =I23*G23/1000000000 -> 234.07164
A24: Постчекаут | Онлайн | B24: =DATA!K38 -> 327393749 | C24: =DATA!K11 -> 225025326 | D24: =IFERROR(C24/B24,0) -> 0.68732322 | E24: =D24 -> 0.68732322 | F24: =ПРАЙС!D8 -> 450 | G24: =ПРАЙС!E8 -> 450 | H24: =C24*'APP Медиа'!$B$13 -> 3.5388303e+08 | I24: 3.8363083e+08 | J24: =(C24*F24+(H24-C24)*G24)/1000000000 -> 159.24736 | K24: =I24*G24/1000000000 -> 172.63388
A25: Сплешскрин | B25: =DATA!K39 -> 1036086155 | C25: =DATA!K12 -> 171630789 | D25: =IFERROR(C25/B25,0) -> 0.16565301 | E25: =D25 -> 0.16565301 | F25: =ПРАЙС!D6 -> 600 | G25: =ПРАЙС!E6 -> 600 | H25: =C25*'APP Медиа'!$B$13 -> 2.6991283e+08 | I25: 2.9260201e+08 | J25: =(C25*F25+(H25-C25)*G25)/1000000000 -> 161.9477 | K25: =I25*G25/1000000000 -> 175.56121
A26: Главная | Профиль | B26: =DATA!K40 -> 115500217 | C26: =DATA!K13 -> 88018827 | D26: =IFERROR(C26/B26,0) -> 0.76206633 | E26: =D26 -> 0.76206633 | F26: =ПРАЙС!D10 -> 350 | G26: =ПРАЙС!E10 -> 400 | H26: =C26*'APP Медиа'!$B$13 -> 1.3842161e+08 | I26: 1.5005749e+08 | J26: =(C26*F26+(H26-C26)*G26)/1000000000 -> 50.967705 | K26: =I26*G26/1000000000 -> 60.022997
A27: Доставка | Косметик | B27: =DATA!K41 -> 157466270 | C27: =DATA!K14 -> 66337293 | D27: =IFERROR(C27/B27,0) -> 0.42127938 | E27: =D27 -> 0.42127938 | F27: =ПРАЙС!D40 -> 600 | G27: =ПРАЙС!E40 -> 1000 | H27: =C27*'APP Медиа'!$B$13 -> 1.0432444e+08 | I27: 1.1309407e+08 | J27: =(C27*F27+(H27-C27)*G27)/1000000000 -> 77.789527 | K27: =I27*G27/1000000000 -> 113.09407
A28: В магазине | Акции и каталог розницы | B28: =DATA!K42 -> 162748470 | C28: =DATA!K15 -> 48272076 | D28: =IFERROR(C28/B28,0) -> 0.29660541 | E28: =D28 -> 0.29660541 | F28: =ПРАЙС!D11 -> 350 | G28: =ПРАЙС!E11 -> 400 | H28: =C28*'APP Медиа'!$B$13 -> 75914426 | I28: 82295878 | J28: =(C28*F28+(H28-C28)*G28)/1000000000 -> 27.952167 | K28: =I28*G28/1000000000 -> 32.918351
A29: Доставка экспресс главная | B29: =DATA!K43 -> 36588033 | C29: =DATA!K16 -> 23105497 | D29: =IFERROR(C29/B29,0) -> 0.63150421 | E29: =D29 -> 0.63150421 | F29: =ПРАЙС!D16 -> 350 | G29: =ПРАЙС!E16 -> 400 | H29: =C29*'APP Медиа'!$B$13 -> 36336547 | I29: 39391038 | J29: =(C29*F29+(H29-C29)*G29)/1000000000 -> 13.379344 | K29: =I29*G29/1000000000 -> 15.756415
A30: Главная | Баннер в рекомендациях | B30: =DATA!K44 -> 63483189 | C30: =DATA!K17 -> 22291337 | D30: =IFERROR(C30/B30,0) -> 0.35113764 | E30: =D30 -> 0.35113764 | F30: =ПРАЙС!D9 -> 350 | G30: =ПРАЙС!E9 -> 400 | H30: =C30*'APP Медиа'!$B$13 -> 35056169 | I30: 38003030 | J30: =(C30*F30+(H30-C30)*G30)/1000000000 -> 12.907901 | K30: =I30*G30/1000000000 -> 15.201212
A31: Прочие плейсменты | B31: =DATA!K45 -> 19689206 | C31: =DATA!K18 -> 9864551 | D31: =IFERROR(C31/B31,0) -> 0.50101314 | E31: =D31 -> 0.50101314 | F31: 400 | G31: 450 | H31: =C31*'APP Медиа'!$B$13 -> 15513352 | I31: 16817422 | J31: =(C31*F31+(H31-C31)*G31)/1000000000 -> 6.487781 | K31: =I31*G31/1000000000 -> 7.56784
A32: Постчекаут | Маркет | B32: =DATA!K46 -> 4678593 | C32: =DATA!K19 -> 4678593 | D32: =IFERROR(C32/B32,0) -> 1 | E32: =D32 -> 1 | F32: =ПРАЙС!D8 -> 450 | G32: =ПРАЙС!E8 -> 450 | H32: =C32*'APP Медиа'!$B$13 -> 7357725.9 | I32: 7976224.6 | J32: =(C32*F32+(H32-C32)*G32)/1000000000 -> 3.3109766 | K32: =I32*G32/1000000000 -> 3.5893011
A33: В магазине | Категории | B33: =DATA!K47 -> 150435958 | C33: =DATA!K20 -> 4052095 | D33: =IFERROR(C33/B33,0) -> 0.026935681 | E33: =D33 -> 0.026935681 | F33: =ПРАЙС!D11 -> 350 | G33: =ПРАЙС!E11 -> 400 | H33: =C33*'APP Медиа'!$B$13 -> 6372472.3 | I33: 6908149.5 | J33: =(C33*F33+(H33-C33)*G33)/1000000000 -> 2.3463842 | K33: =I33*G33/1000000000 -> 2.7632598
A34: Доставка косметик главная | B34: =DATA!K48 -> 6837543 | C34: =DATA!K21 -> 3360036 | D34: =IFERROR(C34/B34,0) -> 0.49140985 | E34: =D34 -> 0.49140985 | F34: =ПРАЙС!D40 -> 600 | G34: =ПРАЙС!E40 -> 1000 | H34: =C34*'APP Медиа'!$B$13 -> 5284115.1 | I34: 5728303.7 | J34: =(C34*F34+(H34-C34)*G34)/1000000000 -> 3.9401007 | K34: =I34*G34/1000000000 -> 5.7283037
A35: Доставка гипер главная | B35: =DATA!K49 -> 3635345 | C35: =DATA!K22 -> 2382744 | D35: =IFERROR(C35/B35,0) -> 0.6554382 | E35: =D35 -> 0.6554382 | F35: =ПРАЙС!D16 -> 350 | G35: =ПРАЙС!E16 -> 400 | H35: =C35*'APP Медиа'!$B$13 -> 3747190 | I35: 4062183.1 | J35: =(C35*F35+(H35-C35)*G35)/1000000000 -> 1.3797388 | K35: =I35*G35/1000000000 -> 1.6248732
A36: Маркет | Главный экран | B36: =DATA!K50 -> 4538152 | C36: =DATA!K23 -> 1492219 | D36: =IFERROR(C36/B36,0) -> 0.32881644 | E36: =D36 -> 0.32881644 | F36: =ПРАЙС!D13 -> 350 | G36: =ПРАЙС!E13 -> 400 | H36: =C36*'APP Медиа'!$B$13 -> 2346718 | I36: 2543985.7 | J36: =(C36*F36+(H36-C36)*G36)/1000000000 -> 0.86407624 | K36: =I36*G36/1000000000 -> 1.0175943
A37: Доставка | Мигом | B37: =DATA!K51 -> 18231325 | C37: =DATA!K24 -> 1034774 | D37: =IFERROR(C37/B37,0) -> 0.056758025 | E37: =D37 -> 0.056758025 | F37: =ПРАЙС!D17 -> 350 | G37: =ПРАЙС!E17 -> 400 | H37: =C37*'APP Медиа'!$B$13 -> 1627323.3 | I37: 1764117.9 | J37: =(C37*F37+(H37-C37)*G37)/1000000000 -> 0.59919062 | K37: =I37*G37/1000000000 -> 0.70564717
A38: Доставка | Рестораны | B38: =DATA!K52 -> 8689939 | C38: =DATA!K25 -> 187684 | D38: =IFERROR(C38/B38,0) -> 0.02159785 | E38: =D38 -> 0.02159785 | F38: =ПРАЙС!D19 -> 350 | G38: =ПРАЙС!E19 -> 400 | H38: =C38*'APP Медиа'!$B$13 -> 295158.7 | I38: 319970.07 | J38: =(C38*F38+(H38-C38)*G38)/1000000000 -> 0.10867928 | K38: =I38*G38/1000000000 -> 0.12798803
A39: ИТОГО | B39: =SUM(B19:B38) -> 9719817709 | C39: =SUM(C19:C38) -> 3813307063 | D39: =IFERROR(C39/B39,0) -> 0.3923229 | E39: =IFERROR(I39/(B39*'APP Медиа'!$B$13*(1+'APP Медиа'!$B$14)*'APP Медиа'!$B$15),0) -> 0.35967227 | F39: =IFERROR(SUMPRODUCT(C19:C38,F19:F38)/C39,0) -> 498.80555 | G39: =IFERROR(SUMPRODUCT(I19:I38,G19:G38)/I39,0) -> 581.73438 | H39: =SUM(H19:H38) -> 5.9969457e+09 | I39: =SUM(I19:I38) -> 6.5010557e+09 | J39: =SUM(J19:J38) -> 3172.3964 | K39: =SUM(K19:K38) -> 3781.8876 | M39: CPM в колонках F и G взвешен по фактической структуре показов
A41: 2. СТОРИС - МЕДИЙНЫЙ ИНВЕНТАРЬ С ОПЛАТОЙ ПО CPD | L41: Описание: выручка сторис (оплата за день, CPD). Логика: кампании AdTech в месяц (DATA; 2027 = × (1 + рост аудитории)) × дней на кампанию × CPD (ПРАЙС) × 12 мес; 2026 = 8 мес по старому CPD + 4 мес по новому.
A42: Показатель | B42: 2026 | C42: 2027 | D42: Ед. изм.
A43: Уникальных кампаний AdTech в месяц | B43: =DATA!L65 -> 264.375 | C43: =B43*(1+'APP Медиа'!$B$14) -> 312.61576 | D43: ед. | M43: Среднемесячное число кампаний AdTech в сторис
A44: Размещений-дней на 1 кампанию в месяц | B44: 0.91 | C44: =B44 -> 0.91 | D44: дн.
A45: CPD сторис, ₽ | B45: =ПРАЙС!D22 -> 70000 | C45: =ПРАЙС!E22 -> 100000 | D45: ₽ | M45: CPD сторис - лист «ПРАЙС», строка «Сторис»
A46: ВЫРУЧКА СТОРИС, млн ₽ | B46: =(B43*B44*(8*B45+4*C45))/1000000 -> 230.958 | C46: =(C43*C44*12*C45)/1000000 -> 341.3764 | D46: млн ₽
A48: 3. ВЫРУЧКА МЕДИА ПО МЕСЯЦАМ | R48: Описание: помесячная выручка APP Медиа 2027. Логика: годовая выручка блоков 1–2 × доля месяца по DAC («Вводные») × сезонный коэффициент цены (вкл/выкл в B4). Итог идёт в P&L, строка APP.
A49: Показатель | B49: Ед. изм. | C49: янв | D49: фев | E49: мар | F49: апр | G49: май | H49: июн | I49: июл | J49: авг | K49: сен | L49: окт | M49: ноя | N49: дек | O49: 2027 | P49: 2026 | Q49: Комментарий
A50: Доля месяца в объёме (по DAC) | B50: % | C50: =Вводные!C6 -> 0.078210312 | D50: =Вводные!D6 -> 0.078070803 | E50: =Вводные!E6 -> 0.080484922 | F50: =Вводные!F6 -> 0.081215553 | G50: =Вводные!G6 -> 0.08251605 | H50: =Вводные!H6 -> 0.083087933 | I50: =Вводные!I6 -> 0.084234918 | J50: =Вводные!J6 -> 0.084849353 | ... N50: =Вводные!N6 -> 0.088666517 | O50: =SUM(C50:N50) -> 1 | Q50: Внутри года выручка распределяется так же, как растёт аудитория
A51: Сезонный коэффициент цены (с учётом календаризации) | B51: × | C51: 0.30166696 | D51: 0.75551507 | E51: 1.0259951 | F51: 1.016765 | G51: 1.0007403 | H51: 0.99385232 | I51: 0.98031953 | J51: 1.1122521 | K51: 1.1066765 | L51: 1.5010847 | M51: 1.8996364 | N51: 2.2617836 | O51: =IF('APP Медиа'!$B$4=1,N6,1) -> 14.1 | Q51: Цена месяца × коэффициент. Выключатель - ячейка B4 сверху
A52: Медиа CPM - выручка | B52: млн ₽ | C52: =$K$39*C50*C51 -> 89.227841 | D52: =$K$39*D50*D51 -> 223.0696 | E52: =$K$39*E50*E51 -> 312.29744 | F52: =$K$39*F50*F51 -> 312.29744 | G52: =$K$39*G50*G51 -> 312.29744 | H52: =$K$39*H50*H51 -> 312.29744 | I52: =$K$39*I50*I51 -> 312.29744 | J52: =$K$39*J50*J51 -> 356.91136 | ... N52: =$K$39*N50*N51 -> 758.43665 | O52: =SUM(C52:N52) -> 4461.392 | P52: =J39 -> 3172.3964 | Q52: Годовая выручка по CPM, разложенная по месяцам
A53: Сторис CPD - выручка | B53: млн ₽ | C53: =$C$46*C50*C51 -> 8.054253 | D53: =$C$46*D50*D51 -> 20.135633 | E53: =$C$46*E50*E51 -> 28.189886 | F53: =$C$46*F50*F51 -> 28.189886 | G53: =$C$46*G50*G51 -> 28.189886 | H53: =$C$46*H50*H51 -> 28.189886 | I53: =$C$46*I50*I51 -> 28.189886 | J53: =$C$46*J50*J51 -> 32.217012 | ... N53: =$C$46*N50*N51 -> 68.461151 | O53: =SUM(C53:N53) -> 402.71265 | P53: =B46 -> 230.958 | Q53: Годовая выручка сторис, разложенная по месяцам
A54: ВЫРУЧКА APP МЕДИА | B54: млн ₽ | C54: =C52+C53 -> 97.282094 | D54: =D52+D53 -> 243.20523 | E54: =E52+E53 -> 340.48733 | F54: =F52+F53 -> 340.48733 | G54: =G52+G53 -> 340.48733 | H54: =H52+H53 -> 340.48733 | I54: =I52+I53 -> 340.48733 | J54: =J52+J53 -> 389.12837 | ... N54: =N52+N53 -> 826.8978 | O54: =SUM(C54:N54) -> 4864.1047 | P54: =SUM(P52:P53)*N6/12 -> 3998.9414 | Q54: Итого медиа: CPM + сторис

Sheet APP Перформанс
A1: APP ПЕРФОРМАНС - БЮДЖЕТ 2027
A2: Закрепы монетизируются по CPD. Драйвер объёма - уникальные кампании в месяц. Суммы в млн руб. без НДС.
A4: ПЕРЕКЛЮЧАТЕЛИ
A5: Сезонные коэффициенты цены | B5: 1 | C5: 1 - цена месяца умножается на коэффициент. 0 - цена равна прайсу во всех месяцах.
A7: Месяц | B7: янв | C7: фев | D7: мар | E7: апр | F7: май | G7: июн | H7: июл | I7: авг | J7: сен | K7: окт | L7: ноя | M7: дек | N7: Сумма за год
A8: Коэффициент | B8: 1 | C8: 1.1 | D8: 1.2 | E8: 1.1 | F8: 1.2 | G8: 1 | H8: 1 | I8: 1.1 | J8: 1.1 | K8: 1.2 | L8: 1.4 | M8: 1.7 | N8: =SUM(B8:M8) -> 14.1
A10: Рост аудитории 2027 к 2026 | B10: ='APP Медиа'!B14 -> 0.18247094
A13: 1. ДРАЙВЕРЫ | Q13: Описание: драйверы перформанса (закрепы, CPD). Логика: кампании AdTech 2026 (DATA) → 2027 = × (1 + рост аудитории); средний чек 2027 = чек по старому прайсу (блок 3) × индексация нового прайса (блок 4); сезонность - по переключателю B5.
A14: Показатель | B14: Ед. изм. | C14: янв | D14: фев | E14: мар | F14: апр | G14: май | H14: июн | I14: июл | J14: авг | K14: сен | L14: окт | M14: ноя | N14: дек | O14: 2027 | P14: 2026
A15: Уникальных кампаний AdTech, 2026 | B15: ед. | C15: =DATA!C69 -> 2198 | D15: =DATA!D69 -> 1619 | E15: =DATA!E69 -> 1672 | F15: =DATA!F69 -> 1577 | G15: =DATA!G69 -> 1532 | H15: =DATA!H69 -> 2010 | I15: =DATA!I69 -> 2174 | J15: =DATA!J69 -> 2155 | K15: =J15*1.02 -> 2198.1 | L15: =K15*1.047 -> 2301.4107 | M15: =L15*1.05 -> 2416.4812 | N15: =M15*1.05 -> 2537.3053 | O15: =AVERAGE(C15:N15) -> 2032.5248
A16: Уникальных кампаний AdTech, 2027 | B16: ед. | C16: 662.1915 | D16: 1504.9807 | E16: 1931.3919 | F16: 2106.973 | G16: 1931.3919 | H16: 2317.6702 | I16: 2317.6702 | J16: 2407.9691 | K16: 2407.9691 | L16: 3035.0444 | M16: 3310.9575 | N16: 3310.9575 | O16: =AVERAGE(C16:N16) -> 2270.4306
A17: Средний чек кампании в месяц, старый прайс | B17: ₽ | C17: =$O$35 -> 67961.827 | D17: =$O$35 -> 67961.827 | E17: =$O$35 -> 67961.827 | F17: =$O$35 -> 67961.827 | G17: =$O$35 -> 67961.827 | H17: =$O$35 -> 67961.827 | I17: =$O$35 -> 67961.827 | J17: =$O$35 -> 67961.827 | ... N17: =$O$35 -> 67961.827 | O17: =AVERAGE(C17:N17) -> 67961.827
A18: Индексация чека по новому прайсу | B18: × | C18: =$O$48 -> 1.2586195 | D18: =$O$48 -> 1.2586195 | E18: =$O$48 -> 1.2586195 | F18: =$O$48 -> 1.2586195 | G18: =$O$48 -> 1.2586195 | H18: =$O$48 -> 1.2586195 | I18: =$O$48 -> 1.2586195 | J18: =$O$48 -> 1.2586195 | ... N18: =$O$48 -> 1.2586195 | O18: =AVERAGE(C18:N18) -> 1.2586195
A19: Средний чек кампании в месяц, 2027 | B19: ₽ | C19: =C17*C18 -> 85538.081 | D19: =D17*D18 -> 85538.081 | E19: =E17*E18 -> 85538.081 | F19: =F17*F18 -> 85538.081 | G19: =G17*G18 -> 85538.081 | H19: =H17*H18 -> 85538.081 | I19: =I17*I18 -> 85538.081 | J19: =J17*J18 -> 85538.081 | ... N19: =N17*N18 -> 85538.081 | O19: =AVERAGE(C19:N19) -> 85538.081
A20: Сезонный коэффициент цены | B20: × | C20: =IF($B$5=1,B8,1) -> 1 | D20: =IF($B$5=1,C8,1) -> 1.1 | E20: =IF($B$5=1,D8,1) -> 1.2 | F20: =IF($B$5=1,E8,1) -> 1.1 | G20: =IF($B$5=1,F8,1) -> 1.2 | H20: =IF($B$5=1,G8,1) -> 1 | I20: =IF($B$5=1,H8,1) -> 1 | J20: =IF($B$5=1,I8,1) -> 1.1 | ... N20: =IF($B$5=1,M8,1) -> 1.7
A22: 2. ВЫРУЧКА | Q22: Описание: выручка перформанса по месяцам. Логика: кампании × средний чек × сезонный коэффициент / 10⁶. Строка 2027 идёт в P&L, строка APP.
A23: Выручка перформанса 2026 | B23: млн ₽ | C23: =C15*C17*C20/1000000 -> 149.3801 | D23: =D15*D17*D20/1000000 -> 121.03322 | E23: =E15*E17*E20/1000000 -> 136.35861 | F23: =F15*F17*F20/1000000 -> 117.89338 | G23: =G15*G17*G20/1000000 -> 124.94102 | H23: =H15*H17*H20/1000000 -> 136.60327 | I23: =I15*I17*I20/1000000 -> 147.74901 | J23: =J15*J17*J20/1000000 -> 161.10351 | K23: =K15*K17*K18*K20/1000000 -> 206.82338 | L23: =L15*L17*L18*L20/1000000 -> 236.22991 | M23: =M15*M17*M18*M20/1000000 -> 289.38164 | N23: =N15*N17*N18*N20/1000000 -> 368.96159 | O23: =SUM(C23:N23) -> 2196.4586
A24: ВЫРУЧКА ПЕРФОРМАНСА 2027 | B24: млн ₽ | C24: =C16*C19*C20/1000000 -> 56.64259 | D24: =D16*D19*D20/1000000 -> 141.60648 | E24: =E16*E19*E20/1000000 -> 198.24907 | F24: =F16*F19*F20/1000000 -> 198.24907 | G24: =G16*G19*G20/1000000 -> 198.24907 | H24: =H16*H19*H20/1000000 -> 198.24907 | I24: =I16*I19*I20/1000000 -> 198.24907 | J24: =J16*J19*J20/1000000 -> 226.57036 | ... N24: =N16*N19*N20/1000000 -> 481.46202 | O24: =SUM(C24:N24) -> 2832.1295 | P24: =O23 -> 2196.4586
A26: 3. РАСЧЁТ СРЕДНЕГО ЧЕКА КАМПАНИИ (калибровка на факт 2026) | Q26: Описание: калибровка среднего чека на факт 2026. Логика: выручка перформанса = APP 2026 − APP Медиа 2026; чек = (остаток − надбавка нового прайса за сен–дек) / Σ(кампании × сезонность).
A27: Выручка перформанса не наблюдается напрямую: в отчётности APP она сидит внутри общей выручки. Считаем её как остаток и делим на кампании-месяцы.
A28: APP факт + прогноз 2026 | O28: 6195.4
A29: минус выручка APP Медиа 2026 (CPM + сторис) | O29: ='APP Медиа'!P54 -> 3998.9414
A30: Выручка перформанса 2026, млн ₽ (остаток) | O30: =O28-O29 -> 2196.4586
A31: Кампании-месяцы × сезонный коэффициент, янв–авг | O31: =SUMPRODUCT(C15:J15,C20:J20) -> 16112.9
A32: Кампании-месяцы × сезонный коэффициент, сен–дек | O32: =SUMPRODUCT(K15:N15,K20:N20) -> 12876.096
A33: Прирост чека от нового прайса, ₽ (из блока 4) | O33: =O47 -> 17576.254
A34: Надбавка нового прайса за сен–дек, млн ₽ | O34: =O32*O33/1000000 -> 226.31353
A35: СРЕДНИЙ ЧЕК КАМПАНИИ, СТАРЫЙ ПРАЙС, ₽ | O35: =(O30-O34)*1000000/(O31+O32) -> 67961.827
A37: 4. РАСЧЁТ ИНДЕКСАЦИИ ЧЕКА ПО НОВОМУ ПРАЙСУ | Q37: Описание: индексация чека от нового прайса. Логика: прирост чека = инкремент прайса по перформансу, ₽/мес (ПРАЙС) / среднее число кампаний янв–авг; индексация = 1 + прирост / чек по старому прайсу.
A39: Приоритетный вывод в категории | O39: =ПРАЙС!G28 -> 25714286
A40: Брендированная именная категория | O40: =ПРАЙС!G5 -> 3125000
A41: Подборка «Покупайте с выгодой» | O41: =ПРАЙС!G15 -> 3977777.8
A42: ИТОГО инкремент прайса по перформансу, ₽/мес | O42: =ПРАЙС!G70 -> 32817063
A43: Справочно: инкремент по медийным CPM-форматам, ₽/мес | O43: =ПРАЙС!G68 -> 89325000
A44: Справочно: инкремент по сторис, ₽/мес | O44: =ПРАЙС!G69 -> 7200000
A46: Кампаний AdTech в месяц, среднее янв–авг 2026 | O46: =AVERAGE(C15:J15) -> 1867.125
A47: Прирост среднего чека, ₽ | O47: =O42/O46 -> 17576.254
A48: ИНДЕКСАЦИЯ ЧЕКА | O48: =1+O47/O35 -> 1.2586195

Sheet In-store
A1: IN-STORE DIGITAL - БЮДЖЕТ 2027
A2: Устройства × средний доход на устройство в месяц × месяцев работы × реализация. Суммы в млн руб. без НДС.
A4: Месяц | B4: янв | C4: фев | D4: мар | E4: апр | F4: май | G4: июн | H4: июл | I4: авг | J4: сен | K4: окт | L4: ноя | M4: дек | N4: Сумма за год | O4: Описание: вводные In-Store
A5: Коэффициент | B5: 1 | C5: 1.1 | D5: 1.2 | E5: 1.1 | F5: 1.2 | G5: 1 | H5: 1 | I5: 1.1 | J5: 1.1 | K5: 1.2 | L5: 1.4 | M5: 1.7 | N5: =SUM(B5:M5) -> 14.1
A6: Утилизация 2027, % | B6: 0.1728149 | C6: 0.39276987 | D6: 0.50404346 | E6: 0.54983941 | F6: 0.50404346 | G6: 0.60485216 | H6: 0.60485216 | I6: 0.62837419 | J6: 0.62837419 | K6: 0.7920683 | L6: 0.86407451 | M6: 0.86407451 | N6: =SUMPRODUCT(B5:M5,B6:M6)/N5 -> 0.61281063
A7: Утилизация 2026, % | B7: 0.069856041 | C7: 0.15594075 | D7: 0.15250181 | E7: 0.10644586 | F7: 0.33938425 | G7: 0.70163249 | H7: 0.9 | I7: 0.55313783 | J7: 0.68662285 | K7: 0.45257033 | L7: 0.51916773 | M7: 0.60824823 | N7: 0.44099681
A9: 1. СПРАВОЧНИК ОБОРУДОВАНИЯ | L9: Описание: выручка по типам оборудования. Логика: устройства × доход на устройство в мес (ПРАЙС) × месяцев работы × % реализации / 10⁶; 2026 - парк из DATA, 2027 - план парка (ввод).
A10: Тип оборудования | B10: Устройств 2026 | C10: Устройств 2027 | D10: Доход/устр. мес 2026, ₽ | E10: Доход/устр. мес 2027, ₽ | F10: Месяцев 2026 | G10: Месяцев 2027 | H10: Реализация 2026 | I10: Реализация 2027 | J10: Выручка 2026 | K10: Выручка 2027
A11: КСО | B11: =DATA!B74 -> 16500 | C11: 57000 | D11: =ПРАЙС!B76 -> 4809 | E11: =ПРАЙС!C76 -> 2885.4 | F11: =DATA!C74 -> 12 | G11: 12 | H11: 0.925 | I11: 1 | J11: =B11*D11*F11*H11/1000000 -> 880.76835 | K11: =C11*E11*G11*I11*$N$6/0.638297872340426/1000000 -> 1894.8072
A12: КСО - новые | B12: =DATA!B75 -> 40500 | C12: 0 | D12: =ПРАЙС!B77 -> 4809 | E12: =ПРАЙС!C77 -> 2885.4 | F12: =DATA!C75 -> 3 | G12: 0 | H12: 0.925 | I12: 1 | J12: =B12*D12*F12*H12/1000000 -> 540.47149 | K12: =C12*E12*G12*I12*$N$6/0.638297872340426/1000000 -> 0
A13: Шелф-баннеры | B13: =DATA!B76 -> 25 | C13: 2750 | D13: =ПРАЙС!B78 -> 28800 | E13: =ПРАЙС!C78 -> 30240 | F13: =DATA!C76 -> 12 | G13: 12 | H13: 0.925 | I13: 1 | J13: =B13*D13*F13*H13/1000000 -> 7.992 | K13: =C13*E13*G13*I13*$N$6/0.638297872340426/1000000 -> 958.07304
A14: Шелф-баннеры - новые | B14: =DATA!B77 -> 2725 | C14: 3250 | D14: =ПРАЙС!B79 -> 28800 | E14: =ПРАЙС!C79 -> 30240 | F14: =DATA!C77 -> 3 | G14: 2 | H14: 0.925 | I14: 1 | J14: =B14*D14*F14*H14/1000000 -> 217.782 | K14: =C14*E14*G14*I14*$N$6/0.638297872340426/1000000 -> 188.71136
A15: Фасадные экраны | B15: =DATA!B78 -> 400 | C15: 1231 | D15: =ПРАЙС!B80 -> 30214 | E15: =ПРАЙС!C80 -> 24171.2 | F15: =DATA!C78 -> 12 | G15: 12 | H15: 0.925 | I15: 1 | J15: =B15*D15*F15*H15/1000000 -> 134.15016 | K15: =C15*E15*G15*I15*$N$6/0.638297872340426/1000000 -> 342.79968
A16: Фасадные экраны - новые | B16: =DATA!B79 -> 831 | C16: 428 | D16: =ПРАЙС!B81 -> 30214 | E16: =ПРАЙС!C81 -> 24171.2 | F16: =DATA!C79 -> 4 | G16: 4 | H16: 0.925 | I16: 1 | J16: =B16*D16*F16*H16/1000000 -> 92.898986 | K16: =C16*E16*G16*I16*$N$6/0.638297872340426/1000000 -> 39.728747
A17: TFT | B17: =DATA!B80 -> 2310 | C17: 2310 | D17: =ПРАЙС!B82 -> 14350 | E17: =ПРАЙС!C82 -> 11480 | F17: =DATA!C80 -> 12 | G17: 12 | H17: 0.925 | I17: 1 | J17: =B17*D17*F17*H17/1000000 -> 367.94835 | K17: =C17*E17*G17*I17*$N$6/0.638297872340426/1000000 -> 305.51885
A18: Дисплеи покупателя | B18: =DATA!B81 -> 6121 | C18: 6121 | D18: =ПРАЙС!B83 -> 1784 | E18: =ПРАЙС!C83 -> 1784 | F18: =DATA!C81 -> 12 | G18: 12 | H18: 0.925 | I18: 1 | J18: =B18*D18*F18*H18/1000000 -> 121.21049 | K18: =C18*E18*G18*I18*$N$6/0.638297872340426/1000000 -> 125.806
A19: Радио | B19: =DATA!B82 -> 3821 | C19: 3821 | D19: =ПРАЙС!B84 -> 506 | E19: =ПРАЙС!C84 -> 2024 | F19: =DATA!C82 -> 12 | G19: 12 | H19: 0.925 | I19: 1 | J19: =B19*D19*F19*H19/1000000 -> 21.461029 | K19: =C19*E19*G19*I19*$N$6/0.638297872340426/1000000 -> 89.098765
A20: Прайсчекеры | B20: =DATA!B83 -> 4408 | C20: 4408 | D20: =ПРАЙС!B85 -> 1112 | E20: =ПРАЙС!C85 -> 1112 | F20: =DATA!C83 -> 12 | G20: 12 | H20: 0.925 | I20: 1 | J20: =B20*D20*F20*H20/1000000 -> 54.408826 | K20: =C20*E20*G20*I20*$N$6/0.638297872340426/1000000 -> 56.471655
A21: Медиа-фасады | B21: =DATA!B84 -> 0 | C21: 1 | D21: =ПРАЙС!B86 -> 200000 | E21: =ПРАЙС!C86 -> 240000 | F21: =DATA!C84 -> 12 | G21: 12 | H21: 0.925 | I21: 1 | J21: =B21*D21*F21*H21/1000000 -> 0 | K21: =C21*E21*G21*I21*$N$6/0.638297872340426/1000000 -> 2.7650016
A22: Медиа-фасады - новые | B22: =DATA!B85 -> 1 | C22: 20 | D22: =ПРАЙС!B87 -> 200000 | E22: =ПРАЙС!C87 -> 240000 | F22: =DATA!C85 -> 4 | G22: 2 | H22: 0.925 | I22: 1 | J22: =B22*D22*F22*H22/1000000 -> 0.74 | K22: =C22*E22*G22*I22*$N$6/0.638297872340426/1000000 -> 9.2166719
A23: LED | B23: =DATA!B86 -> 79 | C23: 79 | D23: =ПРАЙС!B88 -> 7136 | E23: =ПРАЙС!C88 -> 7136 | F23: =DATA!C86 -> 12 | G23: 12 | H23: 0.925 | I23: 1 | J23: =B23*D23*F23*H23/1000000 -> 6.2575584 | K23: =C23*E23*G23*I23*$N$6/0.638297872340426/1000000 -> 6.4948044
A24: ИТОГО (парк на конец года) | B24: =SUM(B11:B23) -> 77721 | C24: =SUM(C11:C23) -> 81419 | J24: =SUM(J11:J23) -> 2446.0892 | K24: =SUM(K11:K23) -> 4019.4918
A26: 2. РАСКЛАДКА ПО МЕСЯЦАМ | Q26: Описание: помесячная выручка in-store. Логика: 2027 = годовая выручка (блок 1) × коэффициент (строка 5) × утилизация (строка 6) / Σ(коэффициент × утилизация); 2026 - помесячный факт + прогноз (ввод). Итог 2027 идёт в P&L.
A27: Показатель | B27: Ед. изм. | C27: янв | D27: фев | E27: мар | F27: апр | G27: май | H27: июн | I27: июл | J27: авг | K27: сен | L27: окт | M27: ноя | N27: дек | O27: 2027 | P27: 2026
A28: ВЫРУЧКА IN-STORE 2027 | B28: млн ₽ | C28: =$K$24*B$5*B$6/SUMPRODUCT($B$5:$M$5,$B$6:$M$6) -> 80.390907 | D28: =$K$24*C$5*C$6/SUMPRODUCT($B$5:$M$5,$B$6:$M$6) -> 200.98173 | E28: =$K$24*D$5*D$6/SUMPRODUCT($B$5:$M$5,$B$6:$M$6) -> 281.36817 | F28: =$K$24*E$5*E$6/SUMPRODUCT($B$5:$M$5,$B$6:$M$6) -> 281.35478 | G28: =$K$24*F$5*F$6/SUMPRODUCT($B$5:$M$5,$B$6:$M$6) -> 281.36817 | H28: =$K$24*G$5*G$6/SUMPRODUCT($B$5:$M$5,$B$6:$M$6) -> 281.36817 | I28: =$K$24*H$5*H$6/SUMPRODUCT($B$5:$M$5,$B$6:$M$6) -> 281.36817 | J28: =$K$24*I$5*I$6/SUMPRODUCT($B$5:$M$5,$B$6:$M$6) -> 321.5413 | ... N28: =$K$24*M$5*M$6/SUMPRODUCT($B$5:$M$5,$B$6:$M$6) -> 683.32271 | O28: =SUM(C28:N28) -> 4019.4918 | P28: =J24 -> 2446.0892
A29: Выручка in-store 2026 | B29: млн ₽ | C29: 27.481635 | D29: 67.48246 | E29: 71.993757 | F29: 46.06383 | G29: 160.21808 | H29: 276.02492 | I29: 354.06345 | J29: 239.3672 | K29: 297.13207 | L29: 213.65149 | M29: 285.93961 | N29: 406.78822 | O29: =SUM(C29:N29) -> 2446.2067
A31: ПАРК ОБОРУДОВАНИЯ - РАСШИФРОВКА | R31: Описание: справочная расшифровка парка. Логика: базовый парк + ввод за 2026 = парк на конец года; средний парк = Σ(устройства × месяцы) / 12.
A32: Базовый парк на начало 2026 | O32: =B11+B13+B15+B17+B18+B19+B20+B21+B23 -> 33664 | Q32: Устройства, работавшие все 12 месяцев
A33: Введено в течение 2026 | O33: =B12+B14+B16+B22 -> 44057 | Q33: 40 500 КСО и 2 725 шелф-баннеров - по 3 месяца, 831 фасадный экран - 5 месяцев
A34: Парк на конец 2026 | O34: =B24 -> 77721 | Q34: Он же - базовый парк на начало 2027
A35: Средний парк 2026, взвешенный по месяцам работы | O35: =SUMPRODUCT(B11:B23,F11:F23)/12 -> 44747.583 | Q35: Сколько устройств в среднем монетизировалось в течение года

Sheet DMP
A1: DMP + ONLINE И DMP + ANALYTICS - БЮДЖЕТ 2027
A2: Выручка по проектам и маржинальность трафика. Источник - план команды DMP. Суммы в млн руб. без НДС.
C3: =C9/$O$9 -> 0.02 | D3: =D9/$O$9 -> 0.05 | E3: =E9/$O$9 -> 0.07 | F3: =F9/$O$9 -> 0.07 | G3: =G9/$O$9 -> 0.07 | H3: =H9/$O$9 -> 0.07 | I3: =I9/$O$9 -> 0.07 | J3: =J9/$O$9 -> 0.08 | ... N3: =N9/$O$9 -> 0.17
A4: 1. DMP + ONLINE, 2027 | R4: Описание: выручка DMP + Online по направлениям (план команды DMP). Логика: выручка = Σ трёх направлений; закупка трафика = Σ выручка × (1 − маржинальность) → расходы на маркетинг в интернете; итоговая маржа = 1 − закупка / выручка.
A5: Показатель | B5: Ед. изм. | C5: янв | D5: фев | E5: мар | F5: апр | G5: май | H5: июн | I5: июл | J5: авг | K5: сен | L5: окт | M5: ноя | N5: дек | O5: 2027 | P5: 2026 | Q5: Комментарий
A6: Пакеты и Онлайн+ТВ | B6: млн ₽ | C6: 7.3142857 | D6: 24 | E6: 28 | F6: 24.888889 | G6: 29.866667 | H6: 31.36 | I6: 31.111111 | J6: 25.6 | K6: 35.555556 | L6: 52.8 | M6: 44.8 | N6: 57.263158 | O6: =SUM(C6:N6) -> 392.55967 | Q6: План команды DMP
A7: Баннеры и OLV | B7: млн ₽ | C7: 15.542857 | D7: 33.333333 | E7: 56 | F7: 62.222222 | G7: 58.666667 | H7: 56 | I7: 56 | J7: 70.4 | K7: 64 | L7: 79.2 | M7: 112 | N7: 124.54737 | O7: =SUM(C7:N7) -> 787.91245
A8: Развитие новых площадок (SmartTV, Авито, МР) | B8: млн ₽ | C8: 9.1428571 | D8: 22.666667 | E8: 28 | F8: 24.888889 | G8: 23.466667 | H8: 24.64 | I8: 24.888889 | J8: 32 | K8: 28.444444 | L8: 44 | M8: 67.2 | N8: 90.189474 | O8: =SUM(C8:N8) -> 419.52789
A9: ВЫРУЧКА DMP + ONLINE | B9: млн ₽ | C9: =C6+C7+C8 -> 32 | D9: =D6+D7+D8 -> 80 | E9: =E6+E7+E8 -> 112 | F9: =F6+F7+F8 -> 112 | G9: =G6+G7+G8 -> 112 | H9: =H6+H7+H8 -> 112 | I9: =I6+I7+I8 -> 112 | J9: =J6+J7+J8 -> 128 | ... N9: =N6+N7+N8 -> 272 | O9: =SUM(C9:N9) -> 1600 | P9: =O23 -> 987
A11: Маржинальность: пакеты и Онлайн+ТВ | B11: % | C11: 0.24969525 | D11: 0.24969525 | E11: 0.24969525 | F11: 0.24969525 | G11: 0.24969525 | H11: 0.24969525 | I11: 0.24969525 | J11: 0.24969525 | K11: 0.24969525 | L11: 0.24969525 | M11: 0.24969525 | N11: 0.24969525 | O11: =AVERAGE(C11:N11) -> 0.24969525
A12: Маржинальность: баннеры и OLV | B12: % | C12: 0.43727143 | D12: 0.37474604 | E12: 0.43727143 | F12: 0.37474604 | G12: 0.37474604 | H12: 0.37474604 | I12: 0.37474604 | J12: 0.37474604 | K12: 0.43727143 | L12: 0.37474604 | M12: 0.43727143 | N12: 0.43727143 | O12: =AVERAGE(C12:N12) -> 0.40079829
A13: Маржинальность: новые площадки | B13: % | C13: 0.43727143 | D13: 0.43727143 | E13: 0.43727143 | F13: 0.43727143 | G13: 0.43727143 | H13: 0.43727143 | I13: 0.43727143 | J13: 0.43727143 | K13: 0.43727143 | L13: 0.43727143 | M13: 0.43727143 | N13: 0.43727143 | O13: =AVERAGE(C13:N13) -> 0.43727143
A14: ЗАКУПКА ТРАФИКА | B14: млн ₽ | C14: =C6*(1-C11)+C7*(1-C12)+C8*(1-C13) -> 19.3793 | D14: =D6*(1-D11)+D7*(1-D12)+D8*(1-D13) -> 51.604294 | E14: =E6*(1-E11)+E7*(1-E12)+E8*(1-E13) -> 68.277733 | F14: =F6*(1-F11)+F7*(1-F12)+F8*(1-F13) -> 71.584631 | G14: =G6*(1-G11)+G7*(1-G12)+G8*(1-G13) -> 72.296031 | H14: =H6*(1-H11)+H7*(1-H12)+H8*(1-H13) -> 72.409411 | I14: =I6*(1-I11)+I7*(1-I12)+I8*(1-I13) -> 72.362725 | J14: =J6*(1-J11)+J7*(1-J12)+J8*(1-J13) -> 81.232995 | ... N14: =N6*(1-N11)+N7*(1-N12)+N8*(1-N13) -> 163.80337 | O14: =SUM(C14:N14) -> 1000
A15: Маржинальность итоговая | B15: % | C15: =IFERROR(1-C14/C9,"") -> 0.39439688 | D15: =IFERROR(1-D14/D9,"") -> 0.35494633 | E15: =IFERROR(1-E14/E9,"") -> 0.39037739 | F15: =IFERROR(1-F14/F9,"") -> 0.36085151 | G15: =IFERROR(1-G14/G9,"") -> 0.35449972 | H15: =IFERROR(1-H14/H9,"") -> 0.3534874 | I15: =IFERROR(1-I14/I9,"") -> 0.35390424 | J15: =IFERROR(1-J14/J9,"") -> 0.36536723 | ... O15: =IFERROR(1-O14/O9,"") -> 0.375
A17: 2. DMP + ANALYTICS, 2027 | R17: Описание: выручка DMP + Analytics (план команды DMP). Логика: выручка = DMP + Adhoc, без закупки трафика. Итог идёт в P&L.
A18: DMP | B18: млн ₽ | C18: 0.748 | D18: 2.805 | E18: 4.3633333 | F18: 3.4906667 | G18: 4.3633333 | H18: 3.6361111 | I18: 3.4906667 | J18: 3.3244444 | K18: 4.9866667 | L18: 6.8566667 | M18: 8.7266667 | N18: 7.3361538 | O18: =SUM(C18:N18) -> 54.127709 | Q18: План команды DMP
A19: Adhoc | B19: млн ₽ | C19: 2.992 | D19: 6.545 | E19: 8.7266667 | F19: 9.5993333 | G19: 8.7266667 | H19: 9.4538889 | I19: 9.5993333 | J19: 11.635556 | K19: 9.9733333 | L19: 13.713333 | M19: 17.453333 | N19: 24.453846 | O19: =SUM(C19:N19) -> 132.87229
A20: ВЫРУЧКА DMP + ANALYTICS | B20: млн ₽ | C20: =C18+C19 -> 3.74 | D20: =D18+D19 -> 9.35 | E20: =E18+E19 -> 13.09 | F20: =F18+F19 -> 13.09 | G20: =G18+G19 -> 13.09 | H20: =H18+H19 -> 13.09 | I20: =I18+I19 -> 13.09 | J20: =J18+J19 -> 14.96 | ... N20: =N18+N19 -> 31.79 | O20: =SUM(C20:N20) -> 187 | P20: =O24 -> 102.4
A22: 3. БАЗА 2026 (факт + прогноз, Master File, блок ACT) | R22: Описание: база 2026 (факт + прогноз, Master File). Логика: справочные значения для сравнения 2027 с 2026 (YoY).
A23: DMP + Online 2026 | B23: млн ₽ | C23: 16.9 | D23: 11.7 | E23: 3.4 | F23: 25.5 | G23: 57.6 | H23: 213.3 | I23: 71.9 | J23: 97.3 | K23: 120.8 | L23: 86.9 | M23: 116.3 | N23: 165.4 | O23: =SUM(C23:N23) -> 987
A24: DMP + Analytics 2026 | B24: млн ₽ | C24: 4.5 | D24: 1.5 | E24: 4.2 | F24: 5.3 | G24: 4.1 | H24: 8 | I24: 5.7 | J24: 11.5 | K24: 14.2 | L24: 10.2 | M24: 13.7 | N24: 19.5 | O24: =SUM(C24:N24) -> 102.4
A25: Закупка трафика 2026 | B25: млн ₽ | C25: 17.85 | D25: 23.25 | E25: 38.1 | F25: 30.84 | G25: 38 | H25: 37.5 | I25: 37.5 | J25: 37.5 | K25: 40 | L25: 45 | M25: 72.5 | N25: 92.5 | O25: =SUM(C25:N25) -> 510.54 | Q25: План команды DMP на 2026

Sheet Content factory
A1: CONTENT FACTORY - БЮДЖЕТ 2027
A2: Ячейка креаторов производит публикации, публикации дают просмотры. Просмотры делятся на внутренних заказчиков и внешних рекламодателей. Суммы в млн руб. без НДС.
A4: 1. ПРОИЗВОДСТВО: ОТ ЯЧЕЕК К ПРОСМОТРАМ | Q4: Описание: производственная воронка. Логика: публикации = ячейки × креаторы × контент-ед. на креатора × коэф. дублирования; просмотры = публикации × просмотры на публикацию × загруженность / 10⁶.
A5: Показатель | B5: Ед. изм. | C5: янв | D5: фев | E5: мар | F5: апр | G5: май | H5: июн | I5: июл | J5: авг | K5: сен | L5: окт | M5: ноя | N5: дек | O5: 2027 | P5: 2026
A6: Ячеек в работе | B6: ед. | C6: 2 | D6: 4 | E6: 6 | F6: 6 | G6: 6 | H6: 6 | I6: 6 | J6: 6 | K6: 6 | L6: 6 | M6: 6 | N6: 6 | O6: =AVERAGE(C6:N6) -> 5.5
A7: Креаторов на ячейку | B7: чел. | C7: 25 | D7: 25 | E7: 25 | F7: 25 | G7: 25 | H7: 25 | I7: 25 | J7: 25 | K7: 25 | L7: 25 | M7: 25 | N7: 25 | O7: =AVERAGE(C7:N7) -> 25
A8: Контент-единиц на креатора в месяц | B8: ед. | C8: 60 | D8: 60 | E8: 60 | F8: 60 | G8: 60 | H8: 60 | I8: 60 | J8: 60 | K8: 60 | L8: 70 | M8: 70 | N8: 70 | O8: =AVERAGE(C8:N8) -> 62.5
A9: Коэффициент дублирования | B9: × | C9: 4 | D9: 4 | E9: 4 | F9: 4 | G9: 4 | H9: 4 | I9: 4 | J9: 4 | K9: 4 | L9: 4 | M9: 4 | N9: 4 | O9: =AVERAGE(C9:N9) -> 4
A10: Публикаций всего | B10: ед. | C10: =C6*C7*C8*C9 -> 12000 | D10: =D6*D7*D8*D9 -> 24000 | E10: =E6*E7*E8*E9 -> 36000 | F10: =F6*F7*F8*F9 -> 36000 | G10: =G6*G7*G8*G9 -> 36000 | H10: =H6*H7*H8*H9 -> 36000 | I10: =I6*I7*I8*I9 -> 36000 | J10: =J6*J7*J8*J9 -> 36000 | ... N10: =N6*N7*N8*N9 -> 42000 | O10: =SUM(C10:N10) -> 414000
A11: Просмотров на публикацию | B11: ед. | C11: 948 | D11: 1185 | E11: 1106 | F11: 1106 | G11: 1106 | H11: 1106 | I11: 1106 | J11: 1264 | K11: 1264 | L11: 1489.7143 | M11: 1896 | N11: 2302.2857 | O11: =AVERAGE(C11:N11) -> 1323.25
A12: Коэффициент загруженности | B12: × | C12: 1 | D12: 1 | E12: 1 | F12: 1 | G12: 1 | H12: 1 | I12: 1 | J12: 1 | K12: 1 | L12: 1 | M12: 1 | N12: 1 | O12: =AVERAGE(C12:N12) -> 1
A13: ПРОСМОТРЫ ВСЕГО | B13: млн | C13: =C10*C11*C12/1000000 -> 11.376 | D13: =D10*D11*D12/1000000 -> 28.44 | E13: =E10*E11*E12/1000000 -> 39.816 | F13: =F10*F11*F12/1000000 -> 39.816 | G13: =G10*G11*G12/1000000 -> 39.816 | H13: =H10*H11*H12/1000000 -> 39.816 | I13: =I10*I11*I12/1000000 -> 39.816 | J13: =J10*J11*J12/1000000 -> 45.504 | ... N13: =N10*N11*N12/1000000 -> 96.696 | O13: =SUM(C13:N13) -> 568.8
A15: 2. СПЛИТ ПРОСМОТРОВ | Q15: Описание: сплит просмотров. Логика: внешние рекламодатели = просмотры × доля; внутренние заказчики (ВГО) = просмотры × (1 − доля).
A16: Доля внешних рекламодателей | B16: % | C16: 0.5 | D16: 0.5 | E16: 0.5 | F16: 0.5 | G16: 0.5 | H16: 0.5 | I16: 0.5 | J16: 0.5 | K16: 0.5 | L16: 0.5 | M16: 0.5 | N16: 0.5 | O16: =AVERAGE(C16:N16) -> 0.5
A17: Просмотры внешних рекламодателей | B17: млн | C17: =C13*C16 -> 5.688 | D17: =D13*D16 -> 14.22 | E17: =E13*E16 -> 19.908 | F17: =F13*F16 -> 19.908 | G17: =G13*G16 -> 19.908 | H17: =H13*H16 -> 19.908 | I17: =I13*I16 -> 19.908 | J17: =J13*J16 -> 22.752 | ... N17: =N13*N16 -> 48.348 | O17: =SUM(C17:N17) -> 284.4
A18: Просмотры внутренних заказчиков | B18: млн | C18: =C13*(1-C16) -> 5.688 | D18: =D13*(1-D16) -> 14.22 | E18: =E13*(1-E16) -> 19.908 | F18: =F13*(1-F16) -> 19.908 | G18: =G13*(1-G16) -> 19.908 | H18: =H13*(1-H16) -> 19.908 | I18: =I13*(1-I16) -> 19.908 | J18: =J13*(1-J16) -> 22.752 | ... N18: =N13*(1-N16) -> 48.348 | O18: =SUM(C18:N18) -> 284.4
A20: 3. ЭКОНОМИКА ПРОСМОТРА | Q20: Описание: юнит-экономика просмотра. Логика: цены и ставка креатора - из ПРАЙС; OPEX ячеек = ячейки × креаторы × ставка; себестоимость = (OPEX + PEX команды) / просмотры; маржа = цена − себестоимость.
A21: Рыночная цена просмотра | B21: руб. | C21: =ПРАЙС!$B$93 -> 0.75 | D21: =ПРАЙС!$B$93 -> 0.75 | E21: =ПРАЙС!$B$93 -> 0.75 | F21: =ПРАЙС!$B$93 -> 0.75 | G21: =ПРАЙС!$B$93 -> 0.75 | H21: =ПРАЙС!$B$93 -> 0.75 | I21: =ПРАЙС!$B$93 -> 0.75 | J21: =ПРАЙС!$B$93 -> 0.75 | ... N21: =ПРАЙС!$B$93 -> 0.75 | O21: =AVERAGE(C21:N21) -> 0.75
A22: Внутренняя цена просмтра ВГО | B22: руб. | C22: 0.5 | D22: 0.5 | E22: 0.5 | F22: 0.5 | G22: 0.5 | H22: 0.5 | I22: 0.5 | J22: 0.5 | K22: 0.5 | L22: 0.5 | M22: 0.5 | N22: 0.5 | O22: =AVERAGE(C22:N22) -> 0.5
A23: Ставка креатора в месяц | B23: руб. | C23: =80000*1.06 -> 84800 | D23: =70000*1.06 -> 74200 | E23: =90000*1.06 -> 95400 | F23: =93000*1.06 -> 98580 | G23: =95000*1.06 -> 100700 | H23: =100000*1.06 -> 106000 | I23: =100000*1.06 -> 106000 | J23: =107000*1.06 -> 113420 | K23: =107000*1.06 -> 113420 | L23: =107000*1.06 -> 113420 | M23: =115000*1.06 -> 121900 | N23: =120000*1.06 -> 127200 | O23: =AVERAGE(C23:N23) -> 104586.67
A24: OPEX ячеек (оплата креаторам) | B24: млн руб. | C24: =C6*C7*C23/1000000 -> 4.24 | D24: =D6*D7*D23/1000000 -> 7.42 | E24: =E6*E7*E23/1000000 -> 14.31 | F24: =F6*F7*F23/1000000 -> 14.787 | G24: =G6*G7*G23/1000000 -> 15.105 | H24: =H6*H7*H23/1000000 -> 15.9 | I24: =I6*I7*I23/1000000 -> 15.9 | J24: =J6*J7*J23/1000000 -> 17.013 | ... N24: =N6*N7*N23/1000000 -> 19.08 | O24: =SUM(C24:N24) -> 176.066
A25: PEX Content Factory (общая команда) | B25: млн руб. | C25: =1572580/1000000 -> 1.57258 | D25: =3387147/1000000 -> 3.387147 | E25: =4321588/1000000 -> 4.321588 | F25: =5328775/1000000 -> 5.328775 | G25: =6495575/1000000 -> 6.495575 | H25: =6617872/1000000 -> 6.617872 | I25: =6410866/1000000 -> 6.410866 | J25: =5760800/1000000 -> 5.7608 | K25: =6237729/1000000 -> 6.237729 | L25: =6595838/1000000 -> 6.595838 | M25: =6597352/1000000 -> 6.597352 | N25: =7082370/1000000 -> 7.08237 | O25: =SUM(C25:N25) -> 66.408492
A26: Себестоимость просмотра | B26: руб. | C26: =IFERROR((C24+C25)/C13,0) -> 0.51095113 | D26: =IFERROR((D24+D25)/D13,0) -> 0.37999814 | E26: =IFERROR((E24+E25)/E13,0) -> 0.46794223 | F26: =IFERROR((F24+F25)/F13,0) -> 0.50521838 | G26: =IFERROR((G24+G25)/G13,0) -> 0.54250992 | H26: =IFERROR((H24+H25)/H13,0) -> 0.56554832 | I26: =IFERROR((I24+I25)/I13,0) -> 0.56034926 | J26: =IFERROR((J24+J25)/J13,0) -> 0.50047908 | ... N26: =IFERROR((N24+N25)/N13,0) -> 0.2705631 | O26: =AVERAGE(C26:N26) -> 0.45869311
A27: Маржа с просмотра ВГО | B27: руб. | C27: =C22-C26 -> -0.010951125 | D27: =D22-D26 -> 0.12000186 | E27: =E22-E26 -> 0.032057766 | F27: =F22-F26 -> -0.0052183795 | G27: =G22-G26 -> -0.042509921 | H27: =H22-H26 -> -0.065548322 | I27: =I22-I26 -> -0.060349257 | J27: =J22-J26 -> -0.00047907876 | ... N27: =N22-N26 -> 0.2294369 | O27: =AVERAGE(C27:N27) -> 0.041306892
A28: Маржа с просмотра | B28: руб. | C28: =C21-C26 -> 0.23904887 | D28: =D21-D26 -> 0.37000186 | E28: =E21-E26 -> 0.28205777 | F28: =F21-F26 -> 0.24478162 | G28: =G21-G26 -> 0.20749008 | H28: =H21-H26 -> 0.18445168 | I28: =I21-I26 -> 0.18965074 | J28: =J21-J26 -> 0.24952092 | ... N28: =N21-N26 -> 0.4794369 | O28: =AVERAGE(C28:N28) -> 0.29130689
A30: 4. РЕЗУЛЬТАТ | Q30: Описание: финансовый результат Content factory. Логика: выручка = просмотры × цена (внешние - рыночная, ВГО - внутренняя); результат = выручка − OPEX ячеек − PEX команды. Выручка → P&L, оплата креаторам → Marketing.
A31: ВЫРУЧКА - внешние рекламодатели | B31: млн руб. | C31: =C17*C21 -> 4.266 | D31: =D17*D21 -> 10.665 | E31: =E17*E21 -> 14.931 | F31: =F17*F21 -> 14.931 | G31: =G17*G21 -> 14.931 | H31: =H17*H21 -> 14.931 | I31: =I17*I21 -> 14.931 | J31: =J17*J21 -> 17.064 | ... N31: =N17*N21 -> 36.261 | O31: =SUM(C31:N31) -> 213.3
A32: ВЫРУЧКА (ВГО) - внутренние заказчики | B32: млн руб. | C32: =C18*C22 -> 2.844 | D32: =D18*D22 -> 7.11 | E32: =E18*E22 -> 9.954 | F32: =F18*F22 -> 9.954 | G32: =G18*G22 -> 9.954 | H32: =H18*H22 -> 9.954 | I32: =I18*I22 -> 9.954 | J32: =J18*J22 -> 11.376 | ... N32: =N18*N22 -> 24.174 | O32: =SUM(C32:N32) -> 142.2 | P32: 11.448
A33: Выручка всего | B33: млн руб. | C33: =C31+C32 -> 7.11 | D33: =D31+D32 -> 17.775 | E33: =E31+E32 -> 24.885 | F33: =F31+F32 -> 24.885 | G33: =G31+G32 -> 24.885 | H33: =H31+H32 -> 24.885 | I33: =I31+I32 -> 24.885 | J33: =J31+J32 -> 28.44 | ... N33: =N31+N32 -> 60.435 | O33: =SUM(C33:N33) -> 355.5 | Q33: =O31/O33 -> 0.6
A34: Расходы: OPEX ячеек | B34: млн руб. | C34: =-C24 -> -4.24 | D34: =-D24 -> -7.42 | E34: =-E24 -> -14.31 | F34: =-F24 -> -14.787 | G34: =-G24 -> -15.105 | H34: =-H24 -> -15.9 | I34: =-I24 -> -15.9 | J34: =-J24 -> -17.013 | ... N34: =-N24 -> -19.08 | O34: =SUM(C34:N34) -> -176.066
A35: Расходы: PEX Content Factory (общая команда) | B35: млн руб. | C35: =-C25 -> -1.57258 | D35: =-D25 -> -3.387147 | E35: =-E25 -> -4.321588 | F35: =-F25 -> -5.328775 | G35: =-G25 -> -6.495575 | H35: =-H25 -> -6.617872 | I35: =-I25 -> -6.410866 | J35: =-J25 -> -5.7608 | ... N35: =-N25 -> -7.08237 | O35: =SUM(C35:N35) -> -66.408492
A36: Расходы всего | B36: млн руб. | C36: =C34+C35 -> -5.81258 | D36: =D34+D35 -> -10.807147 | E36: =E34+E35 -> -18.631588 | F36: =F34+F35 -> -20.115775 | G36: =G34+G35 -> -21.600575 | H36: =H34+H35 -> -22.517872 | I36: =I34+I35 -> -22.310866 | J36: =J34+J35 -> -22.7738 | ... N36: =N34+N35 -> -26.16237 | O36: =SUM(C36:N36) -> -242.47449
A37: Результат Content factory | B37: млн руб. | C37: =C33+C34+C35 -> 1.29742 | D37: =D33+D34+D35 -> 6.967853 | E37: =E33+E34+E35 -> 6.253412 | F37: =F33+F34+F35 -> 4.769225 | G37: =G33+G34+G35 -> 3.284425 | H37: =H33+H34+H35 -> 2.367128 | I37: =I33+I34+I35 -> 2.574134 | J37: =J33+J34+J35 -> 5.6662 | ... N37: =N33+N34+N35 -> 34.27263 | O37: =SUM(C37:N37) -> 113.02551
A38: Рентабельность | B38: % | C38: =IFERROR(C37/C33,0) -> 0.1824782 | D38: =IFERROR(D37/D33,0) -> 0.39200298 | E38: =IFERROR(E37/E33,0) -> 0.25129243 | F38: =IFERROR(F37/F33,0) -> 0.19165059 | G38: =IFERROR(G37/G33,0) -> 0.13198413 | H38: =IFERROR(H37/H33,0) -> 0.095122684 | I38: =IFERROR(I37/I33,0) -> 0.10344119 | J38: =IFERROR(J37/J33,0) -> 0.19923347 | ... O38: =IFERROR(O37/O33,0) -> 0.31793392

Sheet RMN
A1: RMN - сделки с бренд-бюджетами, План 2026, руб. | C1: Описание: справочно - сделки с бренд-бюджетами 2026
A2: Бренд | B2: Возмещение
A3: Нестле | B3: 100000000
A4: Ферерро | B4: 100000000
A5: Монделиз | B5: 100000000
A6: Логика Молока | B6: 20000000
A7: Марс | B7: 100000000
A8: РОСТ | B8: 60000000
A9: Дамате | B9: 50000000
A10: P&G | B10: 30000000
A11: JDE | B11: 15000000
A12: Поставщики | B12: 100000000
A13: Пепси | B13: 75000000
B14: =SUM(B3:B13) -> 750000000
A16: RMN - План 2027, млн руб.
B17: янв | C17: фев | D17: мар | E17: апр | F17: май | G17: июн | H17: июл | I17: авг | J17: сен | K17: окт | L17: ноя | M17: дек | N17: 2027
A18: RMN (Brand budgets call) | B18: 17.004183 | C18: 42.510457 | D18: 59.51464 | E18: 59.51464 | F18: 59.51464 | G18: 59.51464 | H18: 59.51464 | I18: 68.016732 | J18: 68.016732 | K18: 93.523006 | L18: 119.02928 | M18: 144.53555 | N18: 850.20914

Sheet Расходы
B1: Расходы 2027, млн руб. | Q1: Описание: расходы 2027 по статьям P&L, млн ₽ (со знаком «–»). Логика: большинство статей - SUMIFS из «Потребности» по колонке «Мэппинг к отчетности» / 10⁶; ФОТ - из PEX; рекламный сбор = 0,7% выручки; часть статей - ввод; AT Platform = потребности − CAPEX-часть ФОТ (PEX).
B2: Статья | C2: Янв.2027 | D2: Фев.2027 | E2: Мар.2027 | F2: Апр.2027 | G2: Май.2027 | H2: Июн.2027 | I2: Июл.2027 | J2: Авг.2027 | K2: Сен.2027 | L2: Окт.2027 | M2: Ноя.2027 | N2: Дек.2027 | O2: 2027 | P2: 2026
B3: Налоги и взносы, связанные с расходами на оплату труда (ФОТ) | C3: =PEX!C24 -> -20.502132 | D3: =PEX!D24 -> -20.887499 | E3: =PEX!E24 -> -20.996231 | F3: =PEX!F24 -> -21.347445 | G3: =PEX!G24 -> -21.745961 | H3: =PEX!H24 -> -21.199164 | I3: =PEX!I24 -> -21.729056 | J3: =PEX!J24 -> -18.508763 | ... N3: =PEX!N24 -> -23.873296 | O3: =SUM(C3:N3) -> -258.40169 | P3: -201.50085
B4: Индексация | C4: =PEX!C25 -> 0 | D4: =PEX!D25 -> 0 | E4: =PEX!E25 -> 0 | F4: =PEX!F25 -> 0 | G4: =PEX!G25 -> 0 | H4: =PEX!H25 -> 0 | I4: =PEX!I25 -> 0 | J4: =PEX!J25 -> 0 | ... N4: =PEX!N25 -> 0 | O4: =SUM(C4:N4) -> 0 | P4: 0
B5: Оплата труда - постоянная часть | C5: =PEX!C26 -> -71.250322 | D5: =PEX!D26 -> -72.589574 | E5: =PEX!E26 -> -72.967448 | F5: =PEX!F26 -> -74.188009 | G5: =PEX!G26 -> -75.572956 | H5: =PEX!H26 -> -73.672694 | I5: =PEX!I26 -> -75.514206 | J5: =PEX!J26 -> -64.322839 | ... N5: =PEX!N26 -> -82.966006 | O5: =SUM(C5:N5) -> -898.01411 | P5: -700.26866
B6: Оплата труда - премии | C6: =PEX!C27 -> -2.6895515 | D6: =PEX!D27 -> -2.7401055 | E6: =PEX!E27 -> -2.7543694 | F6: =PEX!F27 -> -2.8004431 | G6: =PEX!G27 -> -2.852722 | H6: =PEX!H27 -> -2.780991 | I6: =PEX!I27 -> -2.8505043 | J6: =PEX!J27 -> -2.4280534 | ... N6: =PEX!N27 -> -3.1317942 | O6: =SUM(C6:N6) -> -33.898165 | P6: -26.433686
B7: Оплата труда - отпускные | C7: =PEX!C28 -> -4.6155439 | D7: =PEX!D28 -> -4.7022997 | E7: =PEX!E28 -> -4.7267781 | F7: =PEX!F28 -> -4.8058451 | G7: =PEX!G28 -> -4.895561 | H7: =PEX!H28 -> -4.7724634 | I7: =PEX!I28 -> -4.8917552 | J7: =PEX!J28 -> -4.1667866 | ... N7: =PEX!N28 -> -5.3744774 | O7: =SUM(C7:N7) -> -58.172699 | P7: -45.362893
B8: Начисление резерва STI 100%, годовой бонус | C8: =PEX!C29 -> -11.555954 | D8: =PEX!D29 -> -11.773165 | E8: =PEX!E29 -> -11.834452 | F8: =PEX!F29 -> -12.032412 | G8: =PEX!G29 -> -12.257034 | H8: =PEX!H29 -> -11.948834 | I8: =PEX!I29 -> -12.247506 | J8: =PEX!J29 -> -10.432399 | ... N8: =PEX!N29 -> -13.456099 | O8: =SUM(C8:N8) -> -145.6472 | P8: -113.57524
B9: Начисление резерва STI 100%, квартальные бонусы | C9: =PEX!C30 -> -3.350543 | D9: =PEX!D30 -> -3.4135212 | E9: =PEX!E30 -> -3.4312907 | F9: =PEX!F30 -> -3.4886876 | G9: =PEX!G30 -> -3.5538146 | H9: =PEX!H30 -> -3.4644549 | I9: =PEX!I30 -> -3.5510519 | J9: =PEX!J30 -> -3.0247784 | ... N9: =PEX!N30 -> -3.9014725 | O9: =SUM(C9:N9) -> -42.22907 | P9: -32.9301
B10: PEX | C10: =SUM(C3:C9) -> -113.96405 | D10: =SUM(D3:D9) -> -116.10616 | E10: =SUM(E3:E9) -> -116.71057 | F10: =SUM(F3:F9) -> -118.66284 | G10: =SUM(G3:G9) -> -120.87805 | H10: =SUM(H3:H9) -> -117.8386 | I10: =SUM(I3:I9) -> -120.78408 | J10: =SUM(J3:J9) -> -102.88362 | ... N10: =SUM(N3:N9) -> -132.70314 | O10: =SUM(C10:N10) -> -1436.3629 | P10: =SUM(P3:P9) -> -1120.0714
A11: Материальная помощь | B11: Материальная помощь | C11: =-SUMIFS(Потребности!J:J,Потребности!$Y:$Y,Расходы!$A11)/1000000 -> -0.005 | D11: =-SUMIFS(Потребности!K:K,Потребности!$Y:$Y,Расходы!$A11)/1000000 -> 0 | E11: =-SUMIFS(Потребности!L:L,Потребности!$Y:$Y,Расходы!$A11)/1000000 -> -0.005 | F11: =-SUMIFS(Потребности!M:M,Потребности!$Y:$Y,Расходы!$A11)/1000000 -> -0.005 | G11: =-SUMIFS(Потребности!N:N,Потребности!$Y:$Y,Расходы!$A11)/1000000 -> -0.005 | H11: =-SUMIFS(Потребности!O:O,Потребности!$Y:$Y,Расходы!$A11)/1000000 -> 0 | I11: =-SUMIFS(Потребности!P:P,Потребности!$Y:$Y,Расходы!$A11)/1000000 -> -0.005 | J11: =-SUMIFS(Потребности!Q:Q,Потребности!$Y:$Y,Расходы!$A11)/1000000 -> 0 | K11: =-SUMIFS(Потребности!R:R,Потребности!$Y:$Y,Расходы!$A11)/1000000 -> -0.005 | L11: =-SUMIFS(Потребности!S:S,Потребности!$Y:$Y,Расходы!$A11)/1000000 -> 0 | M11: =-SUMIFS(Потребности!T:T,Потребности!$Y:$Y,Расходы!$A11)/1000000 -> -0.005 | N11: =-SUMIFS(Потребности!U:U,Потребности!$Y:$Y,Расходы!$A11)/1000000 -> -0.005 | O11: =SUM(C11:N11) -> -0.04 | P11: -0.4
A12: Затраты на корп. мероприятие кроме проезда и проживания | B12: Затраты на корп. мероприятие кроме проезда и проживания | C12: =-SUMIFS(Потребности!J:J,Потребности!$Y:$Y,Расходы!$A12)/1000000 -> -0.375 | D12: =-SUMIFS(Потребности!K:K,Потребности!$Y:$Y,Расходы!$A12)/1000000 -> -0.375 | E12: =-SUMIFS(Потребности!L:L,Потребности!$Y:$Y,Расходы!$A12)/1000000 -> -0.51 | F12: =-SUMIFS(Потребности!M:M,Потребности!$Y:$Y,Расходы!$A12)/1000000 -> -0.375 | G12: =-SUMIFS(Потребности!N:N,Потребности!$Y:$Y,Расходы!$A12)/1000000 -> -0.375 | H12: =-SUMIFS(Потребности!O:O,Потребности!$Y:$Y,Расходы!$A12)/1000000 -> -0.375 | I12: =-SUMIFS(Потребности!P:P,Потребности!$Y:$Y,Расходы!$A12)/1000000 -> -0.51 | J12: =-SUMIFS(Потребности!Q:Q,Потребности!$Y:$Y,Расходы!$A12)/1000000 -> -0.375 | K12: =-SUMIFS(Потребности!R:R,Потребности!$Y:$Y,Расходы!$A12)/1000000 -> -0.375 | L12: =-SUMIFS(Потребности!S:S,Потребности!$Y:$Y,Расходы!$A12)/1000000 -> -0.375 | M12: =-SUMIFS(Потребности!T:T,Потребности!$Y:$Y,Расходы!$A12)/1000000 -> -0.375 | N12: =-SUMIFS(Потребности!U:U,Потребности!$Y:$Y,Расходы!$A12)/1000000 -> -0.375 | O12: =SUM(C12:N12) -> -4.77 | P12: -3
A13: ДМС и НС | B13: ДМС и НС | C13: =-SUMIFS(Потребности!J:J,Потребности!$Y:$Y,Расходы!$A13)/1000000 -> -0.86919813 | D13: =-SUMIFS(Потребности!K:K,Потребности!$Y:$Y,Расходы!$A13)/1000000 -> -0.86919813 | E13: =-SUMIFS(Потребности!L:L,Потребности!$Y:$Y,Расходы!$A13)/1000000 -> -0.86919813 | F13: =-SUMIFS(Потребности!M:M,Потребности!$Y:$Y,Расходы!$A13)/1000000 -> -0.86919813 | G13: =-SUMIFS(Потребности!N:N,Потребности!$Y:$Y,Расходы!$A13)/1000000 -> -0.86919813 | H13: =-SUMIFS(Потребности!O:O,Потребности!$Y:$Y,Расходы!$A13)/1000000 -> -0.86919813 | I13: =-SUMIFS(Потребности!P:P,Потребности!$Y:$Y,Расходы!$A13)/1000000 -> -0.86919813 | J13: =-SUMIFS(Потребности!Q:Q,Потребности!$Y:$Y,Расходы!$A13)/1000000 -> -0.86919813 | K13: =-SUMIFS(Потребности!R:R,Потребности!$Y:$Y,Расходы!$A13)/1000000 -> -0.86919813 | L13: =-SUMIFS(Потребности!S:S,Потребности!$Y:$Y,Расходы!$A13)/1000000 -> -0.86919813 | M13: =-SUMIFS(Потребности!T:T,Потребности!$Y:$Y,Расходы!$A13)/1000000 -> -0.88241992 | N13: =-SUMIFS(Потребности!U:U,Потребности!$Y:$Y,Расходы!$A13)/1000000 -> -0.97250298 | O13: =SUM(C13:N13) -> -10.546904 | P13: -6.5
A14: Подбор массовых позиций | B14: Подбор массовых позиций | C14: =-SUMIFS(Потребности!J:J,Потребности!$Y:$Y,Расходы!$A14)/1000000 -> 0 | D14: =-SUMIFS(Потребности!K:K,Потребности!$Y:$Y,Расходы!$A14)/1000000 -> 0 | E14: =-SUMIFS(Потребности!L:L,Потребности!$Y:$Y,Расходы!$A14)/1000000 -> 0 | F14: =-SUMIFS(Потребности!M:M,Потребности!$Y:$Y,Расходы!$A14)/1000000 -> 0 | G14: =-SUMIFS(Потребности!N:N,Потребности!$Y:$Y,Расходы!$A14)/1000000 -> 0 | H14: =-SUMIFS(Потребности!O:O,Потребности!$Y:$Y,Расходы!$A14)/1000000 -> 0 | I14: =-SUMIFS(Потребности!P:P,Потребности!$Y:$Y,Расходы!$A14)/1000000 -> 0 | J14: =-SUMIFS(Потребности!Q:Q,Потребности!$Y:$Y,Расходы!$A14)/1000000 -> 0 | K14: =-SUMIFS(Потребности!R:R,Потребности!$Y:$Y,Расходы!$A14)/1000000 -> 0 | L14: =-SUMIFS(Потребности!S:S,Потребности!$Y:$Y,Расходы!$A14)/1000000 -> 0 | M14: =-SUMIFS(Потребности!T:T,Потребности!$Y:$Y,Расходы!$A14)/1000000 -> 0 | N14: =-SUMIFS(Потребности!U:U,Потребности!$Y:$Y,Расходы!$A14)/1000000 -> 0 | O14: =SUM(C14:N14) -> 0 | P14: -4.9
A15: Подбор офисных позиций | B15: Подбор офисных позиций | C15: =-SUMIFS(Потребности!J:J,Потребности!$Y:$Y,Расходы!$A15)/1000000 -> -0.037333 | D15: =-SUMIFS(Потребности!K:K,Потребности!$Y:$Y,Расходы!$A15)/1000000 -> -0.037333 | E15: =-SUMIFS(Потребности!L:L,Потребности!$Y:$Y,Расходы!$A15)/1000000 -> -0.037333 | F15: =-SUMIFS(Потребности!M:M,Потребности!$Y:$Y,Расходы!$A15)/1000000 -> -0.37233367 | G15: =-SUMIFS(Потребности!N:N,Потребности!$Y:$Y,Расходы!$A15)/1000000 -> -0.037333 | H15: =-SUMIFS(Потребности!O:O,Потребности!$Y:$Y,Расходы!$A15)/1000000 -> -0.037333 | I15: =-SUMIFS(Потребности!P:P,Потребности!$Y:$Y,Расходы!$A15)/1000000 -> -0.037333 | J15: =-SUMIFS(Потребности!Q:Q,Потребности!$Y:$Y,Расходы!$A15)/1000000 -> -0.377003 | K15: =-SUMIFS(Потребности!R:R,Потребности!$Y:$Y,Расходы!$A15)/1000000 -> -0.037333 | L15: =-SUMIFS(Потребности!S:S,Потребности!$Y:$Y,Расходы!$A15)/1000000 -> -0.037333 | M15: =-SUMIFS(Потребности!T:T,Потребности!$Y:$Y,Расходы!$A15)/1000000 -> -0.037333 | N15: =-SUMIFS(Потребности!U:U,Потребности!$Y:$Y,Расходы!$A15)/1000000 -> -0.037333 | O15: =SUM(C15:N15) -> -1.1226667 | P15: 0
A16: Расходы на внешнее обучение | B16: Расходы на внешнее обучение | C16: =-SUMIFS(Потребности!J:J,Потребности!$Y:$Y,Расходы!$A16)/1000000 -> 0 | D16: =-SUMIFS(Потребности!K:K,Потребности!$Y:$Y,Расходы!$A16)/1000000 -> 0 | E16: =-SUMIFS(Потребности!L:L,Потребности!$Y:$Y,Расходы!$A16)/1000000 -> -0.51209 | F16: =-SUMIFS(Потребности!M:M,Потребности!$Y:$Y,Расходы!$A16)/1000000 -> -0.51209 | G16: =-SUMIFS(Потребности!N:N,Потребности!$Y:$Y,Расходы!$A16)/1000000 -> -0.51209 | H16: =-SUMIFS(Потребности!O:O,Потребности!$Y:$Y,Расходы!$A16)/1000000 -> -0.51209 | I16: =-SUMIFS(Потребности!P:P,Потребности!$Y:$Y,Расходы!$A16)/1000000 -> -0.51209 | J16: =-SUMIFS(Потребности!Q:Q,Потребности!$Y:$Y,Расходы!$A16)/1000000 -> -0.51209 | K16: =-SUMIFS(Потребности!R:R,Потребности!$Y:$Y,Расходы!$A16)/1000000 -> -0.51209 | L16: =-SUMIFS(Потребности!S:S,Потребности!$Y:$Y,Расходы!$A16)/1000000 -> -0.51209 | M16: =-SUMIFS(Потребности!T:T,Потребности!$Y:$Y,Расходы!$A16)/1000000 -> -0.51209 | N16: =-SUMIFS(Потребности!U:U,Потребности!$Y:$Y,Расходы!$A16)/1000000 -> -0.51209 | O16: =SUM(C16:N16) -> -5.1209 | P16: -5.7
A17: Развитие HR бренда | B17: Развитие HR бренда | C17: =-SUMIFS(Потребности!J:J,Потребности!$Y:$Y,Расходы!$A17)/1000000 -> 0 | D17: =-SUMIFS(Потребности!K:K,Потребности!$Y:$Y,Расходы!$A17)/1000000 -> -4 | E17: =-SUMIFS(Потребности!L:L,Потребности!$Y:$Y,Расходы!$A17)/1000000 -> 0 | F17: =-SUMIFS(Потребности!M:M,Потребности!$Y:$Y,Расходы!$A17)/1000000 -> -10.25 | G17: =-SUMIFS(Потребности!N:N,Потребности!$Y:$Y,Расходы!$A17)/1000000 -> 0 | H17: =-SUMIFS(Потребности!O:O,Потребности!$Y:$Y,Расходы!$A17)/1000000 -> 0 | I17: =-SUMIFS(Потребности!P:P,Потребности!$Y:$Y,Расходы!$A17)/1000000 -> -6 | J17: =-SUMIFS(Потребности!Q:Q,Потребности!$Y:$Y,Расходы!$A17)/1000000 -> 0 | K17: =-SUMIFS(Потребности!R:R,Потребности!$Y:$Y,Расходы!$A17)/1000000 -> 0 | L17: =-SUMIFS(Потребности!S:S,Потребности!$Y:$Y,Расходы!$A17)/1000000 -> 0 | M17: =-SUMIFS(Потребности!T:T,Потребности!$Y:$Y,Расходы!$A17)/1000000 -> 0 | N17: =-SUMIFS(Потребности!U:U,Потребности!$Y:$Y,Расходы!$A17)/1000000 -> 0 | O17: =SUM(C17:N17) -> -20.25 | P17: -14
A18: Карты лояльности (мотивация сотрудников) | B18: Карты лояльности (мотивация сотрудников) | C18: =-SUMIFS(Потребности!J:J,Потребности!$Y:$Y,Расходы!$A18)/1000000 -> -0.02799675 | D18: =-SUMIFS(Потребности!K:K,Потребности!$Y:$Y,Расходы!$A18)/1000000 -> -0.02799675 | E18: =-SUMIFS(Потребности!L:L,Потребности!$Y:$Y,Расходы!$A18)/1000000 -> -0.02799675 | F18: =-SUMIFS(Потребности!M:M,Потребности!$Y:$Y,Расходы!$A18)/1000000 -> -0.02799675 | G18: =-SUMIFS(Потребности!N:N,Потребности!$Y:$Y,Расходы!$A18)/1000000 -> -0.02799675 | H18: =-SUMIFS(Потребности!O:O,Потребности!$Y:$Y,Расходы!$A18)/1000000 -> -0.02799675 | I18: =-SUMIFS(Потребности!P:P,Потребности!$Y:$Y,Расходы!$A18)/1000000 -> -0.02799675 | J18: =-SUMIFS(Потребности!Q:Q,Потребности!$Y:$Y,Расходы!$A18)/1000000 -> -0.02799675 | K18: =-SUMIFS(Потребности!R:R,Потребности!$Y:$Y,Расходы!$A18)/1000000 -> -0.02799675 | L18: =-SUMIFS(Потребности!S:S,Потребности!$Y:$Y,Расходы!$A18)/1000000 -> -0.02799675 | M18: =-SUMIFS(Потребности!T:T,Потребности!$Y:$Y,Расходы!$A18)/1000000 -> -0.02799675 | N18: =-SUMIFS(Потребности!U:U,Потребности!$Y:$Y,Расходы!$A18)/1000000 -> -0.02799675 | O18: =SUM(C18:N18) -> -0.335961 | P18: 0
A19: Прочие компенсации и льготы | B19: Прочие компенсации и льготы | C19: =-SUMIFS(Потребности!J:J,Потребности!$Y:$Y,Расходы!$A19)/1000000 -> -0.041666667 | D19: =-SUMIFS(Потребности!K:K,Потребности!$Y:$Y,Расходы!$A19)/1000000 -> -0.041666667 | E19: =-SUMIFS(Потребности!L:L,Потребности!$Y:$Y,Расходы!$A19)/1000000 -> -0.041666667 | F19: =-SUMIFS(Потребности!M:M,Потребности!$Y:$Y,Расходы!$A19)/1000000 -> -0.041666667 | G19: =-SUMIFS(Потребности!N:N,Потребности!$Y:$Y,Расходы!$A19)/1000000 -> -0.041666667 | H19: =-SUMIFS(Потребности!O:O,Потребности!$Y:$Y,Расходы!$A19)/1000000 -> -0.041666667 | I19: =-SUMIFS(Потребности!P:P,Потребности!$Y:$Y,Расходы!$A19)/1000000 -> -0.041666667 | J19: =-SUMIFS(Потребности!Q:Q,Потребности!$Y:$Y,Расходы!$A19)/1000000 -> -0.041666667 | K19: =-SUMIFS(Потребности!R:R,Потребности!$Y:$Y,Расходы!$A19)/1000000 -> -0.041666667 | L19: =-SUMIFS(Потребности!S:S,Потребности!$Y:$Y,Расходы!$A19)/1000000 -> -0.041666667 | M19: =-SUMIFS(Потребности!T:T,Потребности!$Y:$Y,Расходы!$A19)/1000000 -> -0.041666667 | N19: =-SUMIFS(Потребности!U:U,Потребности!$Y:$Y,Расходы!$A19)/1000000 -> -0.041666667 | O19: =SUM(C19:N19) -> -0.5 | P19: -1.2
A20: Резерв на оплату отпусков | B20: Резерв на оплату отпусков | C20: 0.2 | D20: 0.2 | E20: 0.2 | F20: 0.2 | G20: 0.2 | H20: 0.2 | I20: 0.2 | J20: 0.2 | K20: 0.2 | L20: 0.2 | M20: 0.2 | N20: 0.2 | O20: =SUM(C20:N20) -> 2.4 | P20: 3
B21: Other PEX | C21: =SUM(C11:C20) -> -1.1561945 | D21: =SUM(D11:D20) -> -5.1511945 | E21: =SUM(E11:E20) -> -1.8032845 | F21: =SUM(F11:F20) -> -12.253285 | G21: =SUM(G11:G20) -> -1.6682845 | H21: =SUM(H11:H20) -> -1.6632845 | I21: =SUM(I11:I20) -> -7.8032845 | J21: =SUM(J11:J20) -> -2.0029545 | ... N21: =SUM(N11:N20) -> -1.7715894 | O21: =SUM(C21:N21) -> -40.286432 | P21: =SUM(P11:P20) -> -32.7
A22: PR/GR | B22: PR/GR | C22: =-SUMIFS(Потребности!J:J,Потребности!$Y:$Y,Расходы!$A22)/1000000 -> -0.675 | D22: =-SUMIFS(Потребности!K:K,Потребности!$Y:$Y,Расходы!$A22)/1000000 -> -3.525 | E22: =-SUMIFS(Потребности!L:L,Потребности!$Y:$Y,Расходы!$A22)/1000000 -> -4.25 | F22: =-SUMIFS(Потребности!M:M,Потребности!$Y:$Y,Расходы!$A22)/1000000 -> -2.675 | G22: =-SUMIFS(Потребности!N:N,Потребности!$Y:$Y,Расходы!$A22)/1000000 -> -0.875 | H22: =-SUMIFS(Потребности!O:O,Потребности!$Y:$Y,Расходы!$A22)/1000000 -> -1.9 | I22: =-SUMIFS(Потребности!P:P,Потребности!$Y:$Y,Расходы!$A22)/1000000 -> -4.675 | J22: =-SUMIFS(Потребности!Q:Q,Потребности!$Y:$Y,Расходы!$A22)/1000000 -> -2.025 | K22: =-SUMIFS(Потребности!R:R,Потребности!$Y:$Y,Расходы!$A22)/1000000 -> -3.45 | L22: =-SUMIFS(Потребности!S:S,Потребности!$Y:$Y,Расходы!$A22)/1000000 -> -1.975 | M22: =-SUMIFS(Потребности!T:T,Потребности!$Y:$Y,Расходы!$A22)/1000000 -> -5.875 | N22: =-SUMIFS(Потребности!U:U,Потребности!$Y:$Y,Расходы!$A22)/1000000 -> -1.4 | O22: =SUM(C22:N22) -> -33.3 | P22: -23.25
A23: Организация бизнес-мероприятий для партнеров | B23: Организация бизнес-мероприятий для партнеров | C23: =-SUMIFS(Потребности!J:J,Потребности!$Y:$Y,Расходы!$A23)/1000000 -> 0 | D23: =-SUMIFS(Потребности!K:K,Потребности!$Y:$Y,Расходы!$A23)/1000000 -> -1.5 | E23: =-SUMIFS(Потребности!L:L,Потребности!$Y:$Y,Расходы!$A23)/1000000 -> 0 | F23: =-SUMIFS(Потребности!M:M,Потребности!$Y:$Y,Расходы!$A23)/1000000 -> 0 | G23: =-SUMIFS(Потребности!N:N,Потребности!$Y:$Y,Расходы!$A23)/1000000 -> 0 | H23: =-SUMIFS(Потребности!O:O,Потребности!$Y:$Y,Расходы!$A23)/1000000 -> -0.15 | I23: =-SUMIFS(Потребности!P:P,Потребности!$Y:$Y,Расходы!$A23)/1000000 -> 0 | J23: =-SUMIFS(Потребности!Q:Q,Потребности!$Y:$Y,Расходы!$A23)/1000000 -> 0 | K23: =-SUMIFS(Потребности!R:R,Потребности!$Y:$Y,Расходы!$A23)/1000000 -> -0.15 | L23: =-SUMIFS(Потребности!S:S,Потребности!$Y:$Y,Расходы!$A23)/1000000 -> 0 | M23: =-SUMIFS(Потребности!T:T,Потребности!$Y:$Y,Расходы!$A23)/1000000 -> 0 | N23: =-SUMIFS(Потребности!U:U,Потребности!$Y:$Y,Расходы!$A23)/1000000 -> 0 | O23: =SUM(C23:N23) -> -1.8 | P23: -3.5
A24: Маркетинговые исследования | B24: Маркетинговые исследования | C24: =-SUMIFS(Потребности!J:J,Потребности!$Y:$Y,Расходы!$A24)/1000000 -> -1.1260256 | D24: =-SUMIFS(Потребности!K:K,Потребности!$Y:$Y,Расходы!$A24)/1000000 -> -1.1260256 | E24: =-SUMIFS(Потребности!L:L,Потребности!$Y:$Y,Расходы!$A24)/1000000 -> -1.1260256 | F24: =-SUMIFS(Потребности!M:M,Потребности!$Y:$Y,Расходы!$A24)/1000000 -> -1.1260256 | G24: =-SUMIFS(Потребности!N:N,Потребности!$Y:$Y,Расходы!$A24)/1000000 -> -1.1260256 | H24: =-SUMIFS(Потребности!O:O,Потребности!$Y:$Y,Расходы!$A24)/1000000 -> -1.1260256 | I24: =-SUMIFS(Потребности!P:P,Потребности!$Y:$Y,Расходы!$A24)/1000000 -> -1.4670104 | J24: =-SUMIFS(Потребности!Q:Q,Потребности!$Y:$Y,Расходы!$A24)/1000000 -> -1.4670104 | K24: =-SUMIFS(Потребности!R:R,Потребности!$Y:$Y,Расходы!$A24)/1000000 -> -1.4670104 | L24: =-SUMIFS(Потребности!S:S,Потребности!$Y:$Y,Расходы!$A24)/1000000 -> -1.4670104 | M24: =-SUMIFS(Потребности!T:T,Потребности!$Y:$Y,Расходы!$A24)/1000000 -> -1.4670104 | N24: =-SUMIFS(Потребности!U:U,Потребности!$Y:$Y,Расходы!$A24)/1000000 -> -1.4670104 | O24: =SUM(C24:N24) -> -15.558216 | P24: -8.3
A25: Маркетинг ВГО (не поставщики) | B25: Маркетинг ВГО (не поставщики) | C25: =-SUMIFS(Потребности!J:J,Потребности!$Y:$Y,Расходы!$A25)/1000000 -> -4.1666667 | D25: =-SUMIFS(Потребности!K:K,Потребности!$Y:$Y,Расходы!$A25)/1000000 -> -4.1666667 | E25: =-SUMIFS(Потребности!L:L,Потребности!$Y:$Y,Расходы!$A25)/1000000 -> -4.1666667 | F25: =-SUMIFS(Потребности!M:M,Потребности!$Y:$Y,Расходы!$A25)/1000000 -> -4.1666667 | G25: =-SUMIFS(Потребности!N:N,Потребности!$Y:$Y,Расходы!$A25)/1000000 -> -4.1666667 | H25: =-SUMIFS(Потребности!O:O,Потребности!$Y:$Y,Расходы!$A25)/1000000 -> -4.1666667 | I25: =-SUMIFS(Потребности!P:P,Потребности!$Y:$Y,Расходы!$A25)/1000000 -> -4.1666667 | J25: =-SUMIFS(Потребности!Q:Q,Потребности!$Y:$Y,Расходы!$A25)/1000000 -> -4.1666667 | K25: =-SUMIFS(Потребности!R:R,Потребности!$Y:$Y,Расходы!$A25)/1000000 -> -4.1666667 | L25: =-SUMIFS(Потребности!S:S,Потребности!$Y:$Y,Расходы!$A25)/1000000 -> -4.1666667 | M25: =-SUMIFS(Потребности!T:T,Потребности!$Y:$Y,Расходы!$A25)/1000000 -> -4.1666667 | N25: =-SUMIFS(Потребности!U:U,Потребности!$Y:$Y,Расходы!$A25)/1000000 -> -4.1666667 | O25: =SUM(C25:N25) -> -50 | P25: -20.2
A26: Расходы на маркетинг в сети интернет | B26: Расходы на маркетинг в сети интернет | C26: =-SUMIFS(Потребности!J:J,Потребности!$Y:$Y,Расходы!$A26)/1000000 -> -19.3793 | D26: =-SUMIFS(Потребности!K:K,Потребности!$Y:$Y,Расходы!$A26)/1000000 -> -51.604294 | E26: =-SUMIFS(Потребности!L:L,Потребности!$Y:$Y,Расходы!$A26)/1000000 -> -68.277733 | F26: =-SUMIFS(Потребности!M:M,Потребности!$Y:$Y,Расходы!$A26)/1000000 -> -71.584631 | G26: =-SUMIFS(Потребности!N:N,Потребности!$Y:$Y,Расходы!$A26)/1000000 -> -72.296031 | H26: =-SUMIFS(Потребности!O:O,Потребности!$Y:$Y,Расходы!$A26)/1000000 -> -72.409411 | I26: =-SUMIFS(Потребности!P:P,Потребности!$Y:$Y,Расходы!$A26)/1000000 -> -72.362725 | J26: =-SUMIFS(Потребности!Q:Q,Потребности!$Y:$Y,Расходы!$A26)/1000000 -> -81.232995 | K26: =-SUMIFS(Потребности!R:R,Потребности!$Y:$Y,Расходы!$A26)/1000000 -> -78.698632 | L26: =-SUMIFS(Потребности!S:S,Потребности!$Y:$Y,Расходы!$A26)/1000000 -> -113.89626 | M26: =-SUMIFS(Потребности!T:T,Потребности!$Y:$Y,Расходы!$A26)/1000000 -> -134.45461 | N26: =-SUMIFS(Потребности!U:U,Потребности!$Y:$Y,Расходы!$A26)/1000000 -> -163.80337 | O26: =SUM(C26:N26) -> -1000 | P26: -510.54
A27: Вознаграждения креаторам | B27: Вознаграждения креаторам | C27: =-SUMIFS(Потребности!J:J,Потребности!$Y:$Y,Расходы!$A27)/1000000 -> -4.24 | D27: =-SUMIFS(Потребности!K:K,Потребности!$Y:$Y,Расходы!$A27)/1000000 -> -7.42 | E27: =-SUMIFS(Потребности!L:L,Потребности!$Y:$Y,Расходы!$A27)/1000000 -> -14.31 | F27: =-SUMIFS(Потребности!M:M,Потребности!$Y:$Y,Расходы!$A27)/1000000 -> -14.787 | G27: =-SUMIFS(Потребности!N:N,Потребности!$Y:$Y,Расходы!$A27)/1000000 -> -15.105 | H27: =-SUMIFS(Потребности!O:O,Потребности!$Y:$Y,Расходы!$A27)/1000000 -> -15.9 | I27: =-SUMIFS(Потребности!P:P,Потребности!$Y:$Y,Расходы!$A27)/1000000 -> -15.9 | J27: =-SUMIFS(Потребности!Q:Q,Потребности!$Y:$Y,Расходы!$A27)/1000000 -> -17.013 | K27: =-SUMIFS(Потребности!R:R,Потребности!$Y:$Y,Расходы!$A27)/1000000 -> -17.013 | L27: =-SUMIFS(Потребности!S:S,Потребности!$Y:$Y,Расходы!$A27)/1000000 -> -17.013 | M27: =-SUMIFS(Потребности!T:T,Потребности!$Y:$Y,Расходы!$A27)/1000000 -> -18.285 | N27: =-SUMIFS(Потребности!U:U,Потребности!$Y:$Y,Расходы!$A27)/1000000 -> -19.08 | O27: =SUM(C27:N27) -> -176.066 | P27: -15.6
A28: Вознаграждения рекламным агентствам | B28: Вознаграждения рекламным агентствам | C28: =-SUMIFS(Потребности!J:J,Потребности!$Y:$Y,Расходы!$A28)/1000000 -> -66.25 | D28: =-SUMIFS(Потребности!K:K,Потребности!$Y:$Y,Расходы!$A28)/1000000 -> -66.25 | E28: =-SUMIFS(Потребности!L:L,Потребности!$Y:$Y,Расходы!$A28)/1000000 -> -66.25 | F28: =-SUMIFS(Потребности!M:M,Потребности!$Y:$Y,Расходы!$A28)/1000000 -> -66.25 | G28: =-SUMIFS(Потребности!N:N,Потребности!$Y:$Y,Расходы!$A28)/1000000 -> -66.25 | H28: =-SUMIFS(Потребности!O:O,Потребности!$Y:$Y,Расходы!$A28)/1000000 -> -66.25 | I28: =-SUMIFS(Потребности!P:P,Потребности!$Y:$Y,Расходы!$A28)/1000000 -> -66.25 | J28: =-SUMIFS(Потребности!Q:Q,Потребности!$Y:$Y,Расходы!$A28)/1000000 -> -66.25 | K28: =-SUMIFS(Потребности!R:R,Потребности!$Y:$Y,Расходы!$A28)/1000000 -> -66.25 | L28: =-SUMIFS(Потребности!S:S,Потребности!$Y:$Y,Расходы!$A28)/1000000 -> -66.25 | M28: =-SUMIFS(Потребности!T:T,Потребности!$Y:$Y,Расходы!$A28)/1000000 -> -66.25 | N28: =-SUMIFS(Потребности!U:U,Потребности!$Y:$Y,Расходы!$A28)/1000000 -> -66.25 | O28: =SUM(C28:N28) -> -795 | P28: -354.4
B29: Marketing | C29: =SUM(C22:C28) -> -95.836992 | D29: =SUM(D22:D28) -> -135.59199 | E29: =SUM(E22:E28) -> -158.38042 | F29: =SUM(F22:F28) -> -160.58932 | G29: =SUM(G22:G28) -> -159.81872 | H29: =SUM(H22:H28) -> -161.9021 | I29: =SUM(I22:I28) -> -164.8214 | J29: =SUM(J22:J28) -> -172.15467 | ... N29: =SUM(N22:N28) -> -256.16705 | O29: =SUM(C29:N29) -> -2071.7242 | P29: =SUM(P22:P26) -> -565.79
A30: IT | B30: Техподдержка и сопровождение программного обеспечения | C30: =-SUMIFS(Потребности!J:J,Потребности!$Y:$Y,Расходы!$A30)/1000000 -> -6.4490727 | D30: =-SUMIFS(Потребности!K:K,Потребности!$Y:$Y,Расходы!$A30)/1000000 -> -6.4490727 | E30: =-SUMIFS(Потребности!L:L,Потребности!$Y:$Y,Расходы!$A30)/1000000 -> -6.8490727 | F30: =-SUMIFS(Потребности!M:M,Потребности!$Y:$Y,Расходы!$A30)/1000000 -> -6.6490727 | G30: =-SUMIFS(Потребности!N:N,Потребности!$Y:$Y,Расходы!$A30)/1000000 -> -7.1490727 | H30: =-SUMIFS(Потребности!O:O,Потребности!$Y:$Y,Расходы!$A30)/1000000 -> -7.0995797 | I30: =-SUMIFS(Потребности!P:P,Потребности!$Y:$Y,Расходы!$A30)/1000000 -> -7.0420068 | J30: =-SUMIFS(Потребности!Q:Q,Потребности!$Y:$Y,Расходы!$A30)/1000000 -> -7.309943 | K30: =-SUMIFS(Потребности!R:R,Потребности!$Y:$Y,Расходы!$A30)/1000000 -> -8.8213416 | L30: =-SUMIFS(Потребности!S:S,Потребности!$Y:$Y,Расходы!$A30)/1000000 -> -9.4274407 | M30: =-SUMIFS(Потребности!T:T,Потребности!$Y:$Y,Расходы!$A30)/1000000 -> -9.4274407 | N30: =-SUMIFS(Потребности!U:U,Потребности!$Y:$Y,Расходы!$A30)/1000000 -> -9.4274407 | O30: =SUM(C30:N30) -> -92.100557 | P30: -58.6
B31: IT | C31: =SUM(C30) -> -6.4490727 | D31: =SUM(D30) -> -6.4490727 | E31: =SUM(E30) -> -6.8490727 | F31: =SUM(F30) -> -6.6490727 | G31: =SUM(G30) -> -7.1490727 | H31: =SUM(H30) -> -7.0995797 | I31: =SUM(I30) -> -7.0420068 | J31: =SUM(J30) -> -7.309943 | ... N31: =SUM(N30) -> -9.4274407 | O31: =SUM(C31:N31) -> -92.100557 | P31: =P30 -> -58.6
A32: Аренда | B32: Аренда | C32: =-SUMIFS(Потребности!J:J,Потребности!$Y:$Y,Расходы!$A32) -> 0 | D32: =-SUMIFS(Потребности!K:K,Потребности!$Y:$Y,Расходы!$A32) -> 0 | E32: =-SUMIFS(Потребности!L:L,Потребности!$Y:$Y,Расходы!$A32) -> 0 | F32: =-SUMIFS(Потребности!M:M,Потребности!$Y:$Y,Расходы!$A32) -> 0 | G32: =-SUMIFS(Потребности!N:N,Потребности!$Y:$Y,Расходы!$A32) -> 0 | H32: =-SUMIFS(Потребности!O:O,Потребности!$Y:$Y,Расходы!$A32) -> 0 | I32: =-SUMIFS(Потребности!P:P,Потребности!$Y:$Y,Расходы!$A32) -> 0 | J32: =-SUMIFS(Потребности!Q:Q,Потребности!$Y:$Y,Расходы!$A32) -> 0 | K32: =-SUMIFS(Потребности!R:R,Потребности!$Y:$Y,Расходы!$A32) -> 0 | L32: =-SUMIFS(Потребности!S:S,Потребности!$Y:$Y,Расходы!$A32) -> 0 | M32: =-SUMIFS(Потребности!T:T,Потребности!$Y:$Y,Расходы!$A32) -> 0 | N32: =-SUMIFS(Потребности!U:U,Потребности!$Y:$Y,Расходы!$A32) -> 0 | O32: =SUM(C32:N32) -> 0 | P32: 0
A33: Сервисный договор | B33: Сервисный договор | C33: -0.31333333 | D33: -0.31333333 | E33: -0.31333333 | F33: -0.31333333 | G33: -0.31333333 | H33: -0.31333333 | I33: -0.31333333 | J33: -0.31333333 | K33: -0.31333333 | L33: -0.31333333 | M33: -0.31333333 | N33: -0.31333333 | O33: =SUM(C33:N33) -> -3.76 | P33: -5
A34: Рекламный сбор | B34: Рекламный сбор | C34: =-('APP Медиа'!C54+'APP Перформанс'!C24+'Content factory'!C31+DMP!C9+DMP!C20+'In-store'!C28)*0.7% -> -1.9202511 | D34: =-('APP Медиа'!D54+'APP Перформанс'!D24+'Content factory'!D31+DMP!D9+DMP!D20+'In-store'!D28)*0.7% -> -4.8006591 | E34: =-('APP Медиа'!E54+'APP Перформанс'!E24+'Content factory'!E31+DMP!E9+DMP!E20+'In-store'!E28)*0.7% -> -6.720879 | F34: =-('APP Медиа'!F54+'APP Перформанс'!F24+'Content factory'!F31+DMP!F9+DMP!F20+'In-store'!F28)*0.7% -> -6.7207852 | G34: =-('APP Медиа'!G54+'APP Перформанс'!G24+'Content factory'!G31+DMP!G9+DMP!G20+'In-store'!G28)*0.7% -> -6.720879 | H34: =-('APP Медиа'!H54+'APP Перформанс'!H24+'Content factory'!H31+DMP!H9+DMP!H20+'In-store'!H28)*0.7% -> -6.720879 | I34: =-('APP Медиа'!I54+'APP Перформанс'!I24+'Content factory'!I31+DMP!I9+DMP!I20+'In-store'!I28)*0.7% -> -6.720879 | J34: =-('APP Медиа'!J54+'APP Перформанс'!J24+'Content factory'!J31+DMP!J9+DMP!J20+'In-store'!J28)*0.7% -> -7.6808482 | ... N34: =-('APP Медиа'!N54+'APP Перформанс'!N24+'Content factory'!N31+DMP!N9+DMP!N20+'In-store'!N28)*0.7% -> -16.322135 | O34: =SUM(C34:N34) -> -96.012182 | P34: -80.7
A35: Командировочные расходы | B35: Командировочные - Проезд | C35: -0.085833333 | D35: -0.085833333 | E35: -0.085833333 | F35: -0.085833333 | G35: -0.085833333 | H35: -0.085833333 | I35: -0.085833333 | J35: -0.085833333 | K35: -0.085833333 | L35: -0.085833333 | M35: -0.085833333 | N35: -0.085833333 | O35: =SUM(C35:N35) -> -1.03 | P35: -2.6
A36: Командировочные расходы | B36: Командировочные - Проживание | C36: -0.06 | D36: -0.06 | E36: -0.06 | F36: -0.06 | G36: -0.06 | H36: -0.06 | I36: -0.06 | J36: -0.06 | K36: -0.06 | L36: -0.06 | M36: -0.06 | N36: -0.06 | O36: =SUM(C36:N36) -> -0.72 | P36: -1.9
A37: Командировочные расходы | B37: Командировочные - Суточные | C37: -0.02 | D37: -0.02 | E37: -0.02 | F37: -0.02 | G37: -0.02 | H37: -0.02 | I37: -0.02 | J37: -0.02 | K37: -0.02 | L37: -0.02 | M37: -0.02 | N37: -0.02 | O37: =SUM(C37:N37) -> -0.24 | P37: -0.2
A38: Представительские расходы | B38: Представительские расходы | C38: -0.045833333 | D38: -0.045833333 | E38: -0.045833333 | F38: -0.045833333 | G38: -0.045833333 | H38: -0.045833333 | I38: -0.045833333 | J38: -0.045833333 | K38: -0.045833333 | L38: -0.045833333 | M38: -0.045833333 | N38: -0.045833333 | O38: =SUM(C38:N38) -> -0.55 | P38: -0.7
A39: Почтовые, курьерские услуги | B39: Почтовые, курьерские услуги | C39: 0 | D39: 0 | E39: 0 | F39: 0 | G39: 0 | H39: 0 | I39: 0 | J39: 0 | K39: 0 | L39: 0 | M39: 0 | N39: 0 | O39: =SUM(C39:N39) -> 0 | P39: -0.5
B40: Other OPEX | C40: =SUM(C32:C39) -> -2.4452511 | D40: =SUM(D32:D39) -> -5.3256591 | E40: =SUM(E32:E39) -> -7.245879 | F40: =SUM(F32:F39) -> -7.2457852 | G40: =SUM(G32:G39) -> -7.245879 | H40: =SUM(H32:H39) -> -7.245879 | I40: =SUM(I32:I39) -> -7.245879 | J40: =SUM(J32:J39) -> -8.2058482 | ... N40: =SUM(N32:N39) -> -16.847135 | O40: =SUM(C40:N40) -> -102.31218 | P40: =SUM(P32:P39) -> -91.6
B41: OPEX | C41: =SUM(C31,C29,C21,C10,C40) -> -219.85156 | D41: =SUM(D31,D29,D21,D10,D40) -> -268.62408 | E41: =SUM(E31,E29,E21,E10,E40) -> -290.98923 | F41: =SUM(F31,F29,F21,F10,F40) -> -305.40031 | G41: =SUM(G31,G29,G21,G10,G40) -> -296.76001 | H41: =SUM(H31,H29,H21,H10,H40) -> -295.74945 | I41: =SUM(I31,I29,I21,I10,I40) -> -307.69665 | J41: =SUM(J31,J29,J21,J10,J40) -> -292.55704 | ... N41: =SUM(N31,N29,N21,N10,N40) -> -416.91636 | O41: =SUM(C41:N41) -> -3742.7863 | P41: =SUM(P31,P29,P21,P10,P40) -> -1868.7614
A42: AT Platform | B42: AT Platform | C42: =-SUMIFS(Потребности!J:J,Потребности!$Y:$Y,Расходы!$A42)/1000000-PEX!BG$16/1000000 -> -42.458922 | D42: =-SUMIFS(Потребности!K:K,Потребности!$Y:$Y,Расходы!$A42)/1000000-PEX!BH$16/1000000 -> -43.04558 | E42: =-SUMIFS(Потребности!L:L,Потребности!$Y:$Y,Расходы!$A42)/1000000-PEX!BI$16/1000000 -> -44.505901 | F42: =-SUMIFS(Потребности!M:M,Потребности!$Y:$Y,Расходы!$A42)/1000000-PEX!BJ$16/1000000 -> -44.369799 | G42: =-SUMIFS(Потребности!N:N,Потребности!$Y:$Y,Расходы!$A42)/1000000-PEX!BK$16/1000000 -> -44.528812 | H42: =-SUMIFS(Потребности!O:O,Потребности!$Y:$Y,Расходы!$A42)/1000000-PEX!BL$16/1000000 -> -44.182905 | I42: =-SUMIFS(Потребности!P:P,Потребности!$Y:$Y,Расходы!$A42)/1000000-PEX!BM$16/1000000 -> -47.108845 | J42: =-SUMIFS(Потребности!Q:Q,Потребности!$Y:$Y,Расходы!$A42)/1000000-PEX!BN$16/1000000 -> -46.623045 | K42: =-SUMIFS(Потребности!R:R,Потребности!$Y:$Y,Расходы!$A42)/1000000-PEX!BO$16/1000000 -> -46.242626 | L42: =-SUMIFS(Потребности!S:S,Потребности!$Y:$Y,Расходы!$A42)/1000000-PEX!BP$16/1000000 -> -46.09234 | M42: =-SUMIFS(Потребности!T:T,Потребности!$Y:$Y,Расходы!$A42)/1000000-PEX!BQ$16/1000000 -> -45.970661 | N42: =-SUMIFS(Потребности!U:U,Потребности!$Y:$Y,Расходы!$A42)/1000000-PEX!BR$16/1000000 -> -45.904437 | O42: =SUM(C42:N42) -> -541.03387 | P42: -447.2
A43: Instore Digital | B43: Instore Digital | C43: =-SUMIFS(Потребности!J:J,Потребности!$Y:$Y,Расходы!$A43)/1000000 -> 0 | D43: =-SUMIFS(Потребности!K:K,Потребности!$Y:$Y,Расходы!$A43)/1000000 -> 0 | E43: =-SUMIFS(Потребности!L:L,Потребности!$Y:$Y,Расходы!$A43)/1000000 -> 0 | F43: =-SUMIFS(Потребности!M:M,Потребности!$Y:$Y,Расходы!$A43)/1000000 -> -10.23056 | G43: =-SUMIFS(Потребности!N:N,Потребности!$Y:$Y,Расходы!$A43)/1000000 -> -18.36096 | H43: =-SUMIFS(Потребности!O:O,Потребности!$Y:$Y,Расходы!$A43)/1000000 -> -52.572558 | I43: =-SUMIFS(Потребности!P:P,Потребности!$Y:$Y,Расходы!$A43)/1000000 -> -45.678337 | J43: =-SUMIFS(Потребности!Q:Q,Потребности!$Y:$Y,Расходы!$A43)/1000000 -> -56.619953 | K43: =-SUMIFS(Потребности!R:R,Потребности!$Y:$Y,Расходы!$A43)/1000000 -> -155.41 | L43: =-SUMIFS(Потребности!S:S,Потребности!$Y:$Y,Расходы!$A43)/1000000 -> -170.7335 | M43: =-SUMIFS(Потребности!T:T,Потребности!$Y:$Y,Расходы!$A43)/1000000 -> 0 | N43: =-SUMIFS(Потребности!U:U,Потребности!$Y:$Y,Расходы!$A43)/1000000 -> -100 | O43: =SUM(C43:N43) -> -609.60587 | P43: -732.4
B44: Capex | C44: =C42+C43 -> -42.458922 | D44: =D42+D43 -> -43.04558 | E44: =E42+E43 -> -44.505901 | F44: =F42+F43 -> -54.600359 | G44: =G42+G43 -> -62.889772 | H44: =H42+H43 -> -96.755463 | I44: =I42+I43 -> -92.787183 | J44: =J42+J43 -> -103.243 | ... N44: =N42+N43 -> -145.90444 | O44: =SUM(C44:N44) -> -1150.6397 | P44: =SUM(P42:P43) -> -1179.6

Sheet М+ справочно
A1: М+ (МАГНИТ ПЛЮС) - СПРАВОЧНО
A2: Выручка М+ приходит из того же пула маркетинговой бек-маржи, но в P&L AdTech не входит и на EBITDA не влияет.
Q3: Описание: выручка М+ по продуктам (справочно). Логика: выручка = объём × цена (охват × цена контакта, поставщики × бюджет, офферы × стоимость, отправки × цена); партнёрские продукты - ввод. Итог → P&L, блок «Справочно».
A4: 1. ДРАЙВЕРЫ И ВЫРУЧКА ПО ПРОДУКТАМ
A5: Показатель | B5: Ед. изм. | C5: янв | D5: фев | E5: мар | F5: апр | G5: май | H5: июн | I5: июл | J5: авг | K5: сен | L5: окт | M5: ноя | N5: дек | O5: 2027 | P5: 2026
A6: CVM: охват | B6: млн контактов | C6: 28.925792 | D6: =C6*(D8/C8) -> 29.572552 | E6: =D6*(E8/D8) -> 29.262754 | F6: =E6*(F8/E8) -> 29.57153 | G6: =F6*(G8/F8) -> 29.66848 | H6: =G6*(H8/G8) -> 30.023414 | I6: =H6*(I8/H8) -> 30.166125 | J6: =I6*(J8/I8) -> 30.495208 | K6: =J6*(K8/J8) -> 30.887127 | ... N6: =M6*(N8/M8) -> 31.278202 | O6: =SUM(C6:N6) -> 362.22268
A7: CVM: цена контакта | B7: руб. | C7: 5.75 | D7: 5.75 | E7: 5.75 | F7: 5.75 | G7: 5.75 | H7: 5.75 | I7: 5.75 | J7: 5.75 | K7: 5.75 | L7: 5.75 | M7: 5.75 | N7: 5.75 | O7: =AVERAGE(C7:N7) -> 5.75 | Q7: Заморожена на весь год - индексации нет
A8: CVM: конверсия оффера | B8: % | C8: 0.13248544 | D8: 0.13544772 | E8: 0.13402879 | F8: 0.13544304 | G8: 0.13588709 | H8: 0.13751275 | I8: 0.13816639 | J8: 0.13967366 | K8: 0.14146871 | L8: 0.14201542 | M8: 0.14365748 | N8: 0.14325991 | O8: =AVERAGE(C8:N8) -> 0.13825387
A9: CVM - выручка | B9: млн руб. | C9: =C6*C7 -> 166.32331 | D9: =D6*D7 -> 170.04217 | E9: =E6*E7 -> 168.26084 | F9: =F6*F7 -> 170.0363 | G9: =G6*G7 -> 170.59376 | H9: =H6*H7 -> 172.63463 | I9: =I6*I7 -> 173.45522 | J9: =J6*J7 -> 175.34745 | ... N9: =N6*N7 -> 179.84966 | O9: =SUM(C9:N9) -> 2082.7804
A11: Кешбек на SKU: количество поставщиков | B11: ед. | C11: 38 | D11: 45.6 | E11: 54.264 | F11: 64.03152 | G11: 74.916878 | H11: 86.903579 | I11: 99.939116 | J11: 113.93059 | K11: 128.74157 | L11: 144.19056 | M11: 160.05152 | N11: 176.05667 | O11: =AVERAGE(C11:N11) -> 98.8855 | Q11: Рост с 38 до 176 поставщиков за год
A12: Кешбек на SKU: темп роста числа поставщиков | B12: % | C12: 0 | D12: 0.2 | E12: 0.19 | F12: 0.18 | G12: 0.17 | H12: 0.16 | I12: 0.15 | J12: 0.14 | K12: 0.13 | L12: 0.12 | M12: 0.11 | N12: 0.1 | O12: =AVERAGE(C12:N12) -> 0.1375
A13: Кешбек на SKU: средний бюджет поставщика | B13: млн руб. | C13: 0.96135 | D13: 0.96135 | E13: 0.96135 | F13: 0.96135 | G13: 0.96135 | H13: 0.96135 | I13: 0.96135 | J13: 0.96135 | K13: 0.96135 | L13: 0.96135 | M13: 0.96135 | N13: 0.96135 | O13: =AVERAGE(C13:N13) -> 0.96135 | Q13: Зафиксирован на весь год
A14: Кешбек на SKU - выручка | B14: млн руб. | C14: =C11*C13 -> 36.5313 | D14: =D11*D13 -> 43.83756 | E14: =E11*E13 -> 52.166696 | F14: =F11*F13 -> 61.556702 | G14: =G11*G13 -> 72.021341 | H14: =H11*H13 -> 83.544756 | I14: =I11*I13 -> 96.076469 | J14: =J11*J13 -> 109.52717 | ... N14: =N11*N13 -> 169.25208 | O14: =SUM(C14:N14) -> 1140.7629
A16: Любимые категории: офферов в месяц | B16: ед. | C16: 17.645833 | D16: 24 | E16: 25.383333 | F16: 26.8464 | G16: 28.393797 | H16: 30.030384 | I16: 31.761302 | J16: 33.591988 | K16: 35.528193 | L16: 37.575999 | M16: 39.741837 | N16: 42.032513 | O16: =AVERAGE(C16:N16) -> 31.044298
A17: Любимые категории: стоимость оффера | B17: млн руб. | C17: 2.072161 | D17: 2.079309 | E17: 2.110254 | F17: 2.145641 | G17: 2.180502 | H17: 2.221156 | I17: 2.258018 | J17: 2.290118 | K17: 2.344347 | L17: 2.418103 | M17: 2.436691 | N17: 2.525662 | O17: =AVERAGE(C17:N17) -> 2.2568302
A18: Любимые категории - выручка | B18: млн руб. | C18: =C16*C17 -> 36.565007 | D18: =D16*D17 -> 49.903416 | E18: =E16*E17 -> 53.56528 | F18: =F16*F17 -> 57.602737 | G18: =G16*G17 -> 61.912731 | H18: =H16*H17 -> 66.702168 | I18: =I16*I17 -> 71.717592 | J18: =J16*J17 -> 76.929616 | ... N18: =N16*N17 -> 106.15992 | O18: =SUM(C18:N18) -> 852.05009
A20: Подписка: офферов в месяц | B20: ед. | C20: 10.5 | D20: 10.875 | E20: 11.26875 | F20: 11.682188 | G20: 13.116297 | H20: 13.572112 | I20: 14.050717 | J20: 14.553253 | K20: 16.080916 | L20: 16.634962 | M20: 17.21671 | N20: 17.827545 | O20: =AVERAGE(C20:N20) -> 13.948204
A21: Подписка: стоимость оффера | B21: млн руб. | C21: 1.907511 | D21: 2.083482 | E21: 2.127355 | F21: 2.172303 | G21: 2.24894 | H21: 2.296244 | I21: 2.34469 | J21: 2.394314 | K21: 2.472168 | L21: 2.524377 | M21: 2.577844 | N21: 2.632607 | O21: =AVERAGE(C21:N21) -> 2.3151529
A22: Подписка - выручка | B22: млн руб. | C22: =C20*C21 -> 20.028865 | D22: =D20*D21 -> 22.657867 | E22: =E20*E21 -> 23.972632 | F22: =F20*F21 -> 25.377252 | G22: =G20*G21 -> 29.497765 | H22: =H20*H21 -> 31.164881 | I22: =I20*I21 -> 32.944576 | J22: =J20*J21 -> 34.845057 | ... N22: =N20*N21 -> 46.93292 | O22: =SUM(C22:N22) -> 393.55145
A24: Цели: охват | B24: млн контактов | C24: 3.6331018 | D24: 3.780562 | E24: 3.803905 | F24: 3.9051938 | G24: 3.9770198 | H24: 4.0821023 | I24: 4.1571707 | J24: 4.2567728 | K24: 4.3644902 | L24: 4.4327272 | M24: 4.5341747 | N24: 4.5700041 | O24: =SUM(C24:N24) -> 49.497224
A25: Цели: цена контакта | B25: руб. | C25: 5.75 | D25: 5.75 | E25: 5.75 | F25: 5.75 | G25: 5.75 | H25: 5.75 | I25: 5.75 | J25: 5.75 | K25: 5.75 | L25: 5.75 | M25: 5.75 | N25: 5.75 | O25: =AVERAGE(C25:N25) -> 5.75
A26: Цели - выручка | B26: млн руб. | C26: =C24*C25 -> 20.890335 | D26: =D24*D25 -> 21.738232 | E26: =E24*E25 -> 21.872453 | F26: =F24*F25 -> 22.454865 | G26: =G24*G25 -> 22.867864 | H26: =H24*H25 -> 23.472088 | I26: =I24*I25 -> 23.903731 | J26: =J24*J25 -> 24.476443 | ... N26: =N24*N25 -> 26.277524 | O26: =SUM(C26:N26) -> 284.60904
A28: CRM: квота push | B28: млн отправок | C28: 3.7 | D28: 3.7 | E28: 3.7 | F28: 3.7 | G28: 3.7 | H28: 3.7 | I28: 3.7 | J28: 3.7 | K28: 3.7 | L28: 3.7 | M28: 3.7 | N28: 3.7 | O28: =SUM(C28:N28) -> 44.4
A29: CRM: цена отправки | B29: руб. | C29: 5.42 | D29: 5.42 | E29: 5.42 | F29: 5.42 | G29: 5.42 | H29: 5.42 | I29: 5.42 | J29: 5.42 | K29: 5.42 | L29: 5.42 | M29: 5.42 | N29: 5.42 | O29: =AVERAGE(C29:N29) -> 5.42
A30: CRM - выручка | B30: млн руб. | C30: =C28*C29 -> 20.054 | D30: =D28*D29 -> 20.054 | E30: =E28*E29 -> 20.054 | F30: =F28*F29 -> 20.054 | G30: =G28*G29 -> 20.054 | H30: =H28*H29 -> 20.054 | I30: =I28*I29 -> 20.054 | J30: =J28*J29 -> 20.054 | ... N30: =N28*N29 -> 20.054 | O30: =SUM(C30:N30) -> 240.648
A32: Партнёрские продукты - выручка | B32: млн руб. | C32: 37.5 | D32: 37.5 | E32: 37.5 | F32: 37.5 | G32: 37.5 | H32: 37.5 | I32: 37.5 | J32: 37.5 | K32: 37.5 | L32: 37.5 | M32: 37.5 | N32: 37.5 | O32: =SUM(C32:N32) -> 450
A34: ВЫРУЧКА М+ ВСЕГО | B34: млн руб. | C34: =C9+C14+C18+C22+C26+C30+C32 -> 337.89281 | D34: =D9+D14+D18+D22+D26+D30+D32 -> 365.73325 | E34: =E9+E14+E18+E22+E26+E30+E32 -> 377.3919 | F34: =F9+F14+F18+F22+F26+F30+F32 -> 394.58185 | G34: =G9+G14+G18+G22+G26+G30+G32 -> 414.44746 | H34: =H9+H14+H18+H22+H26+H30+H32 -> 435.07252 | I34: =I9+I14+I18+I22+I26+I30+I32 -> 455.65159 | J34: =J9+J14+J18+J22+J26+J30+J32 -> 478.67974 | ... N34: =N9+N14+N18+N22+N26+N30+N32 -> 586.0261 | O34: =SUM(C34:N34) -> 5444.4019 | P34: 3007

Sheet Потребности
A1: В руб. без НДС | Z1: Описание: реестр потребностей 2027, руб. без НДС. Логика: строка = расход с разбивкой по месяцам; 2027 = Σ месяцев; «Мэппинг к отчетности» (кол. Y) - ключ SUMIFS для листа «Расходы»; BU'26 и факт 7м26 - для сравнения. | AF1: Калькулятор прогноза расходов по IT софт + облака | AP1: Описание: прогноз IT-софта. Логика: цена за ед. 2027 = стоимость 2026 / кол-во 2026 × (1 + инфляция); прогноз = кол-во 2027 × цена; дельта = прогноз − стратегия; итоги → реестр через SUMIFS. | AS1: Вознаграждения рекламным агентствам 2027 | AW1: Описание: премия рекламных агентств 2027. Логика: премия = выручка × % СК по группам (не поставщики / поставщики ММ); итог → строка «Вознаграждения рекламным агентствам» реестра (÷ 12 по месяцам).
AF2: Модификатор | AH2: Значение
A3: Вид расхода | B3: Статья бюджета | C3: Модель | D3: CAPEX/OPEX | E3: Вид ИТ расхода | F3: Кол-во, ед. | G3: Ст-ть, руб. | H3: Заказчик/Ответственный | I3: Комментарий | J3: 46388 | K3: 46419 | L3: 46447 | M3: 46478 | N3: 46508 | O3: 46539 | P3: 46569 | Q3: 46600 | R3: 46631 | S3: 46661 | T3: 46692 | U3: 46722 | V3: 2027 | W3: BU'26 | X3: ACT 7m26 | Y3: Мэппинг к отчетности | AF3: Инфляция, год | AH3: 0.07
A4: Marketing | B4: Вознаграждения рекламным агентствам | C4: 0 | D4: OPEX | E4: н.п. | F4: н.п. | G4: н.п. | H4: Мухутдинов Дамир, Соколов Павел | J4: =$V$4/12 -> 66250000 | K4: =$V$4/12 -> 66250000 | L4: =$V$4/12 -> 66250000 | M4: =$V$4/12 -> 66250000 | N4: =$V$4/12 -> 66250000 | O4: =$V$4/12 -> 66250000 | P4: =$V$4/12 -> 66250000 | Q4: =$V$4/12 -> 66250000 | ... U4: =$V$4/12 -> 66250000 | V4: =Потребности!AV7 -> 795000000 | W4: 3.5173007e+08 | X4: 1.3606165e+08 | Y4: Вознаграждения рекламным агентствам | AS4: В руб. | AT4: Выручка | AU4: %% СК | AV4: Премия СК
A5: Marketing | B5: Расходы на маркетинг в сети интернет | C5: DMP+Online | D5: OPEX | E5: н.п. | F5: н.п. | G5: н.п. | H5: Тарасов Михаил, Кирилова Анастасия | I5: Суммы взяты из бюджета 2027 файла Астемира, рассчитаны от прогнозируемой выручки | J5: 11541342 | K5: 30732937 | L5: 40662804 | M5: 42632227 | N5: 43055902 | O5: 43123425 | P5: 43095621 | Q5: 48378310 | R5: 46868970 | S5: 67830919 | T5: 80074444 | U5: 97553100 | V5: =SUM(J5:U5) -> 595550000 | W5: 533800000 | X5: 3.5078074e+08 | Y5: Расходы на маркетинг в сети интернет | AF5: Софт | AG5: Ответственный | AH5: Статья | AI5: 2026 | AK5: 2027 | AM5: 2027 | AN5: 2027 | AO5: Дельта | AS5: Не поставщики | AT5: 1800000000 | AU5: 0.3 | AV5: =AT5*AU5 -> 540000000
A6: Marketing | B6: Расходы на маркетинг в сети интернет | C6: DMP+Online (ЦМ) | D6: OPEX | E6: н.п. | F6: н.п. | G6: н.п. | H6: Ардаширов Денис | J6: =J5*(K6/K5) -> 7837957.9 | K6: =K5*(L6/L5) -> 20871357 | L6: =L5*(M6/M5) -> 27614929 | M6: =M5*(N6/N5) -> 28952404 | N6: =N5*(O6/O5) -> 29240130 | O6: =O5*(P6/P5) -> 29285986 | P6: =P5*(Q6/Q5) -> 29267104 | Q6: =Q5*(R6/R5) -> 32854685 | ... U6: =U5*(V6/V5) -> 66250275 | V6: =1000000000-V5 -> 404450000 | W6: 0 | X6: 0 | Y6: Расходы на маркетинг в сети интернет | AI6: Кол-во | AJ6: Стоимость | AK6: Кол-во | AL6: Цена за ед. | AM6: прогноз | AN6: стратегия | AS6: Поставщики ММ | AT6: 850000000 | AU6: 0.3 | AV6: =AT6*AU6 -> 255000000
A7: Marketing | B7: Организация бизнес-мероприятий для партнеров | C7: Собственные клиентские мероприятия | D7: OPEX | E7: н.п. | F7: н.п. | G7: н.п. | H7: Вайнштейн Роман, Чистякова Катерина | J7: 0 | K7: 1500000 | L7: 0 | M7: 0 | N7: 0 | O7: 150000 | P7: 0 | Q7: 0 | R7: 150000 | S7: 0 | T7: 0 | U7: 0 | V7: =SUM(J7:U7) -> 1800000 | W7: 10000000 | X7: 0 | Y7: Организация бизнес-мероприятий для партнеров | AF7: Allure TestOps | AG7: IT - Буров Глеб, Сидоренко Ирина | AH7: CAPEX | AI7: 13 | AJ7: 190237.19 | AK7: 10 | AL7: =AJ7/AI7*(1+AH$3) -> 15657.984 | AM7: =AK7*AL7 -> 156579.84 | AO7: =AN7-AM7 -> -156579.84 | AS7: Итого | AT7: =SUM(AT5:AT6) -> 2650000000 | AV7: =SUM(AV5:AV6) -> 795000000
A8: Marketing | B8: PR/GR | C8: Участие в мероприятиях рыночных | D8: OPEX | E8: н.п. | F8: н.п. | G8: н.п. | H8: Вайнштейн Роман, Чистякова Катерина | J8: 0 | K8: 0 | L8: 0 | M8: 200000 | N8: 0 | O8: 0 | P8: 0 | Q8: 0 | R8: 0 | S8: 200000 | T8: 5000000 | U8: 0 | V8: =SUM(J8:U8) -> 5400000 | W8: 15000000 | X8: 0 | Y8: PR/GR | AF8: Miro Starter | AG8: IT - Буров Глеб, Сидоренко Ирина | AH8: CAPEX | AI8: 53 | AJ8: 628299.1 | AK8: 53 | AL8: =AJ8/AI8*(1+AH$3) -> 12684.529 | AM8: =AK8*AL8 -> 672280.04 | AO8: =AN8-AM8 -> -672280.04
A9: Marketing | B9: PR/GR | C9: Пиар (платные публикации и посевы) | D9: OPEX | E9: н.п. | F9: н.п. | G9: н.п. | H9: Вайнштейн Роман, Чистякова Катерина | J9: 675000 | K9: 3525000 | L9: 4250000 | M9: 2475000 | N9: 875000 | O9: 1900000 | P9: 4675000 | Q9: 2025000 | R9: 3450000 | S9: 1775000 | T9: 875000 | U9: 1400000 | V9: =SUM(J9:U9) -> 27900000 | W9: 10000000 | X9: 0 | Y9: PR/GR | AF9: Postman Professional | AG9: IT - Буров Глеб, Сидоренко Ирина | AH9: CAPEX | AI9: 13 | AJ9: 572000 | AK9: 6 | AL9: =AJ9/AI9*(1+AH$3) -> 47080 | AM9: =AK9*AL9 -> 282480 | AO9: =AN9-AM9 -> -282480
A10: MIP/CF | B10: Расходы на маркетинг в сети интернет | C10: 0 | D10: OPEX | E10: н.п. | F10: н.п. | G10: н.п. | H10: Егор Юркевич, Аксенова Татьяна, Заворина Диана | J10: ='Content factory'!C24*1000000 -> 4240000 | K10: ='Content factory'!D24*1000000 -> 7420000 | L10: ='Content factory'!E24*1000000 -> 14310000 | M10: ='Content factory'!F24*1000000 -> 14787000 | N10: ='Content factory'!G24*1000000 -> 15105000 | O10: ='Content factory'!H24*1000000 -> 15900000 | P10: ='Content factory'!I24*1000000 -> 15900000 | Q10: ='Content factory'!J24*1000000 -> 17013000 | ... U10: ='Content factory'!N24*1000000 -> 19080000 | V10: =SUM(J10:U10) -> 176066000 | W10: 15900000 | X10: 18324000 | Y10: Вознаграждения креаторам | AF10: Yonote | AG10: IT - Буров Глеб, Сидоренко Ирина | AH10: CAPEX | AI10: 5 | AJ10: 13200 | AK10: 5 | AL10: =AJ10/AI10*(1+AH$3) -> 2824.8 | AM10: =AK10*AL10 -> 14124 | AO10: =AN10-AM10 -> -14124
A11: Marketing | B11: Маркетинг ВГО (не поставщики) | C11: 0 | D11: OPEX | E11: н.п. | F11: н.п. | G11: н.п. | J11: =$V11/12 -> 4166666.7 | K11: =$V11/12 -> 4166666.7 | L11: =$V11/12 -> 4166666.7 | M11: =$V11/12 -> 4166666.7 | N11: =$V11/12 -> 4166666.7 | O11: =$V11/12 -> 4166666.7 | P11: =$V11/12 -> 4166666.7 | Q11: =$V11/12 -> 4166666.7 | ... U11: =$V11/12 -> 4166666.7 | V11: 50000000 | W11: 20200000 | X11: 20200289 | Y11: Маркетинг ВГО (не поставщики) | AF11: Claude Code | AG11: IT - Буров Глеб | AH11: CAPEX | AI11: 0 | AJ11: 0 | AK11: 20 | AL11: 140000 | AM11: =AK11*AL11 -> 2800000 | AO11: =AN11-AM11 -> -2800000
A12: IT | B12: Allure TestOps | C12: 0 | D12: CAPEX | E12: Service soft | F12: =SUMIFS(Потребности!AK:AK,Потребности!AF:AF,Потребности!B12,Потребности!AH:AH,Потребности!D12) -> 10 | G12: =SUMIFS(Потребности!AM:AM,Потребности!AF:AF,Потребности!B12,Потребности!AH:AH,Потребности!D12) -> 156579.84 | H12: Буров Глеб (IT), Сидоренко Ирина | J12: =$V12/12 -> 13048.32 | K12: =$V12/12 -> 13048.32 | L12: =$V12/12 -> 13048.32 | M12: =$V12/12 -> 13048.32 | N12: =$V12/12 -> 13048.32 | O12: =$V12/12 -> 13048.32 | P12: =$V12/12 -> 13048.32 | Q12: =$V12/12 -> 13048.32 | ... U12: =$V12/12 -> 13048.32 | V12: =SUMIFS(Потребности!AM:AM,Потребности!AF:AF,Потребности!B12,Потребности!AH:AH,Потребности!D12) -> 156579.84 | W12: 190237.19 | X12: 0 | Y12: AT Platform | AF12: Codex Pro/ChatGPT | AG12: IT - Буров Глеб | AH12: CAPEX | AI12: 0 | AJ12: 0 | AK12: 50 | AL12: 140000 | AM12: =AK12*AL12 -> 7000000
A13: IT | B13: Miro Starter | C13: 0 | D13: CAPEX | E13: Service soft | F13: =SUMIFS(Потребности!AK:AK,Потребности!AF:AF,Потребности!B13,Потребности!AH:AH,Потребности!D13) -> 53 | G13: =SUMIFS(Потребности!AM:AM,Потребности!AF:AF,Потребности!B13,Потребности!AH:AH,Потребности!D13) -> 672280.04 | H13: Буров Глеб (IT), Сидоренко Ирина | J13: =$V13/12 -> 56023.336 | K13: =$V13/12 -> 56023.336 | L13: =$V13/12 -> 56023.336 | M13: =$V13/12 -> 56023.336 | N13: =$V13/12 -> 56023.336 | O13: =$V13/12 -> 56023.336 | P13: =$V13/12 -> 56023.336 | Q13: =$V13/12 -> 56023.336 | ... U13: =$V13/12 -> 56023.336 | V13: =SUMIFS(Потребности!AM:AM,Потребности!AF:AF,Потребности!B13,Потребности!AH:AH,Потребности!D13) -> 672280.04 | W13: 628299.1 | X13: 0 | Y13: AT Platform | AF13: Claude Code | AG13: Finance | AH13: CAPEX | AI13: 0 | AJ13: 0 | AK13: 6 | AL13: =AL11 -> 140000 | AM13: =AK13*AL13 -> 840000 | AO13: =AN13-AM13 -> -840000
A14: IT | B14: Postman Professional | C14: 0 | D14: CAPEX | E14: Service soft | F14: =SUMIFS(Потребности!AK:AK,Потребности!AF:AF,Потребности!B14,Потребности!AH:AH,Потребности!D14) -> 6 | G14: =SUMIFS(Потребности!AM:AM,Потребности!AF:AF,Потребности!B14,Потребности!AH:AH,Потребности!D14) -> 282480 | H14: Буров Глеб (IT), Сидоренко Ирина | J14: =$V14/12 -> 23540 | K14: =$V14/12 -> 23540 | L14: =$V14/12 -> 23540 | M14: =$V14/12 -> 23540 | N14: =$V14/12 -> 23540 | O14: =$V14/12 -> 23540 | P14: =$V14/12 -> 23540 | Q14: =$V14/12 -> 23540 | ... U14: =$V14/12 -> 23540 | V14: =SUMIFS(Потребности!AM:AM,Потребности!AF:AF,Потребности!B14,Потребности!AH:AH,Потребности!D14) -> 282480 | W14: 572000 | X14: 0 | Y14: AT Platform | AF14: Proxyman Team | AG14: IT - Буров Глеб, Сидоренко Ирина | AH14: CAPEX | AI14: 9 | AJ14: 84059.217 | AK14: 5 | AL14: =AJ14/AI14*(1+AH$3) -> 9993.7069 | AM14: =AK14*AL14 -> 49968.535 | AO14: =AN14-AM14 -> -49968.535
A15: IT | B15: Yonote | C15: 0 | D15: CAPEX | E15: Service soft | F15: =SUMIFS(Потребности!AK:AK,Потребности!AF:AF,Потребности!B15,Потребности!AH:AH,Потребности!D15) -> 5 | G15: =SUMIFS(Потребности!AM:AM,Потребности!AF:AF,Потребности!B15,Потребности!AH:AH,Потребности!D15) -> 14124 | H15: Буров Глеб (IT), Сидоренко Ирина | J15: =$V15/12 -> 1177 | K15: =$V15/12 -> 1177 | L15: =$V15/12 -> 1177 | M15: =$V15/12 -> 1177 | N15: =$V15/12 -> 1177 | O15: =$V15/12 -> 1177 | P15: =$V15/12 -> 1177 | Q15: =$V15/12 -> 1177 | ... U15: =$V15/12 -> 1177 | V15: =SUMIFS(Потребности!AM:AM,Потребности!AF:AF,Потребности!B15,Потребности!AH:AH,Потребности!D15) -> 14124 | W15: 13200 | X15: 0 | Y15: AT Platform | AF15: Zoom | AG15: Вайнштейн Роман | AH15: CAPEX | AI15: 1 | AJ15: 105600 | AK15: 0 | AL15: =AJ15/AI15*(1+AH$3) -> 112992 | AM15: =AK15*AL15 -> 0 | AO15: =AN15-AM15 -> 0
A16: IT | B16: JetBrains IDE | C16: 0 | D16: CAPEX | E16: Service soft | F16: =SUMIFS(Потребности!AK:AK,Потребности!AF:AF,Потребности!B16,Потребности!AH:AH,Потребности!D16) -> 0 | G16: =SUMIFS(Потребности!AM:AM,Потребности!AF:AF,Потребности!B16,Потребности!AH:AH,Потребности!D16) -> 0 | H16: Буров Глеб (IT), Сидоренко Ирина | J16: =$V16/12 -> 0 | K16: =$V16/12 -> 0 | L16: =$V16/12 -> 0 | M16: =$V16/12 -> 0 | N16: =$V16/12 -> 0 | O16: =$V16/12 -> 0 | P16: =$V16/12 -> 0 | Q16: =$V16/12 -> 0 | ... U16: =$V16/12 -> 0 | V16: =SUMIFS(Потребности!AM:AM,Потребности!AF:AF,Потребности!B16,Потребности!AH:AH,Потребности!D16) -> 0 | W16: 3432000 | X16: 0 | Y16: AT Platform | AF16: Think-cell | AG16: Finance | AH16: CAPEX | AI16: 5 | AJ16: 115000 | AK16: 7 | AL16: =AJ16/AI16*(1+AH$3) -> 24610 | AM16: =AK16*AL16 -> 172270 | AO16: =AN16-AM16 -> -172270
A17: IT | B17: JetBrains AI Assistant | C17: 0 | D17: CAPEX | E17: Service soft | F17: =SUMIFS(Потребности!AK:AK,Потребности!AF:AF,Потребности!B17,Потребности!AH:AH,Потребности!D17) -> 0 | G17: =SUMIFS(Потребности!AM:AM,Потребности!AF:AF,Потребности!B17,Потребности!AH:AH,Потребности!D17) -> 0 | H17: Буров Глеб (IT), Сидоренко Ирина | I17: Буров: при наличии Codex/Claude подписка не нужна | J17: =$V17/12 -> 0 | K17: =$V17/12 -> 0 | L17: =$V17/12 -> 0 | M17: =$V17/12 -> 0 | N17: =$V17/12 -> 0 | O17: =$V17/12 -> 0 | P17: =$V17/12 -> 0 | Q17: =$V17/12 -> 0 | ... U17: =$V17/12 -> 0 | V17: =SUMIFS(Потребности!AM:AM,Потребности!AF:AF,Потребности!B17,Потребности!AH:AH,Потребности!D17) -> 0 | W17: 4290000 | X17: 0 | Y17: AT Platform | AF17: Optimacros | AG17: Finance (Елена Белявская) | AH17: CAPEX | AI17: 1 | AJ17: 4860000 | AK17: =AI17 -> 1 | AL17: =AJ17/AI17*(1+AH$3) -> 5200200 | AM17: =AK17*AL17 -> 5200200
A18: IT | B18: Proxyman Team | C18: 0 | D18: CAPEX | E18: Service soft | F18: =SUMIFS(Потребности!AK:AK,Потребности!AF:AF,Потребности!B18,Потребности!AH:AH,Потребности!D18) -> 5 | G18: =SUMIFS(Потребности!AM:AM,Потребности!AF:AF,Потребности!B18,Потребности!AH:AH,Потребности!D18) -> 49968.535 | H18: Буров Глеб (IT), Сидоренко Ирина | J18: =$V18/12 -> 4164.0445 | K18: =$V18/12 -> 4164.0445 | L18: =$V18/12 -> 4164.0445 | M18: =$V18/12 -> 4164.0445 | N18: =$V18/12 -> 4164.0445 | O18: =$V18/12 -> 4164.0445 | P18: =$V18/12 -> 4164.0445 | Q18: =$V18/12 -> 4164.0445 | ... U18: =$V18/12 -> 4164.0445 | V18: =SUMIFS(Потребности!AM:AM,Потребности!AF:AF,Потребности!B18,Потребности!AH:AH,Потребности!D18) -> 49968.535 | W18: 84059.217 | X18: 58524.6 | Y18: AT Platform | AF18: Brand Analytics | AG18: Вайнштейн Роман/Питьева Татьяна | AH18: CAPEX | AI18: 1 | AJ18: 572400 | AK18: 0 | AL18: =AJ18/AI18*(1+AH$3) -> 612468 | AM18: =AK18*AL18 -> 0 | AO18: =AN18-AM18 -> 0
A19: IT | B19: Zoom | C19: 0 | D19: CAPEX | E19: Soft | F19: =SUMIFS(Потребности!AK:AK,Потребности!AF:AF,Потребности!B19,Потребности!AH:AH,Потребности!D19) -> 0 | G19: =SUMIFS(Потребности!AM:AM,Потребности!AF:AF,Потребности!B19,Потребности!AH:AH,Потребности!D19) -> 0 | H19: Вайнштейн Роман | V19: =SUMIFS(Потребности!AM:AM,Потребности!AF:AF,Потребности!B19,Потребности!AH:AH,Потребности!D19) -> 0 | W19: 105600 | X19: 0 | Y19: AT Platform | AF19: InAppStory (ПО «Редактор и партнерские SDK для повествований») | AG19: Алеманова Юлия/Карагодина Тамара | AH19: CAPEX | AI19: 1 | AJ19: 1000000 | AK19: 0 | AL19: =AJ19/AI19*(1+AH$3) -> 1070000 | AM19: =AK19*AL19 -> 0 | AO19: =AN19-AM19 -> 0
A20: IT | B20: Think-cell | C20: 0 | D20: CAPEX | E20: Soft | F20: =SUMIFS(Потребности!AK:AK,Потребности!AF:AF,Потребности!B20,Потребности!AH:AH,Потребности!D20) -> 7 | G20: =SUMIFS(Потребности!AM:AM,Потребности!AF:AF,Потребности!B20,Потребности!AH:AH,Потребности!D20) -> 172270 | H20: Finance | J20: =$V20/12 -> 14355.833 | K20: =$V20/12 -> 14355.833 | L20: =$V20/12 -> 14355.833 | M20: =$V20/12 -> 14355.833 | N20: =$V20/12 -> 14355.833 | O20: =$V20/12 -> 14355.833 | P20: =$V20/12 -> 14355.833 | Q20: =$V20/12 -> 14355.833 | ... U20: =$V20/12 -> 14355.833 | V20: =SUMIFS(Потребности!AM:AM,Потребности!AF:AF,Потребности!B20,Потребности!AH:AH,Потребности!D20) -> 172270 | W20: 115000 | X20: 0 | Y20: AT Platform | AF20: ПО Pitchdeck Pro 1 year Subscription | AG20: Ожаровская Вероника | AH20: CAPEX | AI20: 2 | AJ20: 53509.84 | AK20: 3 | AL20: =AJ20/AI20*(1+AH$3) -> 28627.764 | AM20: =AK20*AL20 -> 85883.293 | AO20: =AN20-AM20 -> -85883.293
