Workbook

Sheet AdTech 2026
B1: Сентябрь | H1: Октябрь | N1: С сентября
B2: ACT 2026 | D2: CTRL 2026 | F2: ACT VS CTRL | H2: ACT 2026 | J2: CTRL 2026 | L2: ACT VS CTRL | N2: ACT 2026 | P2: CTRL 2026 | R2: ACT VS CTRL
B3: ABC | C3: %GR | D3: ABS | E3: % GR | F3: ABS | G3: % GR | H3: ABC | I3: %GR | J3: ABS | K3: % GR | L3: ABS | M3: % GR | N3: ABC | O3: %GR | P3: ABS | Q3: % GR | R3: ABS | S3: % GR
A4: Gross Revenue | B4: =IF('AdTech Сентябрь'!C5="","",'AdTech Сентябрь'!C5) -> 1.1831932e+09 | C4: =IF(B4="","",B4/B$4) -> 1 | D4: ='AdTech Сентябрь'!E5 -> 1.1262005e+09 | E4: =D4/D$4 -> 1 | F4: =IF(B4="","",B4-D4) -> 56992670 | G4: =IF(B4="","",C4-E4) -> 0 | H4: =IF('AdTech Октябрь'!C5="","",'AdTech Октябрь'!C5) | I4: =IF(H4="","",H4/H$4) | J4: ='AdTech Октябрь'!E5 -> 1.250104e+09 | K4: =J4/J$4 -> 1 | L4: =IF(H4="","",H4-J4) | M4: =IF(H4="","",I4-K4) | N4: =N(B4)+N(H4) -> 1.1831932e+09 | O4: =IF(N4="","",N4/N$4) -> 1 | P4: =D4+IF(H4="",0,J4) -> 1.1262005e+09 | Q4: =P4/P$4 -> 1 | R4: =IF(N4="","",N4-P4) -> 56992670 | S4: =IF(N4="","",O4-Q4) -> 0
A5: APP | B5: =IF('AdTech Сентябрь'!C6="","",'AdTech Сентябрь'!C6) -> 4.6752566e+08 | C5: =IF(B5="","",B5/B$4) -> 0.39513891 | D5: ='AdTech Сентябрь'!E6 -> 7.6532661e+08 | E5: =D5/D$4 -> 0.67956515 | F5: =IF(B5="","",B5-D5) -> -2.9780094e+08 | G5: =IF(B5="","",C5-E5) -> -0.28442623 | H5: =IF('AdTech Октябрь'!C6="","",'AdTech Октябрь'!C6) | I5: =IF(H5="","",H5/H$4) | J5: ='AdTech Октябрь'!E6 -> 5.618219e+08 | K5: =J5/J$4 -> 0.44942013 | L5: =IF(H5="","",H5-J5) | M5: =IF(H5="","",I5-K5) | N5: =N(B5)+N(H5) -> 4.6752566e+08 | O5: =IF(N5="","",N5/N$4) -> 0.39513891 | P5: =D5+IF(H5="",0,J5) -> 7.6532661e+08 | Q5: =P5/P$4 -> 0.67956515 | R5: =IF(N5="","",N5-P5) -> -2.9780094e+08 | S5: =IF(N5="","",O5-Q5) -> -0.28442623
A6: MIP | B6: =IF('AdTech Сентябрь'!C7="","",'AdTech Сентябрь'!C7) -> 0 | C6: =IF(B6="","",B6/B$4) -> 0 | D6: ='AdTech Сентябрь'!E7 -> 841669.4 | E6: =D6/D$4 -> 0.00074735307 | F6: =IF(B6="","",B6-D6) -> -841669.4 | G6: =IF(B6="","",C6-E6) -> -0.00074735307 | H6: =IF('AdTech Октябрь'!C7="","",'AdTech Октябрь'!C7) | I6: =IF(H6="","",H6/H$4) | J6: ='AdTech Октябрь'!E7 -> 816164.27 | K6: =J6/J$4 -> 0.0006528771 | L6: =IF(H6="","",H6-J6) | M6: =IF(H6="","",I6-K6) | N6: =N(B6)+N(H6) -> 0 | O6: =IF(N6="","",N6/N$4) -> 0 | P6: =D6+IF(H6="",0,J6) -> 841669.4 | Q6: =P6/P$4 -> 0.00074735307 | R6: =IF(N6="","",N6-P6) -> -841669.4 | S6: =IF(N6="","",O6-Q6) -> -0.00074735307
A7: Magnit Market | B7: =IF('AdTech Сентябрь'!C8="","",'AdTech Сентябрь'!C8) -> 0 | C7: =IF(B7="","",B7/B$4) -> 0 | D7: ='AdTech Сентябрь'!E8 -> 463410.2 | E7: =D7/D$4 -> 0.00041148108 | F7: =IF(B7="","",B7-D7) -> -463410.2 | G7: =IF(B7="","",C7-E7) -> -0.00041148108 | H7: =IF('AdTech Октябрь'!C8="","",'AdTech Октябрь'!C8) | I7: =IF(H7="","",H7/H$4) | J7: ='AdTech Октябрь'!E8 -> 449367.47 | K7: =J7/J$4 -> 0.00035946407 | L7: =IF(H7="","",H7-J7) | M7: =IF(H7="","",I7-K7) | N7: =N(B7)+N(H7) -> 0 | O7: =IF(N7="","",N7/N$4) -> 0 | P7: =D7+IF(H7="",0,J7) -> 463410.2 | Q7: =P7/P$4 -> 0.00041148108 | R7: =IF(N7="","",N7-P7) -> -463410.2 | S7: =IF(N7="","",O7-Q7) -> -0.00041148108
A8: DMP+ Analitycs | B8: =IF('AdTech Сентябрь'!C9="","",'AdTech Сентябрь'!C9) -> 2432515.4 | C8: =IF(B8="","",B8/B$4) -> 0.0020558904 | D8: ='AdTech Сентябрь'!E9 -> 4861968.8 | E8: =D8/D$4 -> 0.0043171432 | F8: =IF(B8="","",B8-D8) -> -2429453.4 | G8: =IF(B8="","",C8-E8) -> -0.0022612528 | H8: =IF('AdTech Октябрь'!C9="","",'AdTech Октябрь'!C9) | I8: =IF(H8="","",H8/H$4) | J8: ='AdTech Октябрь'!E9 -> 5009486.8 | K8: =J8/J$4 -> 0.004007256 | L8: =IF(H8="","",H8-J8) | M8: =IF(H8="","",I8-K8) | N8: =N(B8)+N(H8) -> 2432515.4 | O8: =IF(N8="","",N8/N$4) -> 0.0020558904 | P8: =D8+IF(H8="",0,J8) -> 4861968.8 | Q8: =P8/P$4 -> 0.0043171432 | R8: =IF(N8="","",N8-P8) -> -2429453.4 | S8: =IF(N8="","",O8-Q8) -> -0.0022612528
A9: DMP+Online | B9: =IF('AdTech Сентябрь'!C10="","",'AdTech Сентябрь'!C10) -> 2.016697e+08 | C9: =IF(B9="","",B9/B$4) -> 0.17044529 | D9: ='AdTech Сентябрь'!E10 -> 69479583 | E9: =D9/D$4 -> 0.061693796 | F9: =IF(B9="","",B9-D9) -> 1.3219012e+08 | G9: =IF(B9="","",C9-E9) -> 0.10875149 | H9: =IF('AdTech Октябрь'!C10="","",'AdTech Октябрь'!C10) | I9: =IF(H9="","",H9/H$4) | J9: ='AdTech Октябрь'!E10 -> 91818953 | K9: =J9/J$4 -> 0.073449052 | L9: =IF(H9="","",H9-J9) | M9: =IF(H9="","",I9-K9) | N9: =N(B9)+N(H9) -> 2.016697e+08 | O9: =IF(N9="","",N9/N$4) -> 0.17044529 | P9: =D9+IF(H9="",0,J9) -> 69479583 | Q9: =P9/P$4 -> 0.061693796 | R9: =IF(N9="","",N9-P9) -> 1.3219012e+08 | S9: =IF(N9="","",O9-Q9) -> 0.10875149
A10: Instore digital | B10: =IF('AdTech Сентябрь'!C11="","",'AdTech Сентябрь'!C11) -> 4.134699e+08 | C10: =IF(B10="","",B10/B$4) -> 0.34945257 | D10: ='AdTech Сентябрь'!E11 -> 1.6137721e+08 | E10: =D10/D$4 -> 0.1432935 | F10: =IF(B10="","",B10-D10) -> 2.5209269e+08 | G10: =IF(B10="","",C10-E10) -> 0.20615908 | H10: =IF('AdTech Октябрь'!C11="","",'AdTech Октябрь'!C11) | I10: =IF(H10="","",H10/H$4) | J10: ='AdTech Октябрь'!E11 -> 2.6290778e+08 | K10: =J10/J$4 -> 0.21030873 | L10: =IF(H10="","",H10-J10) | M10: =IF(H10="","",I10-K10) | N10: =N(B10)+N(H10) -> 4.134699e+08 | O10: =IF(N10="","",N10/N$4) -> 0.34945257 | P10: =D10+IF(H10="",0,J10) -> 1.6137721e+08 | Q10: =P10/P$4 -> 0.1432935 | R10: =IF(N10="","",N10-P10) -> 2.5209269e+08 | S10: =IF(N10="","",O10-Q10) -> 0.20615908
A11: Instore digital_2.0 | B11: =IF('AdTech Сентябрь'!C12="","",'AdTech Сентябрь'!C12) -> 0 | C11: =IF(B11="","",B11/B$4) -> 0 | D11: ='AdTech Сентябрь'!E12 -> 1.213322e+08 | E11: =D11/D$4 -> 0.10773588 | F11: =IF(B11="","",B11-D11) -> -1.213322e+08 | G11: =IF(B11="","",C11-E11) -> -0.10773588 | H11: =IF('AdTech Октябрь'!C12="","",'AdTech Октябрь'!C12) | I11: =IF(H11="","",H11/H$4) | J11: ='AdTech Октябрь'!E12 -> 47092216 | K11: =J11/J$4 -> 0.037670638 | L11: =IF(H11="","",H11-J11) | M11: =IF(H11="","",I11-K11) | N11: =N(B11)+N(H11) -> 0 | O11: =IF(N11="","",N11/N$4) -> 0 | P11: =D11+IF(H11="",0,J11) -> 1.213322e+08 | Q11: =P11/P$4 -> 0.10773588 | R11: =IF(N11="","",N11-P11) -> -1.213322e+08 | S11: =IF(N11="","",O11-Q11) -> -0.10773588
A12: POSM | B12: =IF('AdTech Сентябрь'!C13="","",'AdTech Сентябрь'!C13) -> 456221.13 | C12: =IF(B12="","",B12/B$4) -> 0.00038558466 | D12: ='AdTech Сентябрь'!E13 -> 2517847.2 | E12: =D12/D$4 -> 0.0022357007 | F12: =IF(B12="","",B12-D12) -> -2061626.1 | G12: =IF(B12="","",C12-E12) -> -0.001850116 | H12: =IF('AdTech Октябрь'!C13="","",'AdTech Октябрь'!C13) | I12: =IF(H12="","",H12/H$4) | J12: ='AdTech Октябрь'!E13 -> 2669920.9 | K12: =J12/J$4 -> 0.002135759 | L12: =IF(H12="","",H12-J12) | M12: =IF(H12="","",I12-K12) | N12: =N(B12)+N(H12) -> 456221.13 | O12: =IF(N12="","",N12/N$4) -> 0.00038558466 | P12: =D12+IF(H12="",0,J12) -> 2517847.2 | Q12: =P12/P$4 -> 0.0022357007 | R12: =IF(N12="","",N12-P12) -> -2061626.1 | S12: =IF(N12="","",O12-Q12) -> -0.001850116
A13: Other | B13: =IF('AdTech Сентябрь'!C14="","",'AdTech Сентябрь'!C14) -> 94811798 | C13: =IF(B13="","",B13/B$4) -> 0.080132138 | D13: ='AdTech Сентябрь'!E14 -> 0 | E13: =D13/D$4 -> 0 | F13: =IF(B13="","",B13-D13) -> 94811798 | G13: =IF(B13="","",C13-E13) -> 0.080132138 | H13: =IF('AdTech Октябрь'!C14="","",'AdTech Октябрь'!C14) | I13: =IF(H13="","",H13/H$4) | J13: ='AdTech Октябрь'!E14 -> 0 | K13: =J13/J$4 -> 0 | L13: =IF(H13="","",H13-J13) | M13: =IF(H13="","",I13-K13) | N13: =N(B13)+N(H13) -> 94811798 | O13: =IF(N13="","",N13/N$4) -> 0.080132138 | P13: =D13+IF(H13="",0,J13) -> 0 | Q13: =P13/P$4 -> 0 | R13: =IF(N13="","",N13-P13) -> 94811798 | S13: =IF(N13="","",O13-Q13) -> 0.080132138
A14: Кроссформатные пакеты | B14: =IF('AdTech Сентябрь'!C15="","",'AdTech Сентябрь'!C15) -> 2827369.1 | C14: =IF(B14="","",B14/B$4) -> 0.0023896091 | D14: ='AdTech Сентябрь'!E15 -> 0 | E14: =D14/D$4 -> 0 | F14: =IF(B14="","",B14-D14) -> 2827369.1 | G14: =IF(B14="","",C14-E14) -> 0.0023896091 | H14: =IF('AdTech Октябрь'!C15="","",'AdTech Октябрь'!C15) | I14: =IF(H14="","",H14/H$4) | J14: ='AdTech Октябрь'!E15 -> 0 | K14: =J14/J$4 -> 0 | L14: =IF(H14="","",H14-J14) | M14: =IF(H14="","",I14-K14) | N14: =N(B14)+N(H14) -> 2827369.1 | O14: =IF(N14="","",N14/N$4) -> 0.0023896091 | P14: =D14+IF(H14="",0,J14) -> 0 | Q14: =P14/P$4 -> 0 | R14: =IF(N14="","",N14-P14) -> 2827369.1 | S14: =IF(N14="","",O14-Q14) -> 0.0023896091
A15: М+ и сверка со сплитом | B15: =IF('AdTech Сентябрь'!C16="","",'AdTech Сентябрь'!C16) -> 0 | C15: =IF(B15="","",B15/B$4) -> 0 | D15: ='AdTech Сентябрь'!E16 -> 0 | E15: =D15/D$4 -> 0 | F15: =IF(B15="","",B15-D15) -> 0 | G15: =IF(B15="","",C15-E15) -> 0 | H15: =IF('AdTech Октябрь'!C16="","",'AdTech Октябрь'!C16) | I15: =IF(H15="","",H15/H$4) | J15: ='AdTech Октябрь'!E16 -> 2.7751821e+08 | K15: =J15/J$4 -> 0.2219961 | L15: =IF(H15="","",H15-J15) | M15: =IF(H15="","",I15-K15) | N15: =N(B15)+N(H15) -> 0 | O15: =IF(N15="","",N15/N$4) -> 0 | P15: =D15+IF(H15="",0,J15) -> 0 | Q15: =P15/P$4 -> 0 | R15: =IF(N15="","",N15-P15) -> 0 | S15: =IF(N15="","",O15-Q15) -> 0
... A22: EBITDA | B22: =IF('AdTech Сентябрь'!C23="","",'AdTech Сентябрь'!C23) -> 1.1264105e+09 | C22: =IF(B22="","",B22/B$4) -> 0.95200899 | D22: ='AdTech Сентябрь'!E23 -> 6.2050465e+08 | E22: =D22/D$4 -> 0.55097174 | F22: =IF(B22="","",B22-D22) -> 5.0590589e+08 | G22: =IF(B22="","",C22-E22) -> 0.40103725 | H22: =IF('AdTech Октябрь'!C23="","",'AdTech Октябрь'!C23) | I22: =IF(H22="","",H22/H$4) | J22: ='AdTech Октябрь'!E23 -> 1.0073904e+09 | K22: =J22/J$4 -> 0.80584524 | L22: =IF(H22="","",H22-J22) | M22: =IF(H22="","",I22-K22) | N22: =N(B22)+N(H22) -> 1.1264105e+09 | O22: =IF(N22="","",N22/N$4) -> 0.95200899 | P22: =D22+IF(H22="",0,J22) -> 6.2050465e+08 | Q22: =P22/P$4 -> 0.55097174 | R22: =IF(N22="","",N22-P22) -> 5.0590589e+08 | S22: =IF(N22="","",O22-Q22) -> 0.40103725
B28: =D22 -> 6.2050465e+08 | H28: =J22 -> 1.0073904e+09
B29: =IF(B4="","",F4*E22) -> 31401350 | H29: =IF(H4="","",L4*K22)
B30: =IF(B4="","",G5*B$4) -> -3.3653118e+08 | H30: =IF(H4="","",M5*H$4)
B31: =IF(B4="","",G6*B$4) -> -884263.05 | H31: =IF(H4="","",M6*H$4)
B32: =IF(B4="","",G7*B$4) -> -486861.61 | H32: =IF(H4="","",M7*H$4)
B33: =IF(B4="","",G8*B$4) -> -2675498.9 | H33: =IF(H4="","",M8*H$4)
B34: =IF(B4="","",G9*B$4) -> 1.2867402e+08 | H34: =IF(H4="","",M9*H$4)
B35: =IF(B4="","",G10*B$4) -> 2.4392601e+08 | H35: =IF(H4="","",M10*H$4)
B36: =IF(B4="","",G11*B$4) -> -1.2747236e+08 | H36: =IF(H4="","",M11*H$4)
B37: =IF(B4="","",G12*B$4) -> -2189044.6 | H37: =IF(H4="","",M12*H$4)
B38: =IF(B4="","",G13*B$4) -> 94811798 | H38: =IF(H4="","",M13*H$4)
B39: =IF(B4="","",G14*B$4) -> 2827369.1 | H39: =IF(H4="","",M14*H$4)
B40: =IF(B4="","",G15*B$4) -> 0 | H40: =IF(H4="","",M15*H$4)
B41: =IF(B4="","",G16*B$4) -> 35597312 | H41: =IF(H4="","",M16*H$4)
B42: =IF(B4="","",G17*B$4) -> 1.7960979e+08 | H42: =IF(H4="","",M17*H$4)
B43: =IF(B4="","",G18*B$4) -> 4346889.3 | H43: =IF(H4="","",M18*H$4)
B44: =IF(B4="","",G19*B$4) -> 2.6131006e+08 | H44: =IF(H4="","",M19*H$4)
B45: =IF(B4="","",G20*B$4) -> -2539054.1 | H45: =IF(H4="","",M20*H$4)
B46: =IF(B4="","",G21*B$4) -> -3820467.6 | H46: =IF(H4="","",M21*H$4)

Sheet AdTech Октябрь
C2: Октябрь
C3: ACT 2026 | E3: CTRL 2026 | G3: ACT VS CTRL
C4: ABC | D4: % GR | E4: ABS | F4: % GR | G4: ABS | H4: % GR
B5: Gross Revenue | D5: =IF(C5="","",C5/C$5) | E5: 1.250104e+09 | F5: =E5/E$5 -> 1 | G5: =IF(C5="","",C5-E5) | H5: =IF(C5="","",D5-F5)
B6: APP | D6: =IF(C6="","",C6/C$5) | E6: 5.618219e+08 | F6: =E6/E$5 -> 0.44942013 | G6: =IF(C6="","",C6-E6) | H6: =IF(C6="","",D6-F6)
B7: MIP | D7: =IF(C7="","",C7/C$5) | E7: 816164.27 | F7: =E7/E$5 -> 0.0006528771 | G7: =IF(C7="","",C7-E7) | H7: =IF(C7="","",D7-F7)
B8: Magnit Market | D8: =IF(C8="","",C8/C$5) | E8: 449367.47 | F8: =E8/E$5 -> 0.00035946407 | G8: =IF(C8="","",C8-E8) | H8: =IF(C8="","",D8-F8)
B9: DMP+ Analitycs | D9: =IF(C9="","",C9/C$5) | E9: 5009486.8 | F9: =E9/E$5 -> 0.004007256 | G9: =IF(C9="","",C9-E9) | H9: =IF(C9="","",D9-F9)
B10: DMP+Online | D10: =IF(C10="","",C10/C$5) | E10: 91818953 | F10: =E10/E$5 -> 0.073449052 | G10: =IF(C10="","",C10-E10) | H10: =IF(C10="","",D10-F10)
B11: Instore digital | D11: =IF(C11="","",C11/C$5) | E11: 2.6290778e+08 | F11: =E11/E$5 -> 0.21030873 | G11: =IF(C11="","",C11-E11) | H11: =IF(C11="","",D11-F11)
B12: Instore digital_2.0 | D12: =IF(C12="","",C12/C$5) | E12: 47092216 | F12: =E12/E$5 -> 0.037670638 | G12: =IF(C12="","",C12-E12) | H12: =IF(C12="","",D12-F12)
B13: POSM | D13: =IF(C13="","",C13/C$5) | E13: 2669920.9 | F13: =E13/E$5 -> 0.002135759 | G13: =IF(C13="","",C13-E13) | H13: =IF(C13="","",D13-F13)
B14: Other | D14: =IF(C14="","",C14/C$5) | E14: 0 | F14: =E14/E$5 -> 0 | G14: =IF(C14="","",C14-E14) | H14: =IF(C14="","",D14-F14)
B15: Кроссформатные пакеты | D15: =IF(C15="","",C15/C$5) | E15: 0 | F15: =E15/E$5 -> 0 | G15: =IF(C15="","",C15-E15) | H15: =IF(C15="","",D15-F15)
B16: М+ и сверка со сплитом | D16: =IF(C16="","",C16/C$5) | E16: 2.7751821e+08 | F16: =E16/E$5 -> 0.2219961 | G16: =IF(C16="","",C16-E16) | H16: =IF(C16="","",D16-F16)
... B22: Other OPEX | D22: =IF(C22="","",C22/C$5) | E22: -5915678.6 | F22: =E22/E$5 -> -0.0047321492 | G22: =IF(C22="","",C22-E22) | H22: =IF(C22="","",D22-F22)
B23: EBITDA | C23: =IF(C5="","",C5+SUM(C17:C22)) | D23: =IF(C23="","",C23/C$5) | E23: =IF(E5="","",E5+SUM(E17:E22)) -> 1.0073904e+09 | F23: =E23/E$5 -> 0.80584524 | G23: =IF(C23="","",C23-E23) | H23: =IF(C23="","",D23-F23)

Sheet AdTech Сентябрь
C2: Сентябрь
C3: ACT 2026 | E3: CTRL 2026 | G3: ACT VS CTRL
C4: ABC | D4: % GR | E4: ABS | F4: % GR | G4: ABS | H4: % GR
B5: Gross Revenue | C5: 1.1831932e+09 | D5: =IF(C5="","",C5/C$5) -> 1 | E5: 1.1262005e+09 | F5: =E5/E$5 -> 1 | G5: =IF(C5="","",C5-E5) -> 56992670 | H5: =IF(C5="","",D5-F5) -> 0
B6: APP | C6: 4.6752566e+08 | D6: =IF(C6="","",C6/C$5) -> 0.39513891 | E6: 7.6532661e+08 | F6: =E6/E$5 -> 0.67956515 | G6: =IF(C6="","",C6-E6) -> -2.9780094e+08 | H6: =IF(C6="","",D6-F6) -> -0.28442623
B7: MIP | C7: 0 | D7: =IF(C7="","",C7/C$5) -> 0 | E7: 841669.4 | F7: =E7/E$5 -> 0.00074735307 | G7: =IF(C7="","",C7-E7) -> -841669.4 | H7: =IF(C7="","",D7-F7) -> -0.00074735307
B8: Magnit Market | C8: 0 | D8: =IF(C8="","",C8/C$5) -> 0 | E8: 463410.2 | F8: =E8/E$5 -> 0.00041148108 | G8: =IF(C8="","",C8-E8) -> -463410.2 | H8: =IF(C8="","",D8-F8) -> -0.00041148108
B9: DMP+ Analitycs | C9: 2432515.4 | D9: =IF(C9="","",C9/C$5) -> 0.0020558904 | E9: 4861968.8 | F9: =E9/E$5 -> 0.0043171432 | G9: =IF(C9="","",C9-E9) -> -2429453.4 | H9: =IF(C9="","",D9-F9) -> -0.0022612528
B10: DMP+Online | C10: 2.016697e+08 | D10: =IF(C10="","",C10/C$5) -> 0.17044529 | E10: 69479583 | F10: =E10/E$5 -> 0.061693796 | G10: =IF(C10="","",C10-E10) -> 1.3219012e+08 | H10: =IF(C10="","",D10-F10) -> 0.10875149
B11: Instore digital | C11: 4.134699e+08 | D11: =IF(C11="","",C11/C$5) -> 0.34945257 | E11: 1.6137721e+08 | F11: =E11/E$5 -> 0.1432935 | G11: =IF(C11="","",C11-E11) -> 2.5209269e+08 | H11: =IF(C11="","",D11-F11) -> 0.20615908
B12: Instore digital_2.0 | C12: 0 | D12: =IF(C12="","",C12/C$5) -> 0 | E12: 1.213322e+08 | F12: =E12/E$5 -> 0.10773588 | G12: =IF(C12="","",C12-E12) -> -1.213322e+08 | H12: =IF(C12="","",D12-F12) -> -0.10773588
B13: POSM | C13: 456221.13 | D13: =IF(C13="","",C13/C$5) -> 0.00038558466 | E13: 2517847.2 | F13: =E13/E$5 -> 0.0022357007 | G13: =IF(C13="","",C13-E13) -> -2061626.1 | H13: =IF(C13="","",D13-F13) -> -0.001850116
B14: Other | C14: 94811798 | D14: =IF(C14="","",C14/C$5) -> 0.080132138 | E14: 0 | F14: =E14/E$5 -> 0 | G14: =IF(C14="","",C14-E14) -> 94811798 | H14: =IF(C14="","",D14-F14) -> 0.080132138
B15: Кроссформатные пакеты | C15: 2827369.1 | D15: =IF(C15="","",C15/C$5) -> 0.0023896091 | E15: 0 | F15: =E15/E$5 -> 0 | G15: =IF(C15="","",C15-E15) -> 2827369.1 | H15: =IF(C15="","",D15-F15) -> 0.0023896091
B16: М+ и сверка со сплитом | C16: 0 | D16: =IF(C16="","",C16/C$5) -> 0 | E16: 0 | F16: =E16/E$5 -> 0 | G16: =IF(C16="","",C16-E16) -> 0 | H16: =IF(C16="","",D16-F16) -> 0
... B22: Other OPEX | C22: -9123175.3 | D22: =IF(C22="","",C22/C$5) -> -0.0077106389 | E22: -5047284.1 | F22: =E22/E$5 -> -0.0044816923 | G22: =IF(C22="","",C22-E22) -> -4075891.2 | H22: =IF(C22="","",D22-F22) -> -0.0032289467
B23: EBITDA | C23: =IF(C5="","",C5+SUM(C17:C22)) -> 1.1264105e+09 | D23: =IF(C23="","",C23/C$5) -> 0.95200899 | E23: =IF(E5="","",E5+SUM(E17:E22)) -> 6.2050465e+08 | F23: =E23/E$5 -> 0.55097174 | G23: =IF(C23="","",C23-E23) -> 5.0590589e+08 | H23: =IF(C23="","",D23-F23) -> 0.40103725

Sheet Слайд

Sheet CTRL Октябрь
B1: ACT | C1: 9+3 | E1: ACT VS 9+3
A2: P&L, RUB | B2: Oct 26 | C2: Oct 26 | E2: Oct 26
A3: APP | C3: 5.618219e+08 | E3: =IF(B3="","",B3-C3)
A4: MIP | C4: 816164.27 | E4: =IF(B4="","",B4-C4)
A5: Magnit Market | C5: 449367.47 | E5: =IF(B5="","",B5-C5)
A6: DMP+ Analitycs | C6: 5009486.8 | E6: =IF(B6="","",B6-C6)
A7: DMP+Online | C7: 91818953 | E7: =IF(B7="","",B7-C7)
A8: Instore digital | C8: 2.6290778e+08 | E8: =IF(B8="","",B8-C8)
A9: Instore digital_2.0 | C9: 47092216 | E9: =IF(B9="","",B9-C9)
A10: POSM | C10: 2669920.9 | E10: =IF(B10="","",B10-C10)
A11: Other | C11: 0 | E11: =IF(B11="","",B11-C11)
A12: Кроссформатные пакеты | C12: 0 | E12: =IF(B12="","",B12-C12)
A13: М+ и сверка со сплитом | C13: 2.7751821e+08 | E13: =IF(B13="","",B13-C13)
A14: Gross Revenue | C14: 1.250104e+09 | E14: =IF(B14="","",B14-C14)
... A16: Gross margin | C16: 1.212313e+09 | E16: =IF(B16="","",B16-C16)
A17: Gross margin % | B17: =IF(B14="","",B16/B14) | C17: =IF(C14="","",C16/C14) -> 0.96976971 | E17: =IF(B17="","",B17-C17)
A18: PEX | C18: -89694325 | E18: =IF(B18="","",B18-C18)
A19: Other PEX | C19: -5807323.1 | E19: =IF(B19="","",B19-C19)
A20: Marketing | C20: -1.0164733e+08 | E20: =IF(B20="","",B20-C20)
A21: IT | C21: -1857987.2 | E21: =IF(B21="","",B21-C21)
A22: Other OPEX | C22: -5915678.6 | E22: =IF(B22="","",B22-C22)
A23: Total OPEX | C23: -2.0492264e+08 | E23: =IF(B23="","",B23-C23)
A24: EBITDA | C24: 1.0073904e+09 | E24: =IF(B24="","",B24-C24)
A25: EBITDA, % | B25: =IF(B14="","",B24/B14) | C25: =IF(C14="","",C24/C14) -> 0.80584524 | E25: =IF(B25="","",B25-C25)
A26: Capex | C26: -31696052 | E26: =IF(B26="","",B26-C26)
A27: FCF | C27: 9.756943e+08 | E27: =IF(B27="","",B27-C27)

Sheet CTRL Сентябрь
B1: ACT | C1: 8+4 | E1: ACT VS 8+4
A2: P&L, RUB | B2: Sep 26 | C2: Sep 26 | E2: Sep 26
A3: APP | B3: 4.6752566e+08 | C3: 7.6532661e+08 | E3: =IF(B3="","",B3-C3) -> -2.9780094e+08
A4: MIP | B4: 0 | C4: 841669.4 | E4: =IF(B4="","",B4-C4) -> -841669.4
A5: Magnit Market | B5: 0 | C5: 463410.2 | E5: =IF(B5="","",B5-C5) -> -463410.2
A6: DMP+ Analitycs | B6: 2432515.4 | C6: 4861968.8 | E6: =IF(B6="","",B6-C6) -> -2429453.4
A7: DMP+Online | B7: 2.016697e+08 | C7: 69479583 | E7: =IF(B7="","",B7-C7) -> 1.3219012e+08
A8: Instore digital | B8: 4.134699e+08 | C8: 1.6137721e+08 | E8: =IF(B8="","",B8-C8) -> 2.5209269e+08
A9: Instore digital_2.0 | B9: 0 | C9: 1.213322e+08 | E9: =IF(B9="","",B9-C9) -> -1.213322e+08
A10: POSM | B10: 456221.13 | C10: 2517847.2 | E10: =IF(B10="","",B10-C10) -> -2061626.1
A11: Other | B11: 94811798 | C11: 0 | E11: =IF(B11="","",B11-C11) -> 94811798
A12: Кроссформатные пакеты | B12: 2827369.1 | C12: 0 | E12: =IF(B12="","",B12-C12) -> 2827369.1
A13: М+ и сверка со сплитом | B13: 0 | C13: 0 | E13: =IF(B13="","",B13-C13) -> 0
A14: Gross Revenue | B14: 1.1831932e+09 | C14: 1.1262005e+09 | E14: =IF(B14="","",B14-C14) -> 56992670
... A16: Gross margin | B16: 1.1822653e+09 | C16: 1.0914347e+09 | E16: =IF(B16="","",B16-C16) -> 90830618
A17: Gross margin % | B17: =IF(B14="","",B16/B14) -> 0.99921581 | C17: =IF(C14="","",C16/C14) -> 0.96913001 | E17: =IF(B17="","",B17-C17) -> 0.030085799
A18: PEX | B18: 62456406 | C18: -1.1151028e+08 | E18: =IF(B18="","",B18-C18) -> 1.7396669e+08
A19: Other PEX | B19: -211306.16 | C19: -4338633.9 | E19: =IF(B19="","",B19-C19) -> 4127327.8
A20: Marketing | B20: -105089188 | C20: -3.4875034e+08 | E20: =IF(B20="","",B20-C20) -> 2.4366115e+08
A21: IT | B21: -3887514.7 | C21: -1283507.2 | E21: =IF(B21="","",B21-C21) -> -2604007.5
A22: Other OPEX | B22: -9123175.3 | C22: -5047284.1 | E22: =IF(B22="","",B22-C22) -> -4075891.2
A23: Total OPEX | B23: -55854778 | C23: -4.7093005e+08 | E23: =IF(B23="","",B23-C23) -> 4.1507527e+08
A24: EBITDA | B24: 1.1264105e+09 | C24: 6.2050465e+08 | E24: =IF(B24="","",B24-C24) -> 5.0590589e+08
A25: EBITDA, % | B25: =IF(B14="","",B24/B14) -> 0.95200899 | C25: =IF(C14="","",C24/C14) -> 0.55097174 | E25: =IF(B25="","",B25-C25) -> 0.40103725
A26: Capex | B26: -1.8576542e+08 | C26: -2.4270971e+08 | E26: =IF(B26="","",B26-C26) -> 56944295
A27: FCF | B27: 9.4064512e+08 | C27: 3.7779493e+08 | E27: =IF(B27="","",B27-C27) -> 5.6285018e+08
